Workbook

Sheet CARTEIRA
C2: 呪術廻戦 | L2: =UPPER(DADOS!$F$1) | AH2: ="Nº M-"&DADOS!$B$1&"-"&IF(FICHA!$AB$2="","····",UPPER(LEFT(FICHA!$AB$2,4)))
L3: Carteira de registro · Documento oficial | AH3: ="Emitida "&TEXT(TODAY(),"dd.mm.yyyy")
C8: FOTO 顔 | O8: PORTADOR
O9: Coloque o nome do personagem aqui
O17: CAMINHO | Z17: TRILHA | AK17: ORIGEM
O18: =IF(OR(FICHA!D11="",FICHA!D11="Escolha seu Caminho"),"—",FICHA!D11) | Z18: =IF(OR(FICHA!N11="",FICHA!N11="Escolha sua Trilha"),"—",FICHA!N11) | AK18: =IF(FICHA!X11="","—",FICHA!X11)
O21: NÍVEL | Z21: SERVIDOR USADO | AK21: REGISTRADO POR
O22: =IF(FICHA!AH11="","—",FICHA!AH11) | AK22: Nick do jogador
O26: =IF(DADOS!$AK$32=1,"TÉCNICA MARCIAL DECLARADA",IF(DADOS!$AK$31=1,"ESTILO DECLARADO","TÉCNICA AMALDIÇOADA DECLARADA"))
AK34: SELO REGISTRADO
AH38: =IF(OR(FICHA!D11="",FICHA!D11="Escolha seu Caminho"),"—",UPPER(LEFT(FICHA!D11,3))&"-"&TEXT(FICHA!AH11,"00"))

Sheet FICHA
D2: 呪術 | H2: FICHA DE REGISTRO | AB2: =IF(OR(CARTEIRA!$O$9="",CARTEIRA!$O$9="Coloque o nome do personagem aqui"),"",CARTEIRA!$O$9)
H4: =DADOS!$F$1&" · "&IF(DADOS!$B$1=DADOS!$D$1,"v"&DADOS!$B$1&" · em dia","⚠ v"&DADOS!$B$1&" · a atual é a v"&DADOS!$D$1) | AB4: =IF(OR($D$11="",$D$11="Escolha seu Caminho"),"",$D$11&IF(OR($N$11="",$N$11="Escolha sua Trilha"),""," · "&$N$11)&" · nível "&$AH$11)
A8: CICLO MALDITO | D8: 1 | G8: PERFIL AMALDIÇOADO
AW9: SUA ORIGEM · O QUE VOCÊ ESCOLHEU
D10: CAMINHO | N10: TRILHA | X10: ORIGEM | AH10: NÍVEL | AN10: XP | AW10: ="MARCANTE · "&$D$52&IF($D$53="",""," · "&$D$53)&CHAR(10)&IF('FICHA PESSOAL'!$D$45="","(o texto é escrito na FICHA PESSOAL)",'FICHA PESSOAL'!$D$45)&IF('FICHA PESSOAL'!$D$58="","",CHAR(10)&CHAR(10)&"Talento de Categoria de Efeito 4: "&'FICHA PESSOAL'!$D$58)&CHAR(10)&CHAR(10)&"MENOR 1 · "&$S$52&IF($S$53="",""," · "&$S$53)&CHAR(10)&IF('FICHA PESSOAL'!$R$45="","(o texto é escrito na FICHA PESSOAL)",'FICHA PESSOAL'!$R$45)&CHAR(10)&CHAR(10)&"MENOR 2 · "&$AG$52&IF($AG$53="",""," · "&$AG$53)&CHAR(10)&IF('FICHA PESSOAL'!$AH$45="","(o texto é escrito na FICHA PESSOAL)",'FICHA PESSOAL'!$AH$45)&CHAR(10)&CHAR(10)&"LEGADOS DE HISTÓRIA"&CHAR(10)&IF('FICHA PESSOAL'!$D$54="","(nenhum escrito)",'FICHA PESSOAL'!$D$54)
D11: Escolha seu Caminho | N11: Escolha sua Trilha | X11: Latente | AH11: =DADOS_CONFIG!$S$2 | AN11: =DADOS!$CZ$47
Z14: Pontos Disponíveis | AK14: ="Pontos de Marco de Corpo Disponíveis - "&IF(DADOS!$AK$11>DADOS!$AK$10,DADOS!$AK$11-DADOS!$AK$10&" a mais",DADOS!$AK$10-DADOS!$AK$11&" de "&DADOS!$AK$10)
D15: 2 | G15: VALORES | Z15: =IF(DADOS!$AK$7>DADOS!$AK$6,DADOS!$AK$7-DADOS!$AK$6&" a mais",IF(DADOS!$AK$8>DADOS_CONFIG!$S$5,"Um atributo passou de "&DADOS_CONFIG!$S$5,IF(AND(DADOS!$AK$5=0,DADOS!$AK$9>DADOS_CONFIG!$S$4),"Na criação, nenhum acima de "&DADOS_CONFIG!$S$4,DADOS!$AK$6-DADOS!$AK$7&" de "&DADOS!$AK$6))) | AK15: 0 | AM15: 0 | AO15: 0 | AQ15: 0 | AS15: 0
AK16: FOR | AM16: DEX | AO16: CON | AQ16: INT | AS16: ESS
D18: FOR | L18: DES | T18: CON | AB18: INT | AJ18: ESS
D19: =IFERROR(VALUE($D$21&""),0)+IFERROR(VALUE($AK$15&""),0) | L19: =IFERROR(VALUE($L$21&""),0)+IFERROR(VALUE($AM$15&""),0) | T19: =IFERROR(VALUE($T$21&""),0)+IFERROR(VALUE($AO$15&""),0) | AB19: =IFERROR(VALUE($AB$21&""),0)+IFERROR(VALUE($AQ$15&""),0) | AJ19: =IFERROR(VALUE($AJ$21&""),0)+IFERROR(VALUE($AS$15&""),0)
D21: 0 | L21: 0 | T21: 0 | AB21: 0 | AJ21: 0
D22: Força | L22: Destreza | T22: Constituição | AB22: Inteligência | AJ22: Essência
D25: VIDA - Atual/Máxima | P25: Buff/Debuff | AF25: TEMPORÁRIO | AM25: ± PERDA &/ou GANHO
D26: =J26 | J26: =IF(DADOS_CONFIG!$E$2<>"",NA(),IF(DADOS_CONFIG!$C$2=1,DADOS_CONFIG!$D$2,IF(DADOS_CONFIG!$B$2=0,IF(DADOS_CONFIG!$S$15="Não",IFERROR((IFERROR(IF($D$11="","",(VLOOKUP($D$11,'DADOS_PROGRESSAO'!$M$2:$T$8,3,FALSE)+$T$19)+(VLOOKUP($D$11,'DADOS_PROGRESSAO'!$M$2:$T$8,4,FALSE)+$T$19)*($AH$11-1)),""))+IFERROR(VALUE($P$26&""),0),""),IF(DADOS_CONFIG!$AF$32<>"",NA(),SUM(DADOS_CONFIG!$AF$2:$AF$31)+IFERROR(VALUE('FICHA'!$P$26&""),0))),IF((IF(DADOS_CONFIG!$S$15="Não",IFERROR((IFERROR(IF($D$11="","",(VLOOKUP($D$11,'DADOS_PROGRESSAO'!$M$2:$T$8,3,FALSE)+$T$19)+(VLOOKUP($D$11,'DADOS_PROGRESSAO'!$M$2:$T$8,4,FALSE)+$T$19)*($AH$11-1)),""))+IFERROR(VALUE($P$26&""),0),""),IF(DADOS_CONFIG!$AF$32<>"",NA(),SUM(DADOS_CONFIG!$AF$2:$AF$31)+IFERROR(VALUE('FICHA'!$P$26&""),0))))="","",(IF(DADOS_CONFIG!$S$15="Não",IFERROR((IFERROR(IF($D$11="","",(VLOOKUP($D$11,'DADOS_PROGRESSAO'!$M$2:$T$8,3,FALSE)+$T$19)+(VLOOKUP($D$11,'DADOS_PROGRESSAO'!$M$2:$T$8,4,FALSE)+$T$19)*($AH$11-1)),""))+IFERROR(VALUE($P$26&""),0),""),IF(DADOS_CONFIG!$AF$32<>"",NA(),SUM(DADOS_CONFIG!$AF$2:$AF$31)+IFERROR(VALUE('FICHA'!$P$26&""),0))))+DADOS_CONFIG!$B$2)))) | P26: 0 | S26: =IFERROR(__xludf.DUMMYFUNCTION("IFERROR(SPARKLINE($D$26,{""charttype"",""bar"";""max"",$J$26;""color1"",IF(N($J$26)=0,DADOS!$CZ$51,IF($D$26/$J$26<=0.25,""#C2334D"",IF($D$26/$J$26<=0.5,""#D89B3A"",DADOS!$CZ$51)))}),"""")"),"") | AF26: 0
D29: ENERGIA - Atual/Máxima | P29: Buff/Debuff | AF29: TEMPORÁRIO | AM29: ± PERDA &/ou GANHO
D30: =J30 | J30: =IF(DADOS_CONFIG!$E$3<>"",NA(),IF(DADOS_CONFIG!$C$3=1,DADOS_CONFIG!$D$3,IF(DADOS_CONFIG!$B$3=0,IFERROR((IFERROR(IF($D$11="","",VLOOKUP($D$11,'DADOS_PROGRESSAO'!$M$2:$T$8,5,FALSE)*$AH$11),""))+IFERROR(VALUE($P$30&""),0),""),IF((IFERROR((IFERROR(IF($D$11="","",VLOOKUP($D$11,'DADOS_PROGRESSAO'!$M$2:$T$8,5,FALSE)*$AH$11),""))+IFERROR(VALUE($P$30&""),0),""))="","",(IFERROR((IFERROR(IF($D$11="","",VLOOKUP($D$11,'DADOS_PROGRESSAO'!$M$2:$T$8,5,FALSE)*$AH$11),""))+IFERROR(VALUE($P$30&""),0),""))+DADOS_CONFIG!$B$3)))) | P30: 0 | S30: =IFERROR(__xludf.DUMMYFUNCTION("IFERROR(SPARKLINE($D$30,{""charttype"",""bar"";""max"",$J$30;""color1"",IF(N($J$30)=0,DADOS!$CZ$51,IF($D$30/$J$30<=0.25,""#C2334D"",IF($D$30/$J$30<=0.5,""#D89B3A"",DADOS!$CZ$51)))}),"""")"),"") | AF30: 0
A33: FICHA DE REGISTRO | D33: INTEGRIDADE - Atual/Máxima | P33: Buff/Debuff | AF33: TEMPORÁRIO | AM33: ± PERDA &/ou GANHO
D34: =J34 | J34: =IF(DADOS_CONFIG!$E$4<>"",NA(),IF(DADOS_CONFIG!$C$4=1,DADOS_CONFIG!$D$4,IF(DADOS_CONFIG!$B$4=0,IFERROR((20+(AJ19+5)*($AH$11-1))+IFERROR(VALUE($P$34&""),0),""),IF((IFERROR((20+(AJ19+5)*($AH$11-1))+IFERROR(VALUE($P$34&""),0),""))="","",(IFERROR((20+(AJ19+5)*($AH$11-1))+IFERROR(VALUE($P$34&""),0),""))+DADOS_CONFIG!$B$4)))) | P34: 0 | S34: =IFERROR(__xludf.DUMMYFUNCTION("IFERROR(SPARKLINE($D$34,{""charttype"",""bar"";""max"",$J$34;""color1"",IF(N($J$34)=0,DADOS!$CZ$51,IF($D$34/$J$34<=0.25,""#C2334D"",IF($D$34/$J$34<=0.5,""#D89B3A"",DADOS!$CZ$51)))}),"""")"),"") | AF34: 0
D37: =IF($D$34=""," ",IF($D$34<=0,"Estágio 4 · Você não é mais você mesmo",IF($D$34<=$J$34/4,"Estágio 3 · Desvantagem em ataques e TRs",IF($D$34<=$J$34/2,"Estágio 2 · Metade do deslocamento, +1 PE por Classe",IF($D$34<=$J$34*3/4,"Estágio 1 · Desvantagem em perícias","Alma Inteira")))))
D39: SE A VIDA CHEGAR A 0 · MORRENDO · a cura que você precisa receber para levantar, e o prazo para recebê-la
D40: AGUENTAR · FICA INCONSCIENTE | O40: INSISTIR · 1ª VEZ NA CENA | Z40: INSISTIR · 2ª VEZ EM DIANTE | AK40: PRAZO ATÉ SER DERROTADO
D41: =ROUNDUP(ROUND(N('FICHA'!$J$26)*DADOS_CONFIG!$S$10,10),0) | O41: =MIN(ROUNDUP(ROUND(N('FICHA'!$J$26)*DADOS_CONFIG!$S$11,10),0),DADOS_CONFIG!$S$13*N('FICHA'!$Z$73)) | Z41: =MIN(ROUNDUP(ROUND(N('FICHA'!$J$26)*DADOS_CONFIG!$S$12,10),0),DADOS_CONFIG!$S$13*N('FICHA'!$Z$73)) | AK41: =IF(MAX(0,DADOS_CONFIG!$S$14-(N('FICHA'!$F$48)+N('FICHA'!$H$48)+N('FICHA'!$J$48)+IF(ISBLANK('FICHA'!$J$50),0,IF(IFERROR(AND(ISNUMBER('FICHA'!$J$50),'FICHA'!$J$50>=0,INT('FICHA'!$J$50)='FICHA'!$J$50),FALSE),'FICHA'!$J$50,NA()))))=0,"Derrotado na hora",MAX(0,DADOS_CONFIG!$S$14-(N('FICHA'!$F$48)+N('FICHA'!$H$48)+N('FICHA'!$J$48)+IF(ISBLANK('FICHA'!$J$50),0,IF(IFERROR(AND(ISNUMBER('FICHA'!$J$50),'FICHA'!$J$50>=0,INT('FICHA'!$J$50)='FICHA'!$J$50),FALSE),'FICHA'!$J$50,NA()))))&IF(MAX(0,DADOS_CONFIG!$S$14-(N('FICHA'!$F$48)+N('FICHA'!$H$48)+N('FICHA'!$J$48)+IF(ISBLANK('FICHA'!$J$50),0,IF(IFERROR(AND(ISNUMBER('FICHA'!$J$50),'FICHA'!$J$50>=0,INT('FICHA'!$J$50)='FICHA'!$J$50),FALSE),'FICHA'!$J$50,NA()))))=1," rodada"," rodadas"))
D42: =IF(ISBLANK('CONFIGURAÇÃO'!$F$54),"¼ da vida máxima, para cima",TEXT(DADOS_CONFIG!$S$10,"# ?/?")&" da vida máxima, para cima") | O42: =IF(AND(ISBLANK('CONFIGURAÇÃO'!$F$55),ISBLANK('CONFIGURAÇÃO'!$F$57)),IF(ROUNDUP(N(FICHA!$J$26)/3,0)>15*N(FICHA!$Z$73),"⅓ da vida máxima, no teto de 15 × Classe","⅓ da vida máxima, para cima"),TEXT(DADOS_CONFIG!$S$11,"# ?/?")&" da vida máxima, para cima"&" · teto "&DADOS_CONFIG!$S$13&" × Classe") | Z42: =IF(AND(ISBLANK('CONFIGURAÇÃO'!$F$56),ISBLANK('CONFIGURAÇÃO'!$F$57)),IF(ROUNDUP(N(FICHA!$J$26)/2,0)>15*N(FICHA!$Z$73),"½ da vida máxima, no teto de 15 × Classe","½ da vida máxima, para cima"),TEXT(DADOS_CONFIG!$S$12,"# ?/?")&" da vida máxima, para cima"&" · teto "&DADOS_CONFIG!$S$13&" × Classe") | AK42: =DADOS_CONFIG!$S$14&" rodadas, menos 1 por Sequela marcada"
D44: DESCANSO | O44: O ÚLTIMO DESCANSO
D45: Escolha o descanso
D47: SEQUELAS | O47: EXAUSTÃO | Z47: RESISTÊNCIAS | AK47: IMUNIDADES
F48: 0 | H48: 0 | J48: 0 | O48: 0
D49: ="Próxima queda: "&IF(MAX(0,DADOS_CONFIG!$S$14-(N('FICHA'!$F$48)+N('FICHA'!$H$48)+N('FICHA'!$J$48)+IF(ISBLANK('FICHA'!$J$50),0,IF(IFERROR(AND(ISNUMBER('FICHA'!$J$50),'FICHA'!$J$50>=0,INT('FICHA'!$J$50)='FICHA'!$J$50),FALSE),'FICHA'!$J$50,NA()))))=0,"Derrotado na hora",MAX(0,DADOS_CONFIG!$S$14-(N('FICHA'!$F$48)+N('FICHA'!$H$48)+N('FICHA'!$J$48)+IF(ISBLANK('FICHA'!$J$50),0,IF(IFERROR(AND(ISNUMBER('FICHA'!$J$50),'FICHA'!$J$50>=0,INT('FICHA'!$J$50)='FICHA'!$J$50),FALSE),'FICHA'!$J$50,NA()))))&IF(MAX(0,DADOS_CONFIG!$S$14-(N('FICHA'!$F$48)+N('FICHA'!$H$48)+N('FICHA'!$J$48)+IF(ISBLANK('FICHA'!$J$50),0,IF(IFERROR(AND(ISNUMBER('FICHA'!$J$50),'FICHA'!$J$50>=0,INT('FICHA'!$J$50)='FICHA'!$J$50),FALSE),'FICHA'!$J$50,NA()))))=1," rodada de janela"," rodadas de janela")) | O49: =IF(N($O$48)<=0,"Sem penalidade",IF(N($O$48)=1,"Desvantagem em perícias e ofícios",IF(N($O$48)=2,"Desv. em perícias e ofícios · até 4,5 m","Desv. em perícias, ofícios, ataques e TRs · até 4,5 m")))
D50: SEQUELAS EXTRAS | J50: 0
D51: MARCANTE | S51: MENOR 1 | AG51: MENOR 2
D52: =IF('FICHA PESSOAL'!$D$44="","—",IF('FICHA PESSOAL'!$D$44="✎ Criada com o mestre","Criada com o mestre",'FICHA PESSOAL'!$D$44)) | S52: =IF('FICHA PESSOAL'!$R$44="","—",IF('FICHA PESSOAL'!$R$44="✎ Criada com o mestre","Criada com o mestre",'FICHA PESSOAL'!$R$44)) | AG52: =IF('FICHA PESSOAL'!$AH$44="","—",IF('FICHA PESSOAL'!$AH$44="✎ Criada com o mestre","Criada com o mestre",'FICHA PESSOAL'!$AH$44))
D53: =IF('FICHA PESSOAL'!$D$44="","escolha na FICHA PESSOAL",IFERROR(VLOOKUP('FICHA PESSOAL'!$D$44,'DADOS_CUSTOM'!$AZ$2:$BE$107,5,FALSE),"criada com o mestre")) | S53: =IF('FICHA PESSOAL'!$R$44="","escolha na FICHA PESSOAL",IFERROR(VLOOKUP('FICHA PESSOAL'!$R$44,'DADOS_CUSTOM'!$AZ$2:$BE$107,5,FALSE),"criada com o mestre")) | AG53: =IF('FICHA PESSOAL'!$AH$44="","escolha na FICHA PESSOAL",IFERROR(VLOOKUP('FICHA PESSOAL'!$AH$44,'DADOS_CUSTOM'!$AZ$2:$BE$107,5,FALSE),"criada com o mestre"))
Z55: BLOQUEAR | AK55: Marco Escolhido | AO55: Refino | AQ55: Corpo | AS55: Leque
D56: 3 | G56: REGISTRO | Z56: ="2d10 + " & D59-11 | AK56: =IF(DADOS!$AK$12>DADOS!$AK$5,DADOS!$AK$12-DADOS!$AK$5&" a mais",IF(DADOS!$AK$5=0,"Escolha 1 a cada 4 Nv",DADOS!$AK$5-DADOS!$AK$12&" de "&DADOS!$AK$5&" para escolher")) | AO56: 0 | AQ56: 0 | AS56: 0
D58: DEFESA | L58: Buff/Debuff | O58: PROTEÇÃO | W58: Buff/Debuff | Z58: EQUIPAMENTO | AK58: INICIATIVA | AS58: Buff/Debuff
D59: =IF(DADOS_CONFIG!$E$5<>"",NA(),IF(DADOS_CONFIG!$C$5=1,DADOS_CONFIG!$D$5,IF(DADOS_CONFIG!$B$5=0,IF(OR(COUNTIF('DADOS_CUSTOM'!$C$2:$C$26,'FICHA PESSOAL'!$AH$64)>0,AND(DADOS!$CZ$19=1,COUNTIF('DADOS_CUSTOM'!$C$2:$C$26,'FICHA PESSOAL'!$S$64)>0)),10+MIN('FICHA'!$L$19,MIN(IFERROR(VALUE(DADOS!$CZ$29&""),9999),IF(DADOS!$CZ$19=1,IFERROR(VALUE(VLOOKUP('FICHA PESSOAL'!$S$64,'DADOS_CUSTOM'!$BM$2:$BU$125,4,FALSE)&""),9999),9999)))+'FICHA'!$O$59+IFERROR(VALUE('FICHA'!$L$59&""),0),10+IF($Z$59="",$L$19,MIN($L$19,IFERROR(VALUE(VLOOKUP($Z$59,DADOS!$AE$5:$AH$31,3,FALSE)&""),$L$19)))+$O$59+IFERROR(VALUE($L$59&""),0)),IF((IF(OR(COUNTIF('DADOS_CUSTOM'!$C$2:$C$26,'FICHA PESSOAL'!$AH$64)>0,AND(DADOS!$CZ$19=1,COUNTIF('DADOS_CUSTOM'!$C$2:$C$26,'FICHA PESSOAL'!$S$64)>0)),10+MIN('FICHA'!$L$19,MIN(IFERROR(VALUE(DADOS!$CZ$29&""),9999),IF(DADOS!$CZ$19=1,IFERROR(VALUE(VLOOKUP('FICHA PESSOAL'!$S$64,'DADOS_CUSTOM'!$BM$2:$BU$125,4,FALSE)&""),9999),9999)))+'FICHA'!$O$59+IFERROR(VALUE('FICHA'!$L$59&""),0),10+IF($Z$59="",$L$19,MIN($L$19,IFERROR(VALUE(VLOOKUP($Z$59,DADOS!$AE$5:$AH$31,3,FALSE)&""),$L$19)))+$O$59+IFERROR(VALUE($L$59&""),0)))="","",(IF(OR(COUNTIF('DADOS_CUSTOM'!$C$2:$C$26,'FICHA PESSOAL'!$AH$64)>0,AND(DADOS!$CZ$19=1,COUNTIF('DADOS_CUSTOM'!$C$2:$C$26,'FICHA PESSOAL'!$S$64)>0)),10+MIN('FICHA'!$L$19,MIN(IFERROR(VALUE(DADOS!$CZ$29&""),9999),IF(DADOS!$CZ$19=1,IFERROR(VALUE(VLOOKUP('FICHA PESSOAL'!$S$64,'DADOS_CUSTOM'!$BM$2:$BU$125,4,FALSE)&""),9999),9999)))+'FICHA'!$O$59+IFERROR(VALUE('FICHA'!$L$59&""),0),10+IF($Z$59="",$L$19,MIN($L$19,IFERROR(VALUE(VLOOKUP($Z$59,DADOS!$AE$5:$AH$31,3,FALSE)&""),$L$19)))+$O$59+IFERROR(VALUE($L$59&""),0)))+DADOS_CONFIG!$B$5)))) | L59: 0 | O59: =IF(DADOS_CONFIG!$E$6<>"",NA(),IF(DADOS_CONFIG!$C$6=1,DADOS_CONFIG!$D$6,IF(DADOS_CONFIG!$B$6=0,IF(OR(COUNTIF('DADOS_CUSTOM'!$C$2:$C$26,'FICHA PESSOAL'!$AH$64)>0,AND(DADOS!$CZ$19=1,COUNTIF('DADOS_CUSTOM'!$C$2:$C$26,'FICHA PESSOAL'!$S$64)>0)),IF(DADOS!$CZ$27=1,DADOS!$CZ$28,FLOOR(MIN(10,$O$73+MIN($O$73-1,IFERROR(VALUE($AO$56&""),0)))/3,1)+1)+IF(DADOS!$CZ$19=1,IFERROR(VLOOKUP('FICHA PESSOAL'!$S$64,'DADOS_CUSTOM'!$BM$2:$BU$125,3,FALSE),0),0)+IFERROR(VALUE($W$59&""),0),IF($Z$59="",FLOOR(MIN(10,$O$73+MIN($O$73-1,IFERROR(VALUE($AO$56&""),0)))/3,1)+1,IF(VLOOKUP($Z$59,DADOS!$AE$5:$AH$31,4,FALSE)="sim",0,FLOOR(MIN(10,$O$73+MIN($O$73-1,IFERROR(VALUE($AO$56&""),0)))/3,1)+1)+VLOOKUP($Z$59,DADOS!$AE$5:$AH$31,2,FALSE))+IFERROR(VALUE($W$59&""),0)),IF((IF(OR(COUNTIF('DADOS_CUSTOM'!$C$2:$C$26,'FICHA PESSOAL'!$AH$64)>0,AND(DADOS!$CZ$19=1,COUNTIF('DADOS_CUSTOM'!$C$2:$C$26,'FICHA PESSOAL'!$S$64)>0)),IF(DADOS!$CZ$27=1,DADOS!$CZ$28,FLOOR(MIN(10,$O$73+MIN($O$73-1,IFERROR(VALUE($AO$56&""),0)))/3,1)+1)+IF(DADOS!$CZ$19=1,IFERROR(VLOOKUP('FICHA PESSOAL'!$S$64,'DADOS_CUSTOM'!$BM$2:$BU$125,3,FALSE),0),0)+IFERROR(VALUE($W$59&""),0),IF($Z$59="",FLOOR(MIN(10,$O$73+MIN($O$73-1,IFERROR(VALUE($AO$56&""),0)))/3,1)+1,IF(VLOOKUP($Z$59,DADOS!$AE$5:$AH$31,4,FALSE)="sim",0,FLOOR(MIN(10,$O$73+MIN($O$73-1,IFERROR(VALUE($AO$56&""),0)))/3,1)+1)+VLOOKUP($Z$59,DADOS!$AE$5:$AH$31,2,FALSE))+IFERROR(VALUE($W$59&""),0)))="","",(IF(OR(COUNTIF('DADOS_CUSTOM'!$C$2:$C$26,'FICHA PESSOAL'!$AH$64)>0,AND(DADOS!$CZ$19=1,COUNTIF('DADOS_CUSTOM'!$C$2:$C$26,'FICHA PESSOAL'!$S$64)>0)),IF(DADOS!$CZ$27=1,DADOS!$CZ$28,FLOOR(MIN(10,$O$73+MIN($O$73-1,IFERROR(VALUE($AO$56&""),0)))/3,1)+1)+IF(DADOS!$CZ$19=1,IFERROR(VLOOKUP('FICHA PESSOAL'!$S$64,'DADOS_CUSTOM'!$BM$2:$BU$125,3,FALSE),0),0)+IFERROR(VALUE($W$59&""),0),IF($Z$59="",FLOOR(MIN(10,$O$73+MIN($O$73-1,IFERROR(VALUE($AO$56&""),0)))/3,1)+1,IF(VLOOKUP($Z$59,DADOS!$AE$5:$AH$31,4,FALSE)="sim",0,FLOOR(MIN(10,$O$73+MIN($O$73-1,IFERROR(VALUE($AO$56&""),0)))/3,1)+1)+VLOOKUP($Z$59,DADOS!$AE$5:$AH$31,2,FALSE))+IFERROR(VALUE($W$59&""),0)))+DADOS_CONFIG!$B$6)))) | W59: 0 | Z59: =IF(DADOS!$CZ$27=1,'FICHA PESSOAL'!$AH$64&IF(DADOS!$CZ$19=1," + "&'FICHA PESSOAL'!$S$64,""),IF(DADOS!$CZ$19=1,'FICHA PESSOAL'!$S$64,"")) | AK59: =IF(DADOS_CONFIG!$E$7<>"",NA(),IF(DADOS_CONFIG!$C$7=1,"d20 + "&(DADOS_CONFIG!$D$7),IF(DADOS_CONFIG!$B$7=0,"d20 + "&($L$19+IFERROR(VALUE($AS$59&""),0)),"d20 + "&(IF((($L$19+IFERROR(VALUE($AS$59&""),0)))="","",(($L$19+IFERROR(VALUE($AS$59&""),0)))+DADOS_CONFIG!$B$7))))) | AS59: 0
D62: CD DE FEITIÇO | L62: Buff/Debuff | O62: CONJURAÇÃO | W62: Buff/Debuff | Z62: CORPO A CORPO | AH62: Buff/Debuff | AK62: À DISTÂNCIA | AS62: Buff/Debuff
D63: =IF(DADOS_CONFIG!$E$8<>"",NA(),IF(DADOS_CONFIG!$C$8=1,DADOS_CONFIG!$D$8,IF(DADOS_CONFIG!$B$8=0,8+D67+IFS(Z67="FORÇA",$D$19, Z67="DESTREZA",$L$19, Z67="CONSTITUIÇÃO",$T$19, Z67="INTELIGÊNCIA",$AB$19, Z67="ESSÊNCIA",$AJ$19)+IFERROR(VALUE($L$63&""),0),IF((8+D67+IFS(Z67="FORÇA",$D$19, Z67="DESTREZA",$L$19, Z67="CONSTITUIÇÃO",$T$19, Z67="INTELIGÊNCIA",$AB$19, Z67="ESSÊNCIA",$AJ$19)+IFERROR(VALUE($L$63&""),0))="","",(8+D67+IFS(Z67="FORÇA",$D$19, Z67="DESTREZA",$L$19, Z67="CONSTITUIÇÃO",$T$19, Z67="INTELIGÊNCIA",$AB$19, Z67="ESSÊNCIA",$AJ$19)+IFERROR(VALUE($L$63&""),0))+DADOS_CONFIG!$B$8)))) | L63: 0 | O63: =IF(DADOS_CONFIG!$E$9<>"",NA(),IF(DADOS_CONFIG!$C$9=1,"d20 + "&(DADOS_CONFIG!$D$9),IF(DADOS_CONFIG!$B$9=0,"d20 + "&(D67+IFS(Z67="FORÇA",$D$19, Z67="DESTREZA",$L$19, Z67="CONSTITUIÇÃO",$T$19, Z67="INTELIGÊNCIA",$AB$19, Z67="ESSÊNCIA",$AJ$19)+IFERROR(VALUE($W$63&""),0)),"d20 + "&(IF(((D67+IFS(Z67="FORÇA",$D$19, Z67="DESTREZA",$L$19, Z67="CONSTITUIÇÃO",$T$19, Z67="INTELIGÊNCIA",$AB$19, Z67="ESSÊNCIA",$AJ$19)+IFERROR(VALUE($W$63&""),0)))="","",((D67+IFS(Z67="FORÇA",$D$19, Z67="DESTREZA",$L$19, Z67="CONSTITUIÇÃO",$T$19, Z67="INTELIGÊNCIA",$AB$19, Z67="ESSÊNCIA",$AJ$19)+IFERROR(VALUE($W$63&""),0)))+DADOS_CONFIG!$B$9))))) | W63: 0 | Z63: =IF(DADOS_CONFIG!$E$10<>"",NA(),IF(DADOS_CONFIG!$C$10=1,"d20 + "&(DADOS_CONFIG!$D$10),IF(DADOS_CONFIG!$B$10=0,"d20 + "&(D67+IFS(AK67="FORÇA",$D$19, AK67="DESTREZA",$L$19, AK67="CONSTITUIÇÃO",$T$19, AK67="INTELIGÊNCIA",$AB$19, AK67="ESSÊNCIA",$AJ$19)+IFERROR(VALUE($AH$63&""),0)),"d20 + "&(IF(((D67+IFS(AK67="FORÇA",$D$19, AK67="DESTREZA",$L$19, AK67="CONSTITUIÇÃO",$T$19, AK67="INTELIGÊNCIA",$AB$19, AK67="ESSÊNCIA",$AJ$19)+IFERROR(VALUE($AH$63&""),0)))="","",((D67+IFS(AK67="FORÇA",$D$19, AK67="DESTREZA",$L$19, AK67="CONSTITUIÇÃO",$T$19, AK67="INTELIGÊNCIA",$AB$19, AK67="ESSÊNCIA",$AJ$19)+IFERROR(VALUE($AH$63&""),0)))+DADOS_CONFIG!$B$10))))) | AH63: 0 | AK63: =IF(DADOS_CONFIG!$E$11<>"",NA(),IF(DADOS_CONFIG!$C$11=1,"d20 + "&(DADOS_CONFIG!$D$11),IF(DADOS_CONFIG!$B$11=0,"d20 + "&(D67+IFS(AE70="FORÇA",$D$19, AE70="DESTREZA",$L$19, AE70="CONSTITUIÇÃO",$T$19, AE70="INTELIGÊNCIA",$AB$19, AE70="ESSÊNCIA",$AJ$19)+IFERROR(VALUE($AS$63&""),0)),"d20 + "&(IF(((D67+IFS(AE70="FORÇA",$D$19, AE70="DESTREZA",$L$19, AE70="CONSTITUIÇÃO",$T$19, AE70="INTELIGÊNCIA",$AB$19, AE70="ESSÊNCIA",$AJ$19)+IFERROR(VALUE($AS$63&""),0)))="","",((D67+IFS(AE70="FORÇA",$D$19, AE70="DESTREZA",$L$19, AE70="CONSTITUIÇÃO",$T$19, AE70="INTELIGÊNCIA",$AB$19, AE70="ESSÊNCIA",$AJ$19)+IFERROR(VALUE($AS$63&""),0)))+DADOS_CONFIG!$B$11))))) | AS63: 0
D66: MAESTRIA | O66: DESLOCAMENTO | W66: Buff/Debuff | Z66: ATRIBUTO DE CONJURAÇÃO | AK66: ATRIBUTO DE ATAQUE - CORPO A CORPO
D67: =(1+COUNTIF(DADOS!$X$5:$X$7,"<="&$AH$11)) | O67: =IF(DADOS_CONFIG!$E$12<>"",NA(),IF(DADOS_CONFIG!$C$12=1,(DADOS_CONFIG!$D$12)&" m",IF(DADOS_CONFIG!$B$12=0,IF(DADOS!$CZ$46=1,0,MIN(IF(N($O$48)>=2,4.5,9999),(DADOS_CONFIG!$S$9+IFERROR(VALUE($W$67&""),0))/IF(DADOS!$CZ$45=1,2,1)))&" m",(IF((IF(DADOS!$CZ$46=1,0,MIN(IF(N($O$48)>=2,4.5,9999),(DADOS_CONFIG!$S$9+IFERROR(VALUE($W$67&""),0))/IF(DADOS!$CZ$45=1,2,1))))="","",(IF(DADOS!$CZ$46=1,0,MIN(IF(N($O$48)>=2,4.5,9999),(DADOS_CONFIG!$S$9+IFERROR(VALUE($W$67&""),0))/IF(DADOS!$CZ$45=1,2,1))))+DADOS_CONFIG!$B$12))&" m"))) | W67: 0 | Z67: ESSÊNCIA | AK67: FORÇA
AE69: ATRIBUTO DE ATAQUE - À DISTÂNCIA
D70: 4 | G70: PROGRESSÃO | AE70: DESTREZA
D72: ESPAÇOS DE FEITIÇO | O72: REFINO DE GRAÇA | Z72: CLASSE MÁXIMA | AK72: CLASSE 0
D73: =2+INT($AH$11/2)+COUNTIF(DADOS!$W$5:$W$11,"<="&$AH$11)+IFERROR(VALUE($AS$56&""),0) | O73: =(1+COUNTIF(DADOS!$W$5:$W$11,"<="&$AH$11)) | Z73: =COUNTIF(DADOS!$Y$5:$Y$11,"<="&$AH$11) | AK73: =2+COUNTIF(DADOS!$Z$5:$Z$7,"<="&$AH$11)
D76: 5 | G76: PERÍCIAS
T78: Trein | U78: Espec | AH78: Extra | AK78: TREINAMENTO EM ARMAS
D79: Trein | E79: Espec | R79: Extra | T79: 0 | U79: 0 | V79: Sobrevivência | AD79: Int | AF79: =IF(DADOS_CONFIG!$E$26<>"",NA(),IF(DADOS_CONFIG!$C$26=1,DADOS_CONFIG!$D$26,IF(DADOS_CONFIG!$B$26=0,$AB$19 + IF(U79, $D$67 + INT($D$67 / 2), IF(T79, $D$67, 0)) + AH79,IF(($AB$19 + IF(U79, $D$67 + INT($D$67 / 2), IF(T79, $D$67, 0)) + AH79)="","",($AB$19 + IF(U79, $D$67 + INT($D$67 / 2), IF(T79, $D$67, 0)) + AH79)+DADOS_CONFIG!$B$26)))) | AK79: =IF('DADOS_PROGRESSAO'!$K$7=1,IF('DADOS_PROGRESSAO'!$K$6="Todas","Treinado em Todas as Armas","Treinado em "&TEXTJOIN(", ",TRUE,'CONFIGURAÇÃO'!$AN$24:$AN$36)),IF(FICHA!$D$11="Escolha seu Caminho","—",IF(OR(FICHA!$D$11="Bastião",FICHA!$D$11="Vanguarda",FICHA!$D$11="Incursor"),"Treinado em Todas as Armas","Treinado em Arma de Fogo e Balestra")))
D80: 0 | E80: 0 | F80: Atletismo | N80: For | P80: =IF(DADOS_CONFIG!$E$14<>"",NA(),IF(DADOS_CONFIG!$C$14=1,DADOS_CONFIG!$D$14,IF(DADOS_CONFIG!$B$14=0,$D$19 + IF(E80, $D$67 + INT($D$67 / 2), IF(D80, $D$67, 0)) + R80,IF(($D$19 + IF(E80, $D$67 + INT($D$67 / 2), IF(D80, $D$67, 0)) + R80)="","",($D$19 + IF(E80, $D$67 + INT($D$67 / 2), IF(D80, $D$67, 0)) + R80)+DADOS_CONFIG!$B$14)))) | T80: 0 | U80: 0 | V80: Natureza | AD80: Int | AF80: =IF(DADOS_CONFIG!$E$27<>"",NA(),IF(DADOS_CONFIG!$C$27=1,DADOS_CONFIG!$D$27,IF(DADOS_CONFIG!$B$27=0,$AB$19 + IF(U80, $D$67 + INT($D$67 / 2), IF(T80, $D$67, 0)) + AH80,IF(($AB$19 + IF(U80, $D$67 + INT($D$67 / 2), IF(T80, $D$67, 0)) + AH80)="","",($AB$19 + IF(U80, $D$67 + INT($D$67 / 2), IF(T80, $D$67, 0)) + AH80)+DADOS_CONFIG!$B$27))))
D81: 0 | E81: 0 | F81: Acrobacia | N81: Des | P81: =IF(DADOS_CONFIG!$E$15<>"",NA(),IF(DADOS_CONFIG!$C$15=1,DADOS_CONFIG!$D$15,IF(DADOS_CONFIG!$B$15=0,$L$19 + IF(E81, $D$67 + INT($D$67 / 2), IF(D81, $D$67, 0)) + R81,IF(($L$19 + IF(E81, $D$67 + INT($D$67 / 2), IF(D81, $D$67, 0)) + R81)="","",($L$19 + IF(E81, $D$67 + INT($D$67 / 2), IF(D81, $D$67, 0)) + R81)+DADOS_CONFIG!$B$15)))) | T81: 0 | U81: 0 | V81: Lidar com Animais | AD81: Int | AF81: =IF(DADOS_CONFIG!$E$28<>"",NA(),IF(DADOS_CONFIG!$C$28=1,DADOS_CONFIG!$D$28,IF(DADOS_CONFIG!$B$28=0,$AB$19 + IF(U81, $D$67 + INT($D$67 / 2), IF(T81, $D$67, 0)) + AH81,IF(($AB$19 + IF(U81, $D$67 + INT($D$67 / 2), IF(T81, $D$67, 0)) + AH81)="","",($AB$19 + IF(U81, $D$67 + INT($D$67 / 2), IF(T81, $D$67, 0)) + AH81)+DADOS_CONFIG!$B$28)))) | AK81: Não trocou
D82: 0 | E82: 0 | F82: Furtividade | N82: Des | P82: =IF(DADOS_CONFIG!$E$16<>"",NA(),IF(DADOS_CONFIG!$C$16=1,DADOS_CONFIG!$D$16,IF(DADOS_CONFIG!$B$16=0,$L$19 + IF(E82, $D$67 + INT($D$67 / 2), IF(D82, $D$67, 0)) + R82,IF(($L$19 + IF(E82, $D$67 + INT($D$67 / 2), IF(D82, $D$67, 0)) + R82)="","",($L$19 + IF(E82, $D$67 + INT($D$67 / 2), IF(D82, $D$67, 0)) + R82)+DADOS_CONFIG!$B$16)))) | T82: 0 | U82: 0 | V82: Tecnologia | AD82: Int | AF82: =IF(DADOS_CONFIG!$E$29<>"",NA(),IF(DADOS_CONFIG!$C$29=1,DADOS_CONFIG!$D$29,IF(DADOS_CONFIG!$B$29=0,$AB$19 + IF(U82, $D$67 + INT($D$67 / 2), IF(T82, $D$67, 0)) + AH82,IF(($AB$19 + IF(U82, $D$67 + INT($D$67 / 2), IF(T82, $D$67, 0)) + AH82)="","",($AB$19 + IF(U82, $D$67 + INT($D$67 / 2), IF(T82, $D$67, 0)) + AH82)+DADOS_CONFIG!$B$29))))
D83: 0 | E83: 0 | F83: Pontaria | N83: Des | P83: =IF(DADOS_CONFIG!$E$17<>"",NA(),IF(DADOS_CONFIG!$C$17=1,DADOS_CONFIG!$D$17,IF(DADOS_CONFIG!$B$17=0,$L$19 + IF(E83, $D$67 + INT($D$67 / 2), IF(D83, $D$67, 0)) + R83,IF(($L$19 + IF(E83, $D$67 + INT($D$67 / 2), IF(D83, $D$67, 0)) + R83)="","",($L$19 + IF(E83, $D$67 + INT($D$67 / 2), IF(D83, $D$67, 0)) + R83)+DADOS_CONFIG!$B$17)))) | T83: 0 | U83: 0 | V83: Medicina | AD83: Int | AF83: =IF(DADOS_CONFIG!$E$25<>"",NA(),IF(DADOS_CONFIG!$C$25=1,DADOS_CONFIG!$D$25,IF(DADOS_CONFIG!$B$25=0,$AB$19 + IF(U83, $D$67 + INT($D$67 / 2), IF(T83, $D$67, 0)) + AH83,IF(($AB$19 + IF(U83, $D$67 + INT($D$67 / 2), IF(T83, $D$67, 0)) + AH83)="","",($AB$19 + IF(U83, $D$67 + INT($D$67 / 2), IF(T83, $D$67, 0)) + AH83)+DADOS_CONFIG!$B$25)))) | AK83: =IF(AK81="Não trocou","Anotações e Equipamentos","Treinamentos Extras")
D84: 0 | E84: 0 | F84: Prestidigitação | N84: Des | P84: =IF(DADOS_CONFIG!$E$18<>"",NA(),IF(DADOS_CONFIG!$C$18=1,DADOS_CONFIG!$D$18,IF(DADOS_CONFIG!$B$18=0,$L$19 + IF(E84, $D$67 + INT($D$67 / 2), IF(D84, $D$67, 0)) + R84,IF(($L$19 + IF(E84, $D$67 + INT($D$67 / 2), IF(D84, $D$67, 0)) + R84)="","",($L$19 + IF(E84, $D$67 + INT($D$67 / 2), IF(D84, $D$67, 0)) + R84)+DADOS_CONFIG!$B$18)))) | T84: 0 | U84: 0 | V84: Sentir Energia | AD84: Ess | AF84: =IF(DADOS_CONFIG!$E$30<>"",NA(),IF(DADOS_CONFIG!$C$30=1,DADOS_CONFIG!$D$30,IF(DADOS_CONFIG!$B$30=0,$AJ$19 + IF(U84, $D$67 + INT($D$67 / 2), IF(T84, $D$67, 0)) + AH84,IF(($AJ$19 + IF(U84, $D$67 + INT($D$67 / 2), IF(T84, $D$67, 0)) + AH84)="","",($AJ$19 + IF(U84, $D$67 + INT($D$67 / 2), IF(T84, $D$67, 0)) + AH84)+DADOS_CONFIG!$B$30))))
D85: 0 | E85: 0 | F85: Investigação | N85: Int | P85: =IF(DADOS_CONFIG!$E$19<>"",NA(),IF(DADOS_CONFIG!$C$19=1,DADOS_CONFIG!$D$19,IF(DADOS_CONFIG!$B$19=0,$AB$19 + IF(E85, $D$67 + INT($D$67 / 2), IF(D85, $D$67, 0)) + R85,IF(($AB$19 + IF(E85, $D$67 + INT($D$67 / 2), IF(D85, $D$67, 0)) + R85)="","",($AB$19 + IF(E85, $D$67 + INT($D$67 / 2), IF(D85, $D$67, 0)) + R85)+DADOS_CONFIG!$B$19)))) | T85: 0 | U85: 0 | V85: Percepção | AD85: Ess | AF85: =IF(DADOS_CONFIG!$E$31<>"",NA(),IF(DADOS_CONFIG!$C$31=1,DADOS_CONFIG!$D$31,IF(DADOS_CONFIG!$B$31=0,$AJ$19 + IF(U85, $D$67 + INT($D$67 / 2), IF(T85, $D$67, 0)) + AH85,IF(($AJ$19 + IF(U85, $D$67 + INT($D$67 / 2), IF(T85, $D$67, 0)) + AH85)="","",($AJ$19 + IF(U85, $D$67 + INT($D$67 / 2), IF(T85, $D$67, 0)) + AH85)+DADOS_CONFIG!$B$31))))
D86: 0 | E86: 0 | F86: Intuição | N86: Int | P86: =IF(DADOS_CONFIG!$E$20<>"",NA(),IF(DADOS_CONFIG!$C$20=1,DADOS_CONFIG!$D$20,IF(DADOS_CONFIG!$B$20=0,$AB$19 + IF(E86, $D$67 + INT($D$67 / 2), IF(D86, $D$67, 0)) + R86,IF(($AB$19 + IF(E86, $D$67 + INT($D$67 / 2), IF(D86, $D$67, 0)) + R86)="","",($AB$19 + IF(E86, $D$67 + INT($D$67 / 2), IF(D86, $D$67, 0)) + R86)+DADOS_CONFIG!$B$20)))) | T86: 0 | U86: 0 | V86: Persuasão | AD86: Ess | AF86: =IF(DADOS_CONFIG!$E$32<>"",NA(),IF(DADOS_CONFIG!$C$32=1,DADOS_CONFIG!$D$32,IF(DADOS_CONFIG!$B$32=0,$AJ$19 + IF(U86, $D$67 + INT($D$67 / 2), IF(T86, $D$67, 0)) + AH86,IF(($AJ$19 + IF(U86, $D$67 + INT($D$67 / 2), IF(T86, $D$67, 0)) + AH86)="","",($AJ$19 + IF(U86, $D$67 + INT($D$67 / 2), IF(T86, $D$67, 0)) + AH86)+DADOS_CONFIG!$B$32))))
D87: 0 | E87: 0 | F87: Ocultismo | N87: Int | P87: =IF(DADOS_CONFIG!$E$21<>"",NA(),IF(DADOS_CONFIG!$C$21=1,DADOS_CONFIG!$D$21,IF(DADOS_CONFIG!$B$21=0,$AB$19 + IF(E87, $D$67 + INT($D$67 / 2), IF(D87, $D$67, 0)) + R87,IF(($AB$19 + IF(E87, $D$67 + INT($D$67 / 2), IF(D87, $D$67, 0)) + R87)="","",($AB$19 + IF(E87, $D$67 + INT($D$67 / 2), IF(D87, $D$67, 0)) + R87)+DADOS_CONFIG!$B$21)))) | T87: 0 | U87: 0 | V87: Enganação | AD87: Ess | AF87: =IF(DADOS_CONFIG!$E$33<>"",NA(),IF(DADOS_CONFIG!$C$33=1,DADOS_CONFIG!$D$33,IF(DADOS_CONFIG!$B$33=0,$AJ$19 + IF(U87, $D$67 + INT($D$67 / 2), IF(T87, $D$67, 0)) + AH87,IF(($AJ$19 + IF(U87, $D$67 + INT($D$67 / 2), IF(T87, $D$67, 0)) + AH87)="","",($AJ$19 + IF(U87, $D$67 + INT($D$67 / 2), IF(T87, $D$67, 0)) + AH87)+DADOS_CONFIG!$B$33))))
D88: 0 | E88: 0 | F88: Religião | N88: Int | P88: =IF(DADOS_CONFIG!$E$22<>"",NA(),IF(DADOS_CONFIG!$C$22=1,DADOS_CONFIG!$D$22,IF(DADOS_CONFIG!$B$22=0,$AB$19 + IF(E88, $D$67 + INT($D$67 / 2), IF(D88, $D$67, 0)) + R88,IF(($AB$19 + IF(E88, $D$67 + INT($D$67 / 2), IF(D88, $D$67, 0)) + R88)="","",($AB$19 + IF(E88, $D$67 + INT($D$67 / 2), IF(D88, $D$67, 0)) + R88)+DADOS_CONFIG!$B$22)))) | T88: 0 | U88: 0 | V88: Intimidação | AD88: Ess | AF88: =IF(DADOS_CONFIG!$E$34<>"",NA(),IF(DADOS_CONFIG!$C$34=1,DADOS_CONFIG!$D$34,IF(DADOS_CONFIG!$B$34=0,$AJ$19 + IF(U88, $D$67 + INT($D$67 / 2), IF(T88, $D$67, 0)) + AH88,IF(($AJ$19 + IF(U88, $D$67 + INT($D$67 / 2), IF(T88, $D$67, 0)) + AH88)="","",($AJ$19 + IF(U88, $D$67 + INT($D$67 / 2), IF(T88, $D$67, 0)) + AH88)+DADOS_CONFIG!$B$34)))) | AK88: Perícias Disponíveis
D89: 0 | E89: 0 | F89: História | N89: Int | P89: =IF(DADOS_CONFIG!$E$23<>"",NA(),IF(DADOS_CONFIG!$C$23=1,DADOS_CONFIG!$D$23,IF(DADOS_CONFIG!$B$23=0,$AB$19 + IF(E89, $D$67 + INT($D$67 / 2), IF(D89, $D$67, 0)) + R89,IF(($AB$19 + IF(E89, $D$67 + INT($D$67 / 2), IF(D89, $D$67, 0)) + R89)="","",($AB$19 + IF(E89, $D$67 + INT($D$67 / 2), IF(D89, $D$67, 0)) + R89)+DADOS_CONFIG!$B$23)))) | T89: 0 | U89: 0 | V89: Atuação | AD89: Ess | AF89: =IF(DADOS_CONFIG!$E$35<>"",NA(),IF(DADOS_CONFIG!$C$35=1,DADOS_CONFIG!$D$35,IF(DADOS_CONFIG!$B$35=0,$AJ$19 + IF(U89, $D$67 + INT($D$67 / 2), IF(T89, $D$67, 0)) + AH89,IF(($AJ$19 + IF(U89, $D$67 + INT($D$67 / 2), IF(T89, $D$67, 0)) + AH89)="","",($AJ$19 + IF(U89, $D$67 + INT($D$67 / 2), IF(T89, $D$67, 0)) + AH89)+DADOS_CONFIG!$B$35)))) | AK89: =IF(AND(DADOS!$AK$15>0,$AH$11<10),"Especialização só no nível 10",IF(DADOS!$AK$24>0,DADOS!$AK$24&" a mais",DADOS!$AK$19+DADOS!$AK$21-DADOS!$AK$13&" de "&(DADOS!$AK$19+DADOS!$AK$21)))
D90: 0 | E90: 0 | F90: Hierarquia | N90: Int | P90: =IF(DADOS_CONFIG!$E$24<>"",NA(),IF(DADOS_CONFIG!$C$24=1,DADOS_CONFIG!$D$24,IF(DADOS_CONFIG!$B$24=0,$AB$19 + IF(E90, $D$67 + INT($D$67 / 2), IF(D90, $D$67, 0)) + R90,IF(($AB$19 + IF(E90, $D$67 + INT($D$67 / 2), IF(D90, $D$67, 0)) + R90)="","",($AB$19 + IF(E90, $D$67 + INT($D$67 / 2), IF(D90, $D$67, 0)) + R90)+DADOS_CONFIG!$B$24)))) | T90: 0 | U90: 0 | V90: Provocar | AD90: Ess | AF90: =IF(DADOS_CONFIG!$E$36<>"",NA(),IF(DADOS_CONFIG!$C$36=1,DADOS_CONFIG!$D$36,IF(DADOS_CONFIG!$B$36=0,$AJ$19 + IF(U90, $D$67 + INT($D$67 / 2), IF(T90, $D$67, 0)) + AH90,IF(($AJ$19 + IF(U90, $D$67 + INT($D$67 / 2), IF(T90, $D$67, 0)) + AH90)="","",($AJ$19 + IF(U90, $D$67 + INT($D$67 / 2), IF(T90, $D$67, 0)) + AH90)+DADOS_CONFIG!$B$36))))
D91: PERÍCIAS CUSTOM · CONFIGURAÇÃO
D92: =IF(COUNTIF('DADOS_PROGRESSAO'!$AV$2:$AV$11,"?*")=0,"","T = treino; E = especialização. Usam os mesmos limites do livro. Edite o cadastro em CONFIGURAÇÃO.")
D93: =IF(COUNTIF('DADOS_PROGRESSAO'!$AV$2:$AV$11,"?*")=0,"","T") | E93: =IF(COUNTIF('DADOS_PROGRESSAO'!$AV$2:$AV$11,"?*")=0,"","E") | F93: =IF(COUNTIF('DADOS_PROGRESSAO'!$AV$2:$AV$11,"?*")=0,"","NOME") | W93: =IF(COUNTIF('DADOS_PROGRESSAO'!$AV$2:$AV$11,"?*")=0,"","ATRIBUTO") | AD93: =IF(COUNTIF('DADOS_PROGRESSAO'!$AV$2:$AV$11,"?*")=0,"","TOTAL") | AL93: =IF(COUNTIF('DADOS_PROGRESSAO'!$AV$2:$AV$11,"?*")=0,"","BÔNUS")
D94: FALSE | E94: FALSE | F94: ='DADOS_PROGRESSAO'!$AV$2 | W94: =N439 | AD94: =R439
D95: FALSE | E95: FALSE | F95: ='DADOS_PROGRESSAO'!$AV$3 | W95: =N440 | AD95: =R440
D96: FALSE | E96: FALSE | F96: ='DADOS_PROGRESSAO'!$AV$4 | W96: =N441 | AD96: =R441
D97: FALSE | E97: FALSE | F97: ='DADOS_PROGRESSAO'!$AV$5 | W97: =N442 | AD97: =R442
D98: FALSE | E98: FALSE | F98: ='DADOS_PROGRESSAO'!$AV$6 | W98: =N443 | AD98: =R443
D99: FALSE | E99: FALSE | F99: ='DADOS_PROGRESSAO'!$AV$7 | W99: =N444 | AD99: =R444
D100: FALSE | E100: FALSE | F100: ='DADOS_PROGRESSAO'!$AV$8 | W100: =N445 | AD100: =R445
D101: FALSE | E101: FALSE | F101: ='DADOS_PROGRESSAO'!$AV$9 | W101: =N446 | AD101: =R446
D102: FALSE | E102: FALSE | F102: ='DADOS_PROGRESSAO'!$AV$10 | W102: =N447 | AD102: =R447
D103: FALSE | E103: FALSE | F103: ='DADOS_PROGRESSAO'!$AV$11 | W103: =N448 | AD103: =R448
D105: 6 | G105: OFÍCIOS E TESTES DE RESISTÊNCIA | AK105: =IF(AND(DADOS!$AK$15>0,$AH$11<10),"Especialização só no nível 10: tire a marcação",IF(DADOS!$AK$24>0,"Marcou "&DADOS!$AK$24&" a mais: tire uma perícia, um ofício ou uma especialização",IF(DADOS!$AK$25+DADOS!$AK$26+DADOS!$AK$23=0,"Tudo escolhido","Falta: "&IF(DADOS!$AK$25>0,DADOS!$AK$25&IF(DADOS!$AK$25=1," perícia"," perícias"),"")&IF(AND(DADOS!$AK$26>0,OR(DADOS!$AK$25>0)),IF(OR(DADOS!$AK$23>0),", "," e "),"")&IF(DADOS!$AK$26>0,DADOS!$AK$26&IF(DADOS!$AK$26=1," ofício"," ofícios"),"")&IF(AND(DADOS!$AK$23>0,OR(DADOS!$AK$25>0,DADOS!$AK$26>0))," e ","")&IF(DADOS!$AK$23>0,DADOS!$AK$23&IF(DADOS!$AK$23=1," escolha de Corpo"," escolhas de Corpo"),"")&IF(AND(DADOS!$AK$23>0,DADOS!$AK$25+DADOS!$AK$26=0)," (+1 perícia, +1 ofício"&IF($AH$11>=10," ou uma especialização","")&")","")&IF(AND(DADOS!$AK$17=1,DADOS!$AK$14<=0),", ou "&IF(DADOS!$AK$27>0,DADOS!$AK$27&IF(DADOS!$AK$27=1," perícia"," perícias"),"")&IF(AND(DADOS!$AK$28>0,OR(DADOS!$AK$27>0))," e ","")&IF(DADOS!$AK$28>0,DADOS!$AK$28&IF(DADOS!$AK$28=1," escolha de Corpo"," escolhas de Corpo"),"")&" sem ofício",""))))
D107: Trein | E107: Espec | O107: Extra | Q107: Trein | R107: Espec | AB107: Extra | AF107: Trein | AJ107: Extra
D108: 0 | E108: 0 | F108: Condução | K108: INTELIGÊNCIA | N108: =IF(DADOS_CONFIG!$E$37<>"",NA(),IF(DADOS_CONFIG!$C$37=1,DADOS_CONFIG!$D$37,IF(DADOS_CONFIG!$B$37=0,+IFS(K108="FORÇA",$D$19, K108="DESTREZA",$L$19, K108="CONSTITUIÇÃO",$T$19, K108="INTELIGÊNCIA",$AB$19, K108="ESSÊNCIA",$AJ$19) + IF(E108, $D$67 + INT($D$67 / 2), IF(D108, $D$67, 0)) + O108,IF((+IFS(K108="FORÇA",$D$19, K108="DESTREZA",$L$19, K108="CONSTITUIÇÃO",$T$19, K108="INTELIGÊNCIA",$AB$19, K108="ESSÊNCIA",$AJ$19) + IF(E108, $D$67 + INT($D$67 / 2), IF(D108, $D$67, 0)) + O108)="","",(+IFS(K108="FORÇA",$D$19, K108="DESTREZA",$L$19, K108="CONSTITUIÇÃO",$T$19, K108="INTELIGÊNCIA",$AB$19, K108="ESSÊNCIA",$AJ$19) + IF(E108, $D$67 + INT($D$67 / 2), IF(D108, $D$67, 0)) + O108)+DADOS_CONFIG!$B$37)))) | Q108: 0 | R108: 0 | S108: Entalhador | X108: INTELIGÊNCIA | AA108: =IF(DADOS_CONFIG!$E$43<>"",NA(),IF(DADOS_CONFIG!$C$43=1,DADOS_CONFIG!$D$43,IF(DADOS_CONFIG!$B$43=0,+IFS(X108="FORÇA",$D$19, X108="DESTREZA",$L$19, X108="CONSTITUIÇÃO",$T$19, X108="INTELIGÊNCIA",$AB$19, X108="ESSÊNCIA",$AJ$19) + IF(R108, $D$67 + INT($D$67 / 2), IF(Q108, $D$67, 0)) + AB108,IF((+IFS(X108="FORÇA",$D$19, X108="DESTREZA",$L$19, X108="CONSTITUIÇÃO",$T$19, X108="INTELIGÊNCIA",$AB$19, X108="ESSÊNCIA",$AJ$19) + IF(R108, $D$67 + INT($D$67 / 2), IF(Q108, $D$67, 0)) + AB108)="","",(+IFS(X108="FORÇA",$D$19, X108="DESTREZA",$L$19, X108="CONSTITUIÇÃO",$T$19, X108="INTELIGÊNCIA",$AB$19, X108="ESSÊNCIA",$AJ$19) + IF(R108, $D$67 + INT($D$67 / 2), IF(Q108, $D$67, 0)) + AB108)+DADOS_CONFIG!$B$43)))) | AF108: 0 | AG108: Físico | AK108: FORÇA | AP108: =IF(DADOS_CONFIG!$E$48<>"",NA(),IF(DADOS_CONFIG!$C$48=1,DADOS_CONFIG!$D$48,IF(DADOS_CONFIG!$B$48=0,+IFS(AK108="FORÇA",$D$19, AK108="DESTREZA",$L$19)+IF($AF$108=TRUE,$D$67,0)+AJ108,IF((+IFS(AK108="FORÇA",$D$19, AK108="DESTREZA",$L$19)+IF($AF$108=TRUE,$D$67,0)+AJ108)="","",(+IFS(AK108="FORÇA",$D$19, AK108="DESTREZA",$L$19)+IF($AF$108=TRUE,$D$67,0)+AJ108)+DADOS_CONFIG!$B$48))))
D109: 0 | E109: 0 | F109: Arrombamento | K109: INTELIGÊNCIA | N109: =IF(DADOS_CONFIG!$E$38<>"",NA(),IF(DADOS_CONFIG!$C$38=1,DADOS_CONFIG!$D$38,IF(DADOS_CONFIG!$B$38=0,+IFS(K109="FORÇA",$D$19, K109="DESTREZA",$L$19, K109="CONSTITUIÇÃO",$T$19, K109="INTELIGÊNCIA",$AB$19, K109="ESSÊNCIA",$AJ$19) + IF(E109, $D$67 + INT($D$67 / 2), IF(D109, $D$67, 0)) + O109,IF((+IFS(K109="FORÇA",$D$19, K109="DESTREZA",$L$19, K109="CONSTITUIÇÃO",$T$19, K109="INTELIGÊNCIA",$AB$19, K109="ESSÊNCIA",$AJ$19) + IF(E109, $D$67 + INT($D$67 / 2), IF(D109, $D$67, 0)) + O109)="","",(+IFS(K109="FORÇA",$D$19, K109="DESTREZA",$L$19, K109="CONSTITUIÇÃO",$T$19, K109="INTELIGÊNCIA",$AB$19, K109="ESSÊNCIA",$AJ$19) + IF(E109, $D$67 + INT($D$67 / 2), IF(D109, $D$67, 0)) + O109)+DADOS_CONFIG!$B$38)))) | Q109: 0 | R109: 0 | S109: Alfaiate | X109: INTELIGÊNCIA | AA109: =IF(DADOS_CONFIG!$E$44<>"",NA(),IF(DADOS_CONFIG!$C$44=1,DADOS_CONFIG!$D$44,IF(DADOS_CONFIG!$B$44=0,+IFS(X109="FORÇA",$D$19, X109="DESTREZA",$L$19, X109="CONSTITUIÇÃO",$T$19, X109="INTELIGÊNCIA",$AB$19, X109="ESSÊNCIA",$AJ$19) + IF(R109, $D$67 + INT($D$67 / 2), IF(Q109, $D$67, 0)) + AB109,IF((+IFS(X109="FORÇA",$D$19, X109="DESTREZA",$L$19, X109="CONSTITUIÇÃO",$T$19, X109="INTELIGÊNCIA",$AB$19, X109="ESSÊNCIA",$AJ$19) + IF(R109, $D$67 + INT($D$67 / 2), IF(Q109, $D$67, 0)) + AB109)="","",(+IFS(X109="FORÇA",$D$19, X109="DESTREZA",$L$19, X109="CONSTITUIÇÃO",$T$19, X109="INTELIGÊNCIA",$AB$19, X109="ESSÊNCIA",$AJ$19) + IF(R109, $D$67 + INT($D$67 / 2), IF(Q109, $D$67, 0)) + AB109)+DADOS_CONFIG!$B$44)))) | AF109: 0 | AG109: Vigor | AK109: CONSTITUIÇÃO | AP109: =IF(DADOS_CONFIG!$E$49<>"",NA(),IF(DADOS_CONFIG!$C$49=1,DADOS_CONFIG!$D$49,IF(DADOS_CONFIG!$B$49=0,$T$19+IF($AF$109=TRUE,$D$67,0)+AJ109,IF(($T$19+IF($AF$109=TRUE,$D$67,0)+AJ109)="","",($T$19+IF($AF$109=TRUE,$D$67,0)+AJ109)+DADOS_CONFIG!$B$49))))
D110: 0 | E110: 0 | F110: Herbalismo | K110: INTELIGÊNCIA | N110: =IF(DADOS_CONFIG!$E$39<>"",NA(),IF(DADOS_CONFIG!$C$39=1,DADOS_CONFIG!$D$39,IF(DADOS_CONFIG!$B$39=0,+IFS(K110="FORÇA",$D$19, K110="DESTREZA",$L$19, K110="CONSTITUIÇÃO",$T$19, K110="INTELIGÊNCIA",$AB$19, K110="ESSÊNCIA",$AJ$19) + IF(E110, $D$67 + INT($D$67 / 2), IF(D110, $D$67, 0)) + O110,IF((+IFS(K110="FORÇA",$D$19, K110="DESTREZA",$L$19, K110="CONSTITUIÇÃO",$T$19, K110="INTELIGÊNCIA",$AB$19, K110="ESSÊNCIA",$AJ$19) + IF(E110, $D$67 + INT($D$67 / 2), IF(D110, $D$67, 0)) + O110)="","",(+IFS(K110="FORÇA",$D$19, K110="DESTREZA",$L$19, K110="CONSTITUIÇÃO",$T$19, K110="INTELIGÊNCIA",$AB$19, K110="ESSÊNCIA",$AJ$19) + IF(E110, $D$67 + INT($D$67 / 2), IF(D110, $D$67, 0)) + O110)+DADOS_CONFIG!$B$39)))) | Q110: 0 | R110: 0 | S110: Culinária | X110: INTELIGÊNCIA | AA110: =IF(DADOS_CONFIG!$E$45<>"",NA(),IF(DADOS_CONFIG!$C$45=1,DADOS_CONFIG!$D$45,IF(DADOS_CONFIG!$B$45=0,+IFS(X110="FORÇA",$D$19, X110="DESTREZA",$L$19, X110="CONSTITUIÇÃO",$T$19, X110="INTELIGÊNCIA",$AB$19, X110="ESSÊNCIA",$AJ$19) + IF(R110, $D$67 + INT($D$67 / 2), IF(Q110, $D$67, 0)) + AB110,IF((+IFS(X110="FORÇA",$D$19, X110="DESTREZA",$L$19, X110="CONSTITUIÇÃO",$T$19, X110="INTELIGÊNCIA",$AB$19, X110="ESSÊNCIA",$AJ$19) + IF(R110, $D$67 + INT($D$67 / 2), IF(Q110, $D$67, 0)) + AB110)="","",(+IFS(X110="FORÇA",$D$19, X110="DESTREZA",$L$19, X110="CONSTITUIÇÃO",$T$19, X110="INTELIGÊNCIA",$AB$19, X110="ESSÊNCIA",$AJ$19) + IF(R110, $D$67 + INT($D$67 / 2), IF(Q110, $D$67, 0)) + AB110)+DADOS_CONFIG!$B$45)))) | AF110: 0 | AG110: Intelecto | AK110: INTELIGÊNCIA | AP110: =IF(DADOS_CONFIG!$E$50<>"",NA(),IF(DADOS_CONFIG!$C$50=1,DADOS_CONFIG!$D$50,IF(DADOS_CONFIG!$B$50=0,$AB$19+IF($AF$110=TRUE,$D$67,0)+AJ110,IF(($AB$19+IF($AF$110=TRUE,$D$67,0)+AJ110)="","",($AB$19+IF($AF$110=TRUE,$D$67,0)+AJ110)+DADOS_CONFIG!$B$50))))
D111: 0 | E111: 0 | F111: Forja | K111: INTELIGÊNCIA | N111: =IF(DADOS_CONFIG!$E$40<>"",NA(),IF(DADOS_CONFIG!$C$40=1,DADOS_CONFIG!$D$40,IF(DADOS_CONFIG!$B$40=0,+IFS(K111="FORÇA",$D$19, K111="DESTREZA",$L$19, K111="CONSTITUIÇÃO",$T$19, K111="INTELIGÊNCIA",$AB$19, K111="ESSÊNCIA",$AJ$19) + IF(E111, $D$67 + INT($D$67 / 2), IF(D111, $D$67, 0)) + O111,IF((+IFS(K111="FORÇA",$D$19, K111="DESTREZA",$L$19, K111="CONSTITUIÇÃO",$T$19, K111="INTELIGÊNCIA",$AB$19, K111="ESSÊNCIA",$AJ$19) + IF(E111, $D$67 + INT($D$67 / 2), IF(D111, $D$67, 0)) + O111)="","",(+IFS(K111="FORÇA",$D$19, K111="DESTREZA",$L$19, K111="CONSTITUIÇÃO",$T$19, K111="INTELIGÊNCIA",$AB$19, K111="ESSÊNCIA",$AJ$19) + IF(E111, $D$67 + INT($D$67 / 2), IF(D111, $D$67, 0)) + O111)+DADOS_CONFIG!$B$40)))) | Q111: 0 | R111: 0 | S111: Jogatina | X111: INTELIGÊNCIA | AA111: =IF(DADOS_CONFIG!$E$47<>"",NA(),IF(DADOS_CONFIG!$C$47=1,DADOS_CONFIG!$D$47,IF(DADOS_CONFIG!$B$47=0,+IFS(X111="FORÇA",$D$19, X111="DESTREZA",$L$19, X111="CONSTITUIÇÃO",$T$19, X111="INTELIGÊNCIA",$AB$19, X111="ESSÊNCIA",$AJ$19) + IF(R111, $D$67 + INT($D$67 / 2), IF(Q111, $D$67, 0)) + AB111,IF((+IFS(X111="FORÇA",$D$19, X111="DESTREZA",$L$19, X111="CONSTITUIÇÃO",$T$19, X111="INTELIGÊNCIA",$AB$19, X111="ESSÊNCIA",$AJ$19) + IF(R111, $D$67 + INT($D$67 / 2), IF(Q111, $D$67, 0)) + AB111)="","",(+IFS(X111="FORÇA",$D$19, X111="DESTREZA",$L$19, X111="CONSTITUIÇÃO",$T$19, X111="INTELIGÊNCIA",$AB$19, X111="ESSÊNCIA",$AJ$19) + IF(R111, $D$67 + INT($D$67 / 2), IF(Q111, $D$67, 0)) + AB111)+DADOS_CONFIG!$B$47)))) | AF111: 0 | AG111: Espírito | AK111: ESSÊNCIA | AP111: =IF(DADOS_CONFIG!$E$51<>"",NA(),IF(DADOS_CONFIG!$C$51=1,DADOS_CONFIG!$D$51,IF(DADOS_CONFIG!$B$51=0,$AJ$19+IF($AF$111=TRUE,$D$67,0)+AJ111,IF(($AJ$19+IF($AF$111=TRUE,$D$67,0)+AJ111)="","",($AJ$19+IF($AF$111=TRUE,$D$67,0)+AJ111)+DADOS_CONFIG!$B$51))))
D112: 0 | E112: 0 | F112: Caligrafia | K112: INTELIGÊNCIA | N112: =IF(DADOS_CONFIG!$E$41<>"",NA(),IF(DADOS_CONFIG!$C$41=1,DADOS_CONFIG!$D$41,IF(DADOS_CONFIG!$B$41=0,+IFS(K112="FORÇA",$D$19, K112="DESTREZA",$L$19, K112="CONSTITUIÇÃO",$T$19, K112="INTELIGÊNCIA",$AB$19, K112="ESSÊNCIA",$AJ$19) + IF(E112, $D$67 + INT($D$67 / 2), IF(D112, $D$67, 0)) + O112,IF((+IFS(K112="FORÇA",$D$19, K112="DESTREZA",$L$19, K112="CONSTITUIÇÃO",$T$19, K112="INTELIGÊNCIA",$AB$19, K112="ESSÊNCIA",$AJ$19) + IF(E112, $D$67 + INT($D$67 / 2), IF(D112, $D$67, 0)) + O112)="","",(+IFS(K112="FORÇA",$D$19, K112="DESTREZA",$L$19, K112="CONSTITUIÇÃO",$T$19, K112="INTELIGÊNCIA",$AB$19, K112="ESSÊNCIA",$AJ$19) + IF(E112, $D$67 + INT($D$67 / 2), IF(D112, $D$67, 0)) + O112)+DADOS_CONFIG!$B$41)))) | Q112: 0 | R112: 0 | S112: Instrumento | X112: INTELIGÊNCIA | AA112: =IF(DADOS_CONFIG!$E$46<>"",NA(),IF(DADOS_CONFIG!$C$46=1,DADOS_CONFIG!$D$46,IF(DADOS_CONFIG!$B$46=0,+IFS(X112="FORÇA",$D$19, X112="DESTREZA",$L$19, X112="CONSTITUIÇÃO",$T$19, X112="INTELIGÊNCIA",$AB$19, X112="ESSÊNCIA",$AJ$19) + IF(R112, $D$67 + INT($D$67 / 2), IF(Q112, $D$67, 0)) + AB112,IF((+IFS(X112="FORÇA",$D$19, X112="DESTREZA",$L$19, X112="CONSTITUIÇÃO",$T$19, X112="INTELIGÊNCIA",$AB$19, X112="ESSÊNCIA",$AJ$19) + IF(R112, $D$67 + INT($D$67 / 2), IF(Q112, $D$67, 0)) + AB112)="","",(+IFS(X112="FORÇA",$D$19, X112="DESTREZA",$L$19, X112="CONSTITUIÇÃO",$T$19, X112="INTELIGÊNCIA",$AB$19, X112="ESSÊNCIA",$AJ$19) + IF(R112, $D$67 + INT($D$67 / 2), IF(Q112, $D$67, 0)) + AB112)+DADOS_CONFIG!$B$46))))
D113: 0 | E113: 0 | F113: Burocracia | K113: INTELIGÊNCIA | N113: =IF(DADOS_CONFIG!$E$42<>"",NA(),IF(DADOS_CONFIG!$C$42=1,DADOS_CONFIG!$D$42,IF(DADOS_CONFIG!$B$42=0,+IFS(K113="FORÇA",$D$19, K113="DESTREZA",$L$19, K113="CONSTITUIÇÃO",$T$19, K113="INTELIGÊNCIA",$AB$19, K113="ESSÊNCIA",$AJ$19) + IF(E113, $D$67 + INT($D$67 / 2), IF(D113, $D$67, 0)) + O113,IF((+IFS(K113="FORÇA",$D$19, K113="DESTREZA",$L$19, K113="CONSTITUIÇÃO",$T$19, K113="INTELIGÊNCIA",$AB$19, K113="ESSÊNCIA",$AJ$19) + IF(E113, $D$67 + INT($D$67 / 2), IF(D113, $D$67, 0)) + O113)="","",(+IFS(K113="FORÇA",$D$19, K113="DESTREZA",$L$19, K113="CONSTITUIÇÃO",$T$19, K113="INTELIGÊNCIA",$AB$19, K113="ESSÊNCIA",$AJ$19) + IF(E113, $D$67 + INT($D$67 / 2), IF(D113, $D$67, 0)) + O113)+DADOS_CONFIG!$B$42)))) | AF113: Ofícios Disponíveis | AN113: Testes de Resistência Disponíveis
AF114: =IF(AND(DADOS!$AK$15>0,$AH$11<10),"Especialização só no nível 10",IF(DADOS!$AK$24>0,DADOS!$AK$24&" a mais",DADOS!$AK$20+DADOS!$AK$22-DADOS!$AK$14&" de "&(DADOS!$AK$20+DADOS!$AK$22))) | AN114: =IF(DADOS!$AK$29>2,DADOS!$AK$29-2&" a mais",2-DADOS!$AK$29&" de "&2)
D115: OFÍCIOS CUSTOM · CONFIGURAÇÃO
D116: =IF(COUNTIF('DADOS_PROGRESSAO'!$AW$2:$AW$11,"?*")=0,"","T = treino; E = especialização. Usam os mesmos limites do livro. Edite o cadastro em CONFIGURAÇÃO.")
D117: =IF(COUNTIF('DADOS_PROGRESSAO'!$AW$2:$AW$11,"?*")=0,"","T") | E117: =IF(COUNTIF('DADOS_PROGRESSAO'!$AW$2:$AW$11,"?*")=0,"","E") | F117: =IF(COUNTIF('DADOS_PROGRESSAO'!$AW$2:$AW$11,"?*")=0,"","NOME") | W117: =IF(COUNTIF('DADOS_PROGRESSAO'!$AW$2:$AW$11,"?*")=0,"","ATRIBUTO") | AD117: =IF(COUNTIF('DADOS_PROGRESSAO'!$AW$2:$AW$11,"?*")=0,"","TOTAL") | AL117: =IF(COUNTIF('DADOS_PROGRESSAO'!$AW$2:$AW$11,"?*")=0,"","BÔNUS")
D118: FALSE | E118: FALSE | F118: ='DADOS_PROGRESSAO'!$AW$2 | W118: =IFERROR(VLOOKUP(SUBSTITUTE(SUBSTITUTE(SUBSTITUTE(F118,"~","~~"),"*","~*"),"?","~?"),'DADOS_PROGRESSAO'!$AJ$2:$AK$22,2,FALSE),"") | AD118: =R455
D119: FALSE | E119: FALSE | F119: ='DADOS_PROGRESSAO'!$AW$3 | W119: =IFERROR(VLOOKUP(SUBSTITUTE(SUBSTITUTE(SUBSTITUTE(F119,"~","~~"),"*","~*"),"?","~?"),'DADOS_PROGRESSAO'!$AJ$2:$AK$22,2,FALSE),"") | AD119: =R456
D120: FALSE | E120: FALSE | F120: ='DADOS_PROGRESSAO'!$AW$4 | W120: =IFERROR(VLOOKUP(SUBSTITUTE(SUBSTITUTE(SUBSTITUTE(F120,"~","~~"),"*","~*"),"?","~?"),'DADOS_PROGRESSAO'!$AJ$2:$AK$22,2,FALSE),"") | AD120: =R457
D121: FALSE | E121: FALSE | F121: ='DADOS_PROGRESSAO'!$AW$5 | W121: =IFERROR(VLOOKUP(SUBSTITUTE(SUBSTITUTE(SUBSTITUTE(F121,"~","~~"),"*","~*"),"?","~?"),'DADOS_PROGRESSAO'!$AJ$2:$AK$22,2,FALSE),"") | AD121: =R458
D122: FALSE | E122: FALSE | F122: ='DADOS_PROGRESSAO'!$AW$6 | W122: =IFERROR(VLOOKUP(SUBSTITUTE(SUBSTITUTE(SUBSTITUTE(F122,"~","~~"),"*","~*"),"?","~?"),'DADOS_PROGRESSAO'!$AJ$2:$AK$22,2,FALSE),"") | AD122: =R459
D123: FALSE | E123: FALSE | F123: ='DADOS_PROGRESSAO'!$AW$7 | W123: =IFERROR(VLOOKUP(SUBSTITUTE(SUBSTITUTE(SUBSTITUTE(F123,"~","~~"),"*","~*"),"?","~?"),'DADOS_PROGRESSAO'!$AJ$2:$AK$22,2,FALSE),"") | AD123: =R460
D124: FALSE | E124: FALSE | F124: ='DADOS_PROGRESSAO'!$AW$8 | W124: =IFERROR(VLOOKUP(SUBSTITUTE(SUBSTITUTE(SUBSTITUTE(F124,"~","~~"),"*","~*"),"?","~?"),'DADOS_PROGRESSAO'!$AJ$2:$AK$22,2,FALSE),"") | AD124: =AL455
D125: FALSE | E125: FALSE | F125: ='DADOS_PROGRESSAO'!$AW$9 | W125: =IFERROR(VLOOKUP(SUBSTITUTE(SUBSTITUTE(SUBSTITUTE(F125,"~","~~"),"*","~*"),"?","~?"),'DADOS_PROGRESSAO'!$AJ$2:$AK$22,2,FALSE),"") | AD125: =AL456
D126: FALSE | E126: FALSE | F126: ='DADOS_PROGRESSAO'!$AW$10 | W126: =IFERROR(VLOOKUP(SUBSTITUTE(SUBSTITUTE(SUBSTITUTE(F126,"~","~~"),"*","~*"),"?","~?"),'DADOS_PROGRESSAO'!$AJ$2:$AK$22,2,FALSE),"") | AD126: =AL457
D127: FALSE | E127: FALSE | F127: ='DADOS_PROGRESSAO'!$AW$11 | W127: =IFERROR(VLOOKUP(SUBSTITUTE(SUBSTITUTE(SUBSTITUTE(F127,"~","~~"),"*","~*"),"?","~?"),'DADOS_PROGRESSAO'!$AJ$2:$AK$22,2,FALSE),"") | AD127: =AL458
D130: 7 | G130: HABILIDADES
D133: =DADOS_AM!$JF$2
D134: =DADOS_AM!$IX$2
D140: =DADOS_AM!$IX$3
D146: =DADOS_AM!$IX$4
D152: =DADOS_AM!$IX$5
...

Sheet FICHA AMALDIÇOADA
D2: 呪術 | E2: FICHA AMALDIÇOADA | J2: =FICHA!AB2
E4: =DADOS!$F$1&" · técnica, feitiços e aptidões" | J4: =FICHA!AB4
D7: Técnica | E7: Orçamento | F7: Feitiços | G7: Classe 0 | J7: Liberação | K7: T. Máxima | L7: Domínio | M7: Talentos | P7: Aptidões | Q7: Pactos | R7: ← Clique num nome para ir à seção
A8: CICLO MALDITO
D9: TÉCNICA
D11: NOME DA TÉCNICA | J11: TIPO DE DANO | L11: ATRIBUTO DA TÉCNICA | P11: CONJURAÇÃO | R11: CD
D12: =DADOS_AM!$KV$2 | L12: =DADOS_AM!$KV$3 | P12: =DADOS_AM!$KV$4 | R12: =DADOS_AM!$KV$5
D15: ROTA | J15: =DADOS_AM!$KV$6 | P15: =DADOS_AM!$KV$7
D16: =DADOS_AM!$KV$8 | P16: =DADOS_AM!$KV$9
D17: =DADOS_AM!$KV$10 | J17: =DADOS_AM!$KV$12 | P17: =DADOS_AM!$KV$14
D19: =DADOS_AM!$KV$11 | J19: =DADOS_AM!$KV$13 | P19: =DADOS_AM!$KV$15
D21: REGRA
D25: DESCRIÇÃO | L25: =DADOS_AM!$KV$16
L28: EXPRESSÃO DA TÉCNICA
D32: REGRA PRÓPRIA | P32: CATEGORIA | R32: ESPAÇOS
A33: FICHA AMALDIÇOADA | R33: =DADOS_AM!$KV$17
D36: ALCANCE | E36: ÁREA | F36: MIRA | G36: CONTROLE | J36: AUXILIARES | K36: CASTIGO | L36: TEMPO | M36: MARCA | P36: AMPARO | Q36: LIVRES · FECHADAS
D37: Neutra | E37: Neutra | F37: Neutra | G37: Neutra | J37: Neutra | K37: Neutra | L37: Neutra | M37: Neutra | P37: Neutra | Q37: =DADOS_AM!$KV$18
D38: FAMÍLIAS CUSTOM · CONFIGURAÇÃO
D39: =IF(COUNTIF('DADOS_CRIACAO'!$H$11:$H$20,"?*")=0,"","Escolha Livre, Neutra ou Fechada. Usa os mesmos limites e custos das Famílias do livro.")
D40: =IF(COUNTIF('DADOS_CRIACAO'!$H$11:$H$20,"?*")=0,"","FAMÍLIA") | O40: =IF(COUNTIF('DADOS_CRIACAO'!$H$11:$H$20,"?*")=0,"","ESTADO")
D41: ='DADOS_CRIACAO'!$H$11 | O41: =IF(AND(ISTEXT('DADOS_CRIACAO'!$B$2),'DADOS_CRIACAO'!$B$2<>"",TRIM('DADOS_CRIACAO'!$B$2)='DADOS_CRIACAO'!$B$2,COUNTIF('DADOS_CRIACAO'!$B$2:$B$11,SUBSTITUTE(SUBSTITUTE(SUBSTITUTE('DADOS_CRIACAO'!$B$2,"~","~~"),"*","~*"),"?","~?"))=1,COUNTIF('DADOS_CRIACAO'!$H$2:$H$10,SUBSTITUTE(SUBSTITUTE(SUBSTITUTE('DADOS_CRIACAO'!$B$2,"~","~~"),"*","~*"),"?","~?"))=0),"Neutra","")
D42: ='DADOS_CRIACAO'!$H$12 | O42: =IF(AND(ISTEXT('DADOS_CRIACAO'!$B$3),'DADOS_CRIACAO'!$B$3<>"",TRIM('DADOS_CRIACAO'!$B$3)='DADOS_CRIACAO'!$B$3,COUNTIF('DADOS_CRIACAO'!$B$2:$B$11,SUBSTITUTE(SUBSTITUTE(SUBSTITUTE('DADOS_CRIACAO'!$B$3,"~","~~"),"*","~*"),"?","~?"))=1,COUNTIF('DADOS_CRIACAO'!$H$2:$H$10,SUBSTITUTE(SUBSTITUTE(SUBSTITUTE('DADOS_CRIACAO'!$B$3,"~","~~"),"*","~*"),"?","~?"))=0),"Neutra","")
D43: ='DADOS_CRIACAO'!$H$13 | O43: =IF(AND(ISTEXT('DADOS_CRIACAO'!$B$4),'DADOS_CRIACAO'!$B$4<>"",TRIM('DADOS_CRIACAO'!$B$4)='DADOS_CRIACAO'!$B$4,COUNTIF('DADOS_CRIACAO'!$B$2:$B$11,SUBSTITUTE(SUBSTITUTE(SUBSTITUTE('DADOS_CRIACAO'!$B$4,"~","~~"),"*","~*"),"?","~?"))=1,COUNTIF('DADOS_CRIACAO'!$H$2:$H$10,SUBSTITUTE(SUBSTITUTE(SUBSTITUTE('DADOS_CRIACAO'!$B$4,"~","~~"),"*","~*"),"?","~?"))=0),"Neutra","")
D44: ='DADOS_CRIACAO'!$H$14 | O44: =IF(AND(ISTEXT('DADOS_CRIACAO'!$B$5),'DADOS_CRIACAO'!$B$5<>"",TRIM('DADOS_CRIACAO'!$B$5)='DADOS_CRIACAO'!$B$5,COUNTIF('DADOS_CRIACAO'!$B$2:$B$11,SUBSTITUTE(SUBSTITUTE(SUBSTITUTE('DADOS_CRIACAO'!$B$5,"~","~~"),"*","~*"),"?","~?"))=1,COUNTIF('DADOS_CRIACAO'!$H$2:$H$10,SUBSTITUTE(SUBSTITUTE(SUBSTITUTE('DADOS_CRIACAO'!$B$5,"~","~~"),"*","~*"),"?","~?"))=0),"Neutra","")
D45: ='DADOS_CRIACAO'!$H$15 | O45: =IF(AND(ISTEXT('DADOS_CRIACAO'!$B$6),'DADOS_CRIACAO'!$B$6<>"",TRIM('DADOS_CRIACAO'!$B$6)='DADOS_CRIACAO'!$B$6,COUNTIF('DADOS_CRIACAO'!$B$2:$B$11,SUBSTITUTE(SUBSTITUTE(SUBSTITUTE('DADOS_CRIACAO'!$B$6,"~","~~"),"*","~*"),"?","~?"))=1,COUNTIF('DADOS_CRIACAO'!$H$2:$H$10,SUBSTITUTE(SUBSTITUTE(SUBSTITUTE('DADOS_CRIACAO'!$B$6,"~","~~"),"*","~*"),"?","~?"))=0),"Neutra","")
D46: ='DADOS_CRIACAO'!$H$16 | O46: =IF(AND(ISTEXT('DADOS_CRIACAO'!$B$7),'DADOS_CRIACAO'!$B$7<>"",TRIM('DADOS_CRIACAO'!$B$7)='DADOS_CRIACAO'!$B$7,COUNTIF('DADOS_CRIACAO'!$B$2:$B$11,SUBSTITUTE(SUBSTITUTE(SUBSTITUTE('DADOS_CRIACAO'!$B$7,"~","~~"),"*","~*"),"?","~?"))=1,COUNTIF('DADOS_CRIACAO'!$H$2:$H$10,SUBSTITUTE(SUBSTITUTE(SUBSTITUTE('DADOS_CRIACAO'!$B$7,"~","~~"),"*","~*"),"?","~?"))=0),"Neutra","")
D47: ='DADOS_CRIACAO'!$H$17 | O47: =IF(AND(ISTEXT('DADOS_CRIACAO'!$B$8),'DADOS_CRIACAO'!$B$8<>"",TRIM('DADOS_CRIACAO'!$B$8)='DADOS_CRIACAO'!$B$8,COUNTIF('DADOS_CRIACAO'!$B$2:$B$11,SUBSTITUTE(SUBSTITUTE(SUBSTITUTE('DADOS_CRIACAO'!$B$8,"~","~~"),"*","~*"),"?","~?"))=1,COUNTIF('DADOS_CRIACAO'!$H$2:$H$10,SUBSTITUTE(SUBSTITUTE(SUBSTITUTE('DADOS_CRIACAO'!$B$8,"~","~~"),"*","~*"),"?","~?"))=0),"Neutra","")
D48: ='DADOS_CRIACAO'!$H$18 | O48: =IF(AND(ISTEXT('DADOS_CRIACAO'!$B$9),'DADOS_CRIACAO'!$B$9<>"",TRIM('DADOS_CRIACAO'!$B$9)='DADOS_CRIACAO'!$B$9,COUNTIF('DADOS_CRIACAO'!$B$2:$B$11,SUBSTITUTE(SUBSTITUTE(SUBSTITUTE('DADOS_CRIACAO'!$B$9,"~","~~"),"*","~*"),"?","~?"))=1,COUNTIF('DADOS_CRIACAO'!$H$2:$H$10,SUBSTITUTE(SUBSTITUTE(SUBSTITUTE('DADOS_CRIACAO'!$B$9,"~","~~"),"*","~*"),"?","~?"))=0),"Neutra","")
D49: ='DADOS_CRIACAO'!$H$19 | O49: =IF(AND(ISTEXT('DADOS_CRIACAO'!$B$10),'DADOS_CRIACAO'!$B$10<>"",TRIM('DADOS_CRIACAO'!$B$10)='DADOS_CRIACAO'!$B$10,COUNTIF('DADOS_CRIACAO'!$B$2:$B$11,SUBSTITUTE(SUBSTITUTE(SUBSTITUTE('DADOS_CRIACAO'!$B$10,"~","~~"),"*","~*"),"?","~?"))=1,COUNTIF('DADOS_CRIACAO'!$H$2:$H$10,SUBSTITUTE(SUBSTITUTE(SUBSTITUTE('DADOS_CRIACAO'!$B$10,"~","~~"),"*","~*"),"?","~?"))=0),"Neutra","")
D50: ='DADOS_CRIACAO'!$H$20 | O50: =IF(AND(ISTEXT('DADOS_CRIACAO'!$B$11),'DADOS_CRIACAO'!$B$11<>"",TRIM('DADOS_CRIACAO'!$B$11)='DADOS_CRIACAO'!$B$11,COUNTIF('DADOS_CRIACAO'!$B$2:$B$11,SUBSTITUTE(SUBSTITUTE(SUBSTITUTE('DADOS_CRIACAO'!$B$11,"~","~~"),"*","~*"),"?","~?"))=1,COUNTIF('DADOS_CRIACAO'!$H$2:$H$10,SUBSTITUTE(SUBSTITUTE(SUBSTITUTE('DADOS_CRIACAO'!$B$11,"~","~~"),"*","~*"),"?","~?"))=0),"Neutra","")
D52: ORÇAMENTO
D54: MAIOR CLASSE | F54: ESPAÇOS | J54: DO LEQUE | L54: =DADOS_AM!$KV$20 | P54: EM TALENTOS | Q54: NO DOMÍNIO | R54: EM INVOCAÇÕES | S54: LIVRES
D55: =DADOS_AM!$HM$4 | F55: =DADOS_AM!$HM$13 | J55: =DADOS_AM!$KV$19 | L55: =DADOS_AM!$HM$14 | P55: =DADOS_AM!$KV$21 | Q55: =DADOS_AM!$KV$22 | R55: =DADOS_AM!$KV$23 | S55: =DADOS_AM!$KV$24
D58: PREÇOS DA | E58: PONTOS E PE | F58: LEVE | G58: MÉDIA | J58: PESADA | K58: DEVOLUÇÃO MÁX. | L58: TETO DE DADOS | M58: MELHORIAS | P58: CLASSE 0
D59: 1 | E59: =DADOS_AM!$KV$25 | F59: =DADOS_AM!$KV$26 | G59: =DADOS_AM!$KV$27 | J59: =DADOS_AM!$KV$28 | K59: =DADOS_AM!$KV$29 | L59: =DADOS_AM!$KV$30 | M59: =DADOS_AM!$KV$31 | P59: =DADOS_AM!$KV$32
D61: =DADOS_AM!$KV$33
D64: 1 | G64: =DADOS_AM!$GP$2 | J64: 1 | M64: =DADOS_AM!$GP$3 | P64: 1 | S64: =DADOS_AM!$GP$4
D65: COMO É | J65: COMO É | P65: COMO É
D71: Projétil | E71: =DADOS_AM!$GU$2 | F71: =DADOS_AM!$GR$2 | G71: =DADOS_AM!$GT$2 | J71: Projétil | K71: =DADOS_AM!$GU$3 | L71: =DADOS_AM!$GR$3 | M71: =DADOS_AM!$GT$3 | P71: Projétil | Q71: =DADOS_AM!$GU$4 | R71: =DADOS_AM!$GR$4 | S71: =DADOS_AM!$GT$4
D72: =DADOS_AM!$GS$2 | E72: =DADOS_AM!$GZ$2 | J72: =DADOS_AM!$GS$3 | K72: =DADOS_AM!$GZ$3 | P72: =DADOS_AM!$GS$4 | Q72: =DADOS_AM!$GZ$4
D73: MELHORIAS | G73: =DADOS_AM!$HC$2 | J73: MELHORIAS | M73: =DADOS_AM!$HC$3 | P73: MELHORIAS | S73: =DADOS_AM!$HC$4
G74: =DADOS_AM!$HD$2 | M74: =DADOS_AM!$HD$3 | S74: =DADOS_AM!$HD$4
G75: =DADOS_AM!$HE$2 | M75: =DADOS_AM!$HE$3 | S75: =DADOS_AM!$HE$4
G76: =DADOS_AM!$HF$2 | M76: =DADOS_AM!$HF$3 | S76: =DADOS_AM!$HF$4
D77: RESTRIÇÕES | G77: =DADOS_AM!$HG$2 | J77: RESTRIÇÕES | M77: =DADOS_AM!$HG$3 | P77: RESTRIÇÕES | S77: =DADOS_AM!$HG$4
G78: =DADOS_AM!$HH$2 | M78: =DADOS_AM!$HH$3 | S78: =DADOS_AM!$HH$4
D79: CONTA | E79: =DADOS_AM!$HA$2 | J79: CONTA | K79: =DADOS_AM!$HA$3 | P79: CONTA | Q79: =DADOS_AM!$HA$4
D80: AMPLIAR | E80: =DADOS_AM!$HB$2 | J80: AMPLIAR | K80: =DADOS_AM!$HB$3 | P80: AMPLIAR | Q80: =DADOS_AM!$HB$4
D82: AVISOS | E82: =DADOS_AM!$GQ$2 | J82: AVISOS | K82: =DADOS_AM!$GQ$3 | P82: AVISOS | Q82: =DADOS_AM!$GQ$4
D85: 1 | G85: =DADOS_AM!$GP$5 | J85: 1 | M85: =DADOS_AM!$GP$6 | P85: 1 | S85: =DADOS_AM!$GP$7
D86: COMO É | J86: COMO É | P86: COMO É
D92: Projétil | E92: =DADOS_AM!$GU$5 | F92: =DADOS_AM!$GR$5 | G92: =DADOS_AM!$GT$5 | J92: Projétil | K92: =DADOS_AM!$GU$6 | L92: =DADOS_AM!$GR$6 | M92: =DADOS_AM!$GT$6 | P92: Projétil | Q92: =DADOS_AM!$GU$7 | R92: =DADOS_AM!$GR$7 | S92: =DADOS_AM!$GT$7
D93: =DADOS_AM!$GS$5 | E93: =DADOS_AM!$GZ$5 | J93: =DADOS_AM!$GS$6 | K93: =DADOS_AM!$GZ$6 | P93: =DADOS_AM!$GS$7 | Q93: =DADOS_AM!$GZ$7
D94: MELHORIAS | G94: =DADOS_AM!$HC$5 | J94: MELHORIAS | M94: =DADOS_AM!$HC$6 | P94: MELHORIAS | S94: =DADOS_AM!$HC$7
G95: =DADOS_AM!$HD$5 | M95: =DADOS_AM!$HD$6 | S95: =DADOS_AM!$HD$7
G96: =DADOS_AM!$HE$5 | M96: =DADOS_AM!$HE$6 | S96: =DADOS_AM!$HE$7
G97: =DADOS_AM!$HF$5 | M97: =DADOS_AM!$HF$6 | S97: =DADOS_AM!$HF$7
D98: RESTRIÇÕES | G98: =DADOS_AM!$HG$5 | J98: RESTRIÇÕES | M98: =DADOS_AM!$HG$6 | P98: RESTRIÇÕES | S98: =DADOS_AM!$HG$7
G99: =DADOS_AM!$HH$5 | M99: =DADOS_AM!$HH$6 | S99: =DADOS_AM!$HH$7
D100: CONTA | E100: =DADOS_AM!$HA$5 | J100: CONTA | K100: =DADOS_AM!$HA$6 | P100: CONTA | Q100: =DADOS_AM!$HA$7
D101: AMPLIAR | E101: =DADOS_AM!$HB$5 | J101: AMPLIAR | K101: =DADOS_AM!$HB$6 | P101: AMPLIAR | Q101: =DADOS_AM!$HB$7
D103: AVISOS | E103: =DADOS_AM!$GQ$5 | J103: AVISOS | K103: =DADOS_AM!$GQ$6 | P103: AVISOS | Q103: =DADOS_AM!$GQ$7
D106: 1 | G106: =DADOS_AM!$GP$8 | J106: 1 | M106: =DADOS_AM!$GP$9 | P106: 1 | S106: =DADOS_AM!$GP$10
D107: COMO É | J107: COMO É | P107: COMO É
D113: Projétil | E113: =DADOS_AM!$GU$8 | F113: =DADOS_AM!$GR$8 | G113: =DADOS_AM!$GT$8 | J113: Projétil | K113: =DADOS_AM!$GU$9 | L113: =DADOS_AM!$GR$9 | M113: =DADOS_AM!$GT$9 | P113: Projétil | Q113: =DADOS_AM!$GU$10 | R113: =DADOS_AM!$GR$10 | S113: =DADOS_AM!$GT$10
D114: =DADOS_AM!$GS$8 | E114: =DADOS_AM!$GZ$8 | J114: =DADOS_AM!$GS$9 | K114: =DADOS_AM!$GZ$9 | P114: =DADOS_AM!$GS$10 | Q114: =DADOS_AM!$GZ$10
D115: MELHORIAS | G115: =DADOS_AM!$HC$8 | J115: MELHORIAS | M115: =DADOS_AM!$HC$9 | P115: MELHORIAS | S115: =DADOS_AM!$HC$10
G116: =DADOS_AM!$HD$8 | M116: =DADOS_AM!$HD$9 | S116: =DADOS_AM!$HD$10
G117: =DADOS_AM!$HE$8 | M117: =DADOS_AM!$HE$9 | S117: =DADOS_AM!$HE$10
G118: =DADOS_AM!$HF$8 | M118: =DADOS_AM!$HF$9 | S118: =DADOS_AM!$HF$10
D119: RESTRIÇÕES | G119: =DADOS_AM!$HG$8 | J119: RESTRIÇÕES | M119: =DADOS_AM!$HG$9 | P119: RESTRIÇÕES | S119: =DADOS_AM!$HG$10
G120: =DADOS_AM!$HH$8 | M120: =DADOS_AM!$HH$9 | S120: =DADOS_AM!$HH$10
D121: CONTA | E121: =DADOS_AM!$HA$8 | J121: CONTA | K121: =DADOS_AM!$HA$9 | P121: CONTA | Q121: =DADOS_AM!$HA$10
D122: AMPLIAR | E122: =DADOS_AM!$HB$8 | J122: AMPLIAR | K122: =DADOS_AM!$HB$9 | P122: AMPLIAR | Q122: =DADOS_AM!$HB$10
D124: AVISOS | E124: =DADOS_AM!$GQ$8 | J124: AVISOS | K124: =DADOS_AM!$GQ$9 | P124: AVISOS | Q124: =DADOS_AM!$GQ$10
D127: 1 | G127: =DADOS_AM!$GP$11 | J127: 1 | M127: =DADOS_AM!$GP$12 | P127: 1 | S127: =DADOS_AM!$GP$13
D128: COMO É | J128: COMO É | P128: COMO É
D134: Projétil | E134: =DADOS_AM!$GU$11 | F134: =DADOS_AM!$GR$11 | G134: =DADOS_AM!$GT$11 | J134: Projétil | K134: =DADOS_AM!$GU$12 | L134: =DADOS_AM!$GR$12 | M134: =DADOS_AM!$GT$12 | P134: Projétil | Q134: =DADOS_AM!$GU$13 | R134: =DADOS_AM!$GR$13 | S134: =DADOS_AM!$GT$13
D135: =DADOS_AM!$GS$11 | E135: =DADOS_AM!$GZ$11 | J135: =DADOS_AM!$GS$12 | K135: =DADOS_AM!$GZ$12 | P135: =DADOS_AM!$GS$13 | Q135: =DADOS_AM!$GZ$13
D136: MELHORIAS | G136: =DADOS_AM!$HC$11 | J136: MELHORIAS | M136: =DADOS_AM!$HC$12 | P136: MELHORIAS | S136: =DADOS_AM!$HC$13
G137: =DADOS_AM!$HD$11 | M137: =DADOS_AM!$HD$12 | S137: =DADOS_AM!$HD$13
G138: =DADOS_AM!$HE$11 | M138: =DADOS_AM!$HE$12 | S138: =DADOS_AM!$HE$13
G139: =DADOS_AM!$HF$11 | M139: =DADOS_AM!$HF$12 | S139: =DADOS_AM!$HF$13
D140: RESTRIÇÕES | G140: =DADOS_AM!$HG$11 | J140: RESTRIÇÕES | M140: =DADOS_AM!$HG$12 | P140: RESTRIÇÕES | S140: =DADOS_AM!$HG$13
G141: =DADOS_AM!$HH$11 | M141: =DADOS_AM!$HH$12 | S141: =DADOS_AM!$HH$13
D142: CONTA | E142: =DADOS_AM!$HA$11 | J142: CONTA | K142: =DADOS_AM!$HA$12 | P142: CONTA | Q142: =DADOS_AM!$HA$13
D143: AMPLIAR | E143: =DADOS_AM!$HB$11 | J143: AMPLIAR | K143: =DADOS_AM!$HB$12 | P143: AMPLIAR | Q143: =DADOS_AM!$HB$13
D145: AVISOS | E145: =DADOS_AM!$GQ$11 | J145: AVISOS | K145: =DADOS_AM!$GQ$12 | P145: AVISOS | Q145: =DADOS_AM!$GQ$13
D148: =DADOS_AM!$KV$34
D150: 1 | G150: =DADOS_AM!$GP$14 | J150: 1 | M150: =DADOS_AM!$GP$15 | P150: 1 | S150: =DADOS_AM!$GP$16
D151: COMO É | J151: COMO É | P151: COMO É
D157: Projétil | E157: =DADOS_AM!$GU$14 | F157: =DADOS_AM!$GR$14 | G157: =DADOS_AM!$GT$14 | J157: Projétil | K157: =DADOS_AM!$GU$15 | L157: =DADOS_AM!$GR$15 | M157: =DADOS_AM!$GT$15 | P157: Projétil | Q157: =DADOS_AM!$GU$16 | R157: =DADOS_AM!$GR$16 | S157: =DADOS_AM!$GT$16
D158: =DADOS_AM!$GS$14 | E158: =DADOS_AM!$GZ$14 | J158: =DADOS_AM!$GS$15 | K158: =DADOS_AM!$GZ$15 | P158: =DADOS_AM!$GS$16 | Q158: =DADOS_AM!$GZ$16
D159: MELHORIAS | G159: =DADOS_AM!$HC$14 | J159: MELHORIAS | M159: =DADOS_AM!$HC$15 | P159: MELHORIAS | S159: =DADOS_AM!$HC$16
G160: =DADOS_AM!$HD$14 | M160: =DADOS_AM!$HD$15 | S160: =DADOS_AM!$HD$16
G161: =DADOS_AM!$HE$14 | M161: =DADOS_AM!$HE$15 | S161: =DADOS_AM!$HE$16
G162: =DADOS_AM!$HF$14 | M162: =DADOS_AM!$HF$15 | S162: =DADOS_AM!$HF$16
D163: RESTRIÇÕES | G163: =DADOS_AM!$HG$14 | J163: RESTRIÇÕES | M163: =DADOS_AM!$HG$15 | P163: RESTRIÇÕES | S163: =DADOS_AM!$HG$16
G164: =DADOS_AM!$HH$14 | M164: =DADOS_AM!$HH$15 | S164: =DADOS_AM!$HH$16
...

Sheet INVOCAÇÕES
D2: 呪術 | E2: INVOCAÇÕES | O2: =FICHA!AB2
E4: =DADOS!$F$1&" · as entidades, a montagem e a mesa" | O4: =FICHA!AB4
A8: CICLO MALDITO
D9: O CONJUNTO | H9: 1 | I9: 1 | J9: =DADOS_INVOC!$HG$2 | AA9: 7 | AB9: 7 | AC9: =DADOS_INVOC!$HG$8
H11: =DADOS_INVOC!$HH$2 | AA11: =DADOS_INVOC!$HH$8
D12: SEU NÍVEL | E12: MAESTRIA | F12: TRILHA | I12: NOME | O12: NÍVEL | P12: CLASSE | Q12: MAESTRIA | R12: ENTRADA | S12: RETORNO | U12: VIDA ATUAL | V12: VIDA MÁXIMA | W12: TEMPORÁRIA | X12: ± PERDA / GANHO | Y12: =DADOS_INVOC!$IB$2 | AB12: NOME | AH12: NÍVEL | AI12: CLASSE | AJ12: MAESTRIA | AK12: ENTRADA | AL12: RETORNO | AN12: VIDA ATUAL | AO12: VIDA MÁXIMA | AP12: TEMPORÁRIA | AQ12: ± PERDA / GANHO | AR12: =DADOS_INVOC!$IB$8
D13: =DADOS_INVOC!$DB$2 | E13: =DADOS_INVOC!$QU$2 | F13: =DADOS_INVOC!$QU$3 | O13: =DADOS_INVOC!$FO$2 | P13: =DADOS_INVOC!$FP$2 | Q13: =DADOS_INVOC!$HI$2 | R13: =DADOS_INVOC!$HJ$2 | S13: =DADOS_INVOC!$HK$2 | U13: =DADOS_INVOC!$GG$2 | V13: =DADOS_INVOC!$GF$2 | AH13: =DADOS_INVOC!$FO$8 | AI13: =DADOS_INVOC!$FP$8 | AJ13: =DADOS_INVOC!$HI$8 | AK13: =DADOS_INVOC!$HJ$8 | AL13: =DADOS_INVOC!$HK$8 | AN13: =DADOS_INVOC!$GG$8 | AO13: =DADOS_INVOC!$GF$8
I15: FOTO 式神 | U15: =IFERROR(SPARKLINE(DADOS_INVOC!$GH$2,{"charttype","bar";"max",MAX(1,DADOS_INVOC!$GF$2);"color1",DADOS_INVOC!$DB$12}),"") | AB15: FOTO 式神 | AN15: =IFERROR(SPARKLINE(DADOS_INVOC!$GH$8,{"charttype","bar";"max",MAX(1,DADOS_INVOC!$GF$8);"color1",DADOS_INVOC!$DB$12}),"")
D16: DEFESA USA | E16: ATIVAS, NO MÁXIMO | F16: CORPOS MANTIDOS | O16: =DADOS_INVOC!$HL$2 | AH16: =DADOS_INVOC!$HL$8
D17: Essência | E17: =DADOS_INVOC!$DB$8 | F17: =DADOS_INVOC!$DB$9 | O17: FOR | P17: DES | Q17: CON | R17: INT | S17: ESS | U17: ALMA | V17: INTEGRIDADE ATUAL | W17: INTEGRIDADE MÁXIMA | X17: ESTÁGIO | AH17: FOR | AI17: DES | AJ17: CON | AK17: INT | AL17: ESS | AN17: ALMA | AO17: INTEGRIDADE ATUAL | AP17: INTEGRIDADE MÁXIMA | AQ17: ESTÁGIO
O18: =DADOS_INVOC!$FR$2 | P18: =DADOS_INVOC!$FS$2 | Q18: =DADOS_INVOC!$FT$2 | R18: =DADOS_INVOC!$FU$2 | S18: =DADOS_INVOC!$FV$2 | U18: Com alma | V18: =DADOS_INVOC!$GJ$2 | W18: =DADOS_INVOC!$GL$2 | X18: =DADOS_INVOC!$GM$2 | AH18: =DADOS_INVOC!$FR$8 | AI18: =DADOS_INVOC!$FS$8 | AJ18: =DADOS_INVOC!$FT$8 | AK18: =DADOS_INVOC!$FU$8 | AL18: =DADOS_INVOC!$FV$8 | AN18: Com alma | AO18: =DADOS_INVOC!$GJ$8 | AP18: =DADOS_INVOC!$GL$8 | AQ18: =DADOS_INVOC!$GM$8
D20: =DADOS_INVOC!$QU$4 | O20: 0 | P20: 0 | Q20: 0 | R20: 0 | S20: 0 | AH20: 0 | AI20: 0 | AJ20: 0 | AK20: 0 | AL20: 0
D21: =DADOS_INVOC!$JK$2 | O21: 0 | P21: 0 | Q21: 0 | R21: 0 | S21: 0 | U21: CONDIÇÕES E USOS GASTOS | AH21: 0 | AI21: 0 | AJ21: 0 | AK21: 0 | AL21: 0 | AN21: CONDIÇÕES E USOS GASTOS
D22: =DADOS_INVOC!$JK$3
D23: =DADOS_INVOC!$JK$4 | O23: ATAQUE | P23: CD | Q23: DEFESA | R23: VIDA MÁXIMA | S23: DESLOCAMENTO | AH23: ATAQUE | AI23: CD | AJ23: DEFESA | AK23: VIDA MÁXIMA | AL23: DESLOCAMENTO
D24: =DADOS_INVOC!$JK$5 | O24: =DADOS_INVOC!$HM$2 | P24: =DADOS_INVOC!$HN$2 | Q24: =DADOS_INVOC!$GD$2 | R24: =DADOS_INVOC!$GF$2 | S24: =DADOS_INVOC!$HO$2 | AH24: =DADOS_INVOC!$HM$8 | AI24: =DADOS_INVOC!$HN$8 | AJ24: =DADOS_INVOC!$GD$8 | AK24: =DADOS_INVOC!$GF$8 | AL24: =DADOS_INVOC!$HO$8
D25: =DADOS_INVOC!$JK$6
D26: =DADOS_INVOC!$JK$7 | O26: 0 | P26: 0 | Q26: 0 | R26: 0 | S26: 0 | U26: ANOTAÇÕES | AH26: 0 | AI26: 0 | AJ26: 0 | AK26: 0 | AL26: 0 | AN26: ANOTAÇÕES
D27: =DADOS_INVOC!$JK$8
D28: =DADOS_INVOC!$JK$9 | O28: FÍSICO | P28: VIGOR | Q28: INTELECTO | R28: ESPÍRITO | S28: TR TREINADO | AH28: FÍSICO | AI28: VIGOR | AJ28: INTELECTO | AK28: ESPÍRITO | AL28: TR TREINADO
D29: =DADOS_INVOC!$JK$10 | O29: =DADOS_INVOC!$HP$2 | P29: =DADOS_INVOC!$HQ$2 | Q29: =DADOS_INVOC!$HR$2 | R29: =DADOS_INVOC!$HS$2 | AH29: =DADOS_INVOC!$HP$8 | AI29: =DADOS_INVOC!$HQ$8 | AJ29: =DADOS_INVOC!$HR$8 | AK29: =DADOS_INVOC!$HS$8
D30: =DADOS_INVOC!$JK$11
D31: =DADOS_INVOC!$JK$12 | O31: 0 | P31: 0 | Q31: 0 | R31: 0 | AH31: 0 | AI31: 0 | AJ31: 0 | AK31: 0
D32: =DADOS_INVOC!$JK$13 | U32: =DADOS_INVOC!$IC$2 | Y32: VOL. | AN32: =DADOS_INVOC!$IC$8 | AR32: VOL.
A33: INVOCAÇÕES | O33: ATRIBUTO DE ACERTO | R33: FÍSICO USA | U33: MÃO 1 | AH33: ATRIBUTO DE ACERTO | AK33: FÍSICO USA | AN33: MÃO 1
R34: Força | U34: MÃO 2 | AK34: Força | AN34: MÃO 2
U35: VESTE | AN35: VESTE
U36: GUARDADO · SÓ COM A CARACTERÍSTICA DE TRANSPORTE | Y36: VOL. | AN36: GUARDADO · SÓ COM A CARACTERÍSTICA DE TRANSPORTE | AR36: VOL.
O37: =DADOS_INVOC!$HT$2 | AH37: =DADOS_INVOC!$HT$8
R38: =DADOS_INVOC!$HU$2 | AK38: =DADOS_INVOC!$HU$8
R39: =DADOS_INVOC!$HV$2 | AK39: =DADOS_INVOC!$HV$8
R40: =DADOS_INVOC!$HW$2 | AK40: =DADOS_INVOC!$HW$8
R41: =DADOS_INVOC!$HX$2 | AK41: =DADOS_INVOC!$HX$8
I42: TIPO | L42: OFÍCIO COMPATÍVEL | R42: =DADOS_INVOC!$HY$2 | AB42: TIPO | AE42: OFÍCIO COMPATÍVEL | AK42: =DADOS_INVOC!$HY$8
I43: Shikigami de técnica | R43: =DADOS_INVOC!$HZ$2 | AB43: Shikigami de técnica | AK43: =DADOS_INVOC!$HZ$8
R44: =DADOS_INVOC!$IA$2 | U44: CORPO, SENTIDOS E COMUNICAÇÃO | AK44: =DADOS_INVOC!$IA$8 | AN44: CORPO, SENTIDOS E COMUNICAÇÃO
I46: AQUISIÇÃO | K46: OBTIDA NO NÍVEL | L46: TALISMÃ | O46: =DADOS_INVOC!$ID$2 | AB46: AQUISIÇÃO | AD46: OBTIDA NO NÍVEL | AE46: TALISMÃ | AH46: =DADOS_INVOC!$ID$8
I47: Espaço conhecido | L47: Sem carga | O47: =IF(DADOS_INVOC!$RA$2>=1,"LIVRE","ABERTA") | P47: =IF(DADOS_INVOC!$RA$2>=2,"LIVRE","ABERTA") | Q47: =IF(DADOS_INVOC!$RA$2>=7,"LIVRE","ABERTA") | R47: =IF(DADOS_INVOC!$RA$2>=8,"LIVRE","ABERTA") | S47: =IF(DADOS_INVOC!$RA$2>=9,"LIVRE","ABERTA") | AB47: Espaço conhecido | AE47: Sem carga | AH47: =IF(DADOS_INVOC!$RA$8>=1,"LIVRE","ABERTA") | AI47: =IF(DADOS_INVOC!$RA$8>=2,"LIVRE","ABERTA") | AJ47: =IF(DADOS_INVOC!$RA$8>=7,"LIVRE","ABERTA") | AK47: =IF(DADOS_INVOC!$RA$8>=8,"LIVRE","ABERTA") | AL47: =IF(DADOS_INVOC!$RA$8>=9,"LIVRE","ABERTA")
O49: =IF(DADOS_INVOC!$RA$2>=3,"LIVRE 6","FAMÍLIA 6") | P49: =IF(DADOS_INVOC!$RA$2>=4,"LIVRE 7","FAMÍLIA 7") | Q49: =IF(DADOS_INVOC!$RA$2>=5,"LIVRE 8","FAMÍLIA 8") | R49: =IF(DADOS_INVOC!$RA$2>=6,"LIVRE 9","FAMÍLIA 9") | AH49: =IF(DADOS_INVOC!$RA$8>=3,"LIVRE 6","FAMÍLIA 6") | AI49: =IF(DADOS_INVOC!$RA$8>=4,"LIVRE 7","FAMÍLIA 7") | AJ49: =IF(DADOS_INVOC!$RA$8>=5,"LIVRE 8","FAMÍLIA 8") | AK49: =IF(DADOS_INVOC!$RA$8>=6,"LIVRE 9","FAMÍLIA 9")
I50: AUTONOMIA | K50: Autônoma | AB50: AUTONOMIA | AD50: Autônoma
O51: FAMÍLIAS CUSTOM · CONFIGURAÇÃO | AH51: FAMÍLIAS CUSTOM · CONFIGURAÇÃO
O52: =IF(COUNTIF('DADOS_CRIACAO'!$H$11:$H$20,"?*")=0,"","Livre conta como aberta. As escolhas usam as vagas e os limites desta entidade.") | AH52: =IF(COUNTIF('DADOS_CRIACAO'!$H$11:$H$20,"?*")=0,"","Livre conta como aberta. As escolhas usam as vagas e os limites desta entidade.")
O53: =IF(COUNTIF('DADOS_CRIACAO'!$H$11:$H$20,"?*")=0,"","FAMÍLIA") | R53: =IF(COUNTIF('DADOS_CRIACAO'!$H$11:$H$20,"?*")=0,"","ESTADO") | AH53: =IF(COUNTIF('DADOS_CRIACAO'!$H$11:$H$20,"?*")=0,"","FAMÍLIA") | AK53: =IF(COUNTIF('DADOS_CRIACAO'!$H$11:$H$20,"?*")=0,"","ESTADO")
O54: ='DADOS_CRIACAO'!$H$11 | R54: =IF(O54="","",IFS(O48=O54,IF('DADOS_INVOC'!$RA$2>=1,"Livre","Aberta"),P48=O54,IF('DADOS_INVOC'!$RA$2>=2,"Livre","Aberta"),Q48=O54,IF('DADOS_INVOC'!$RA$2>=7,"Livre","Aberta"),R48=O54,IF('DADOS_INVOC'!$RA$2>=8,"Livre","Aberta"),S48=O54,IF('DADOS_INVOC'!$RA$2>=9,"Livre","Aberta"),O50=O54,IF('DADOS_INVOC'!$RA$2>=3,"Livre","Aberta"),P50=O54,IF('DADOS_INVOC'!$RA$2>=4,"Livre","Aberta"),Q50=O54,IF('DADOS_INVOC'!$RA$2>=5,"Livre","Aberta"),R50=O54,IF('DADOS_INVOC'!$RA$2>=6,"Livre","Aberta"),TRUE,"Não escolhida")) | AH54: ='DADOS_CRIACAO'!$H$11 | AK54: =IF(AH54="","",IFS(AH48=AH54,IF('DADOS_INVOC'!$RA$8>=1,"Livre","Aberta"),AI48=AH54,IF('DADOS_INVOC'!$RA$8>=2,"Livre","Aberta"),AJ48=AH54,IF('DADOS_INVOC'!$RA$8>=7,"Livre","Aberta"),AK48=AH54,IF('DADOS_INVOC'!$RA$8>=8,"Livre","Aberta"),AL48=AH54,IF('DADOS_INVOC'!$RA$8>=9,"Livre","Aberta"),AH50=AH54,IF('DADOS_INVOC'!$RA$8>=3,"Livre","Aberta"),AI50=AH54,IF('DADOS_INVOC'!$RA$8>=4,"Livre","Aberta"),AJ50=AH54,IF('DADOS_INVOC'!$RA$8>=5,"Livre","Aberta"),AK50=AH54,IF('DADOS_INVOC'!$RA$8>=6,"Livre","Aberta"),TRUE,"Não escolhida"))
O55: ='DADOS_CRIACAO'!$H$12 | R55: =IF(O55="","",IFS(O48=O55,IF('DADOS_INVOC'!$RA$2>=1,"Livre","Aberta"),P48=O55,IF('DADOS_INVOC'!$RA$2>=2,"Livre","Aberta"),Q48=O55,IF('DADOS_INVOC'!$RA$2>=7,"Livre","Aberta"),R48=O55,IF('DADOS_INVOC'!$RA$2>=8,"Livre","Aberta"),S48=O55,IF('DADOS_INVOC'!$RA$2>=9,"Livre","Aberta"),O50=O55,IF('DADOS_INVOC'!$RA$2>=3,"Livre","Aberta"),P50=O55,IF('DADOS_INVOC'!$RA$2>=4,"Livre","Aberta"),Q50=O55,IF('DADOS_INVOC'!$RA$2>=5,"Livre","Aberta"),R50=O55,IF('DADOS_INVOC'!$RA$2>=6,"Livre","Aberta"),TRUE,"Não escolhida")) | AH55: ='DADOS_CRIACAO'!$H$12 | AK55: =IF(AH55="","",IFS(AH48=AH55,IF('DADOS_INVOC'!$RA$8>=1,"Livre","Aberta"),AI48=AH55,IF('DADOS_INVOC'!$RA$8>=2,"Livre","Aberta"),AJ48=AH55,IF('DADOS_INVOC'!$RA$8>=7,"Livre","Aberta"),AK48=AH55,IF('DADOS_INVOC'!$RA$8>=8,"Livre","Aberta"),AL48=AH55,IF('DADOS_INVOC'!$RA$8>=9,"Livre","Aberta"),AH50=AH55,IF('DADOS_INVOC'!$RA$8>=3,"Livre","Aberta"),AI50=AH55,IF('DADOS_INVOC'!$RA$8>=4,"Livre","Aberta"),AJ50=AH55,IF('DADOS_INVOC'!$RA$8>=5,"Livre","Aberta"),AK50=AH55,IF('DADOS_INVOC'!$RA$8>=6,"Livre","Aberta"),TRUE,"Não escolhida"))
O56: ='DADOS_CRIACAO'!$H$13 | R56: =IF(O56="","",IFS(O48=O56,IF('DADOS_INVOC'!$RA$2>=1,"Livre","Aberta"),P48=O56,IF('DADOS_INVOC'!$RA$2>=2,"Livre","Aberta"),Q48=O56,IF('DADOS_INVOC'!$RA$2>=7,"Livre","Aberta"),R48=O56,IF('DADOS_INVOC'!$RA$2>=8,"Livre","Aberta"),S48=O56,IF('DADOS_INVOC'!$RA$2>=9,"Livre","Aberta"),O50=O56,IF('DADOS_INVOC'!$RA$2>=3,"Livre","Aberta"),P50=O56,IF('DADOS_INVOC'!$RA$2>=4,"Livre","Aberta"),Q50=O56,IF('DADOS_INVOC'!$RA$2>=5,"Livre","Aberta"),R50=O56,IF('DADOS_INVOC'!$RA$2>=6,"Livre","Aberta"),TRUE,"Não escolhida")) | AH56: ='DADOS_CRIACAO'!$H$13 | AK56: =IF(AH56="","",IFS(AH48=AH56,IF('DADOS_INVOC'!$RA$8>=1,"Livre","Aberta"),AI48=AH56,IF('DADOS_INVOC'!$RA$8>=2,"Livre","Aberta"),AJ48=AH56,IF('DADOS_INVOC'!$RA$8>=7,"Livre","Aberta"),AK48=AH56,IF('DADOS_INVOC'!$RA$8>=8,"Livre","Aberta"),AL48=AH56,IF('DADOS_INVOC'!$RA$8>=9,"Livre","Aberta"),AH50=AH56,IF('DADOS_INVOC'!$RA$8>=3,"Livre","Aberta"),AI50=AH56,IF('DADOS_INVOC'!$RA$8>=4,"Livre","Aberta"),AJ50=AH56,IF('DADOS_INVOC'!$RA$8>=5,"Livre","Aberta"),AK50=AH56,IF('DADOS_INVOC'!$RA$8>=6,"Livre","Aberta"),TRUE,"Não escolhida"))
O57: ='DADOS_CRIACAO'!$H$14 | R57: =IF(O57="","",IFS(O48=O57,IF('DADOS_INVOC'!$RA$2>=1,"Livre","Aberta"),P48=O57,IF('DADOS_INVOC'!$RA$2>=2,"Livre","Aberta"),Q48=O57,IF('DADOS_INVOC'!$RA$2>=7,"Livre","Aberta"),R48=O57,IF('DADOS_INVOC'!$RA$2>=8,"Livre","Aberta"),S48=O57,IF('DADOS_INVOC'!$RA$2>=9,"Livre","Aberta"),O50=O57,IF('DADOS_INVOC'!$RA$2>=3,"Livre","Aberta"),P50=O57,IF('DADOS_INVOC'!$RA$2>=4,"Livre","Aberta"),Q50=O57,IF('DADOS_INVOC'!$RA$2>=5,"Livre","Aberta"),R50=O57,IF('DADOS_INVOC'!$RA$2>=6,"Livre","Aberta"),TRUE,"Não escolhida")) | AH57: ='DADOS_CRIACAO'!$H$14 | AK57: =IF(AH57="","",IFS(AH48=AH57,IF('DADOS_INVOC'!$RA$8>=1,"Livre","Aberta"),AI48=AH57,IF('DADOS_INVOC'!$RA$8>=2,"Livre","Aberta"),AJ48=AH57,IF('DADOS_INVOC'!$RA$8>=7,"Livre","Aberta"),AK48=AH57,IF('DADOS_INVOC'!$RA$8>=8,"Livre","Aberta"),AL48=AH57,IF('DADOS_INVOC'!$RA$8>=9,"Livre","Aberta"),AH50=AH57,IF('DADOS_INVOC'!$RA$8>=3,"Livre","Aberta"),AI50=AH57,IF('DADOS_INVOC'!$RA$8>=4,"Livre","Aberta"),AJ50=AH57,IF('DADOS_INVOC'!$RA$8>=5,"Livre","Aberta"),AK50=AH57,IF('DADOS_INVOC'!$RA$8>=6,"Livre","Aberta"),TRUE,"Não escolhida"))
O58: ='DADOS_CRIACAO'!$H$15 | R58: =IF(O58="","",IFS(O48=O58,IF('DADOS_INVOC'!$RA$2>=1,"Livre","Aberta"),P48=O58,IF('DADOS_INVOC'!$RA$2>=2,"Livre","Aberta"),Q48=O58,IF('DADOS_INVOC'!$RA$2>=7,"Livre","Aberta"),R48=O58,IF('DADOS_INVOC'!$RA$2>=8,"Livre","Aberta"),S48=O58,IF('DADOS_INVOC'!$RA$2>=9,"Livre","Aberta"),O50=O58,IF('DADOS_INVOC'!$RA$2>=3,"Livre","Aberta"),P50=O58,IF('DADOS_INVOC'!$RA$2>=4,"Livre","Aberta"),Q50=O58,IF('DADOS_INVOC'!$RA$2>=5,"Livre","Aberta"),R50=O58,IF('DADOS_INVOC'!$RA$2>=6,"Livre","Aberta"),TRUE,"Não escolhida")) | AH58: ='DADOS_CRIACAO'!$H$15 | AK58: =IF(AH58="","",IFS(AH48=AH58,IF('DADOS_INVOC'!$RA$8>=1,"Livre","Aberta"),AI48=AH58,IF('DADOS_INVOC'!$RA$8>=2,"Livre","Aberta"),AJ48=AH58,IF('DADOS_INVOC'!$RA$8>=7,"Livre","Aberta"),AK48=AH58,IF('DADOS_INVOC'!$RA$8>=8,"Livre","Aberta"),AL48=AH58,IF('DADOS_INVOC'!$RA$8>=9,"Livre","Aberta"),AH50=AH58,IF('DADOS_INVOC'!$RA$8>=3,"Livre","Aberta"),AI50=AH58,IF('DADOS_INVOC'!$RA$8>=4,"Livre","Aberta"),AJ50=AH58,IF('DADOS_INVOC'!$RA$8>=5,"Livre","Aberta"),AK50=AH58,IF('DADOS_INVOC'!$RA$8>=6,"Livre","Aberta"),TRUE,"Não escolhida"))
O59: ='DADOS_CRIACAO'!$H$16 | R59: =IF(O59="","",IFS(O48=O59,IF('DADOS_INVOC'!$RA$2>=1,"Livre","Aberta"),P48=O59,IF('DADOS_INVOC'!$RA$2>=2,"Livre","Aberta"),Q48=O59,IF('DADOS_INVOC'!$RA$2>=7,"Livre","Aberta"),R48=O59,IF('DADOS_INVOC'!$RA$2>=8,"Livre","Aberta"),S48=O59,IF('DADOS_INVOC'!$RA$2>=9,"Livre","Aberta"),O50=O59,IF('DADOS_INVOC'!$RA$2>=3,"Livre","Aberta"),P50=O59,IF('DADOS_INVOC'!$RA$2>=4,"Livre","Aberta"),Q50=O59,IF('DADOS_INVOC'!$RA$2>=5,"Livre","Aberta"),R50=O59,IF('DADOS_INVOC'!$RA$2>=6,"Livre","Aberta"),TRUE,"Não escolhida")) | AH59: ='DADOS_CRIACAO'!$H$16 | AK59: =IF(AH59="","",IFS(AH48=AH59,IF('DADOS_INVOC'!$RA$8>=1,"Livre","Aberta"),AI48=AH59,IF('DADOS_INVOC'!$RA$8>=2,"Livre","Aberta"),AJ48=AH59,IF('DADOS_INVOC'!$RA$8>=7,"Livre","Aberta"),AK48=AH59,IF('DADOS_INVOC'!$RA$8>=8,"Livre","Aberta"),AL48=AH59,IF('DADOS_INVOC'!$RA$8>=9,"Livre","Aberta"),AH50=AH59,IF('DADOS_INVOC'!$RA$8>=3,"Livre","Aberta"),AI50=AH59,IF('DADOS_INVOC'!$RA$8>=4,"Livre","Aberta"),AJ50=AH59,IF('DADOS_INVOC'!$RA$8>=5,"Livre","Aberta"),AK50=AH59,IF('DADOS_INVOC'!$RA$8>=6,"Livre","Aberta"),TRUE,"Não escolhida"))
O60: ='DADOS_CRIACAO'!$H$17 | R60: =IF(O60="","",IFS(O48=O60,IF('DADOS_INVOC'!$RA$2>=1,"Livre","Aberta"),P48=O60,IF('DADOS_INVOC'!$RA$2>=2,"Livre","Aberta"),Q48=O60,IF('DADOS_INVOC'!$RA$2>=7,"Livre","Aberta"),R48=O60,IF('DADOS_INVOC'!$RA$2>=8,"Livre","Aberta"),S48=O60,IF('DADOS_INVOC'!$RA$2>=9,"Livre","Aberta"),O50=O60,IF('DADOS_INVOC'!$RA$2>=3,"Livre","Aberta"),P50=O60,IF('DADOS_INVOC'!$RA$2>=4,"Livre","Aberta"),Q50=O60,IF('DADOS_INVOC'!$RA$2>=5,"Livre","Aberta"),R50=O60,IF('DADOS_INVOC'!$RA$2>=6,"Livre","Aberta"),TRUE,"Não escolhida")) | AH60: ='DADOS_CRIACAO'!$H$17 | AK60: =IF(AH60="","",IFS(AH48=AH60,IF('DADOS_INVOC'!$RA$8>=1,"Livre","Aberta"),AI48=AH60,IF('DADOS_INVOC'!$RA$8>=2,"Livre","Aberta"),AJ48=AH60,IF('DADOS_INVOC'!$RA$8>=7,"Livre","Aberta"),AK48=AH60,IF('DADOS_INVOC'!$RA$8>=8,"Livre","Aberta"),AL48=AH60,IF('DADOS_INVOC'!$RA$8>=9,"Livre","Aberta"),AH50=AH60,IF('DADOS_INVOC'!$RA$8>=3,"Livre","Aberta"),AI50=AH60,IF('DADOS_INVOC'!$RA$8>=4,"Livre","Aberta"),AJ50=AH60,IF('DADOS_INVOC'!$RA$8>=5,"Livre","Aberta"),AK50=AH60,IF('DADOS_INVOC'!$RA$8>=6,"Livre","Aberta"),TRUE,"Não escolhida"))
O61: ='DADOS_CRIACAO'!$H$18 | R61: =IF(O61="","",IFS(O48=O61,IF('DADOS_INVOC'!$RA$2>=1,"Livre","Aberta"),P48=O61,IF('DADOS_INVOC'!$RA$2>=2,"Livre","Aberta"),Q48=O61,IF('DADOS_INVOC'!$RA$2>=7,"Livre","Aberta"),R48=O61,IF('DADOS_INVOC'!$RA$2>=8,"Livre","Aberta"),S48=O61,IF('DADOS_INVOC'!$RA$2>=9,"Livre","Aberta"),O50=O61,IF('DADOS_INVOC'!$RA$2>=3,"Livre","Aberta"),P50=O61,IF('DADOS_INVOC'!$RA$2>=4,"Livre","Aberta"),Q50=O61,IF('DADOS_INVOC'!$RA$2>=5,"Livre","Aberta"),R50=O61,IF('DADOS_INVOC'!$RA$2>=6,"Livre","Aberta"),TRUE,"Não escolhida")) | AH61: ='DADOS_CRIACAO'!$H$18 | AK61: =IF(AH61="","",IFS(AH48=AH61,IF('DADOS_INVOC'!$RA$8>=1,"Livre","Aberta"),AI48=AH61,IF('DADOS_INVOC'!$RA$8>=2,"Livre","Aberta"),AJ48=AH61,IF('DADOS_INVOC'!$RA$8>=7,"Livre","Aberta"),AK48=AH61,IF('DADOS_INVOC'!$RA$8>=8,"Livre","Aberta"),AL48=AH61,IF('DADOS_INVOC'!$RA$8>=9,"Livre","Aberta"),AH50=AH61,IF('DADOS_INVOC'!$RA$8>=3,"Livre","Aberta"),AI50=AH61,IF('DADOS_INVOC'!$RA$8>=4,"Livre","Aberta"),AJ50=AH61,IF('DADOS_INVOC'!$RA$8>=5,"Livre","Aberta"),AK50=AH61,IF('DADOS_INVOC'!$RA$8>=6,"Livre","Aberta"),TRUE,"Não escolhida"))
O62: ='DADOS_CRIACAO'!$H$19 | R62: =IF(O62="","",IFS(O48=O62,IF('DADOS_INVOC'!$RA$2>=1,"Livre","Aberta"),P48=O62,IF('DADOS_INVOC'!$RA$2>=2,"Livre","Aberta"),Q48=O62,IF('DADOS_INVOC'!$RA$2>=7,"Livre","Aberta"),R48=O62,IF('DADOS_INVOC'!$RA$2>=8,"Livre","Aberta"),S48=O62,IF('DADOS_INVOC'!$RA$2>=9,"Livre","Aberta"),O50=O62,IF('DADOS_INVOC'!$RA$2>=3,"Livre","Aberta"),P50=O62,IF('DADOS_INVOC'!$RA$2>=4,"Livre","Aberta"),Q50=O62,IF('DADOS_INVOC'!$RA$2>=5,"Livre","Aberta"),R50=O62,IF('DADOS_INVOC'!$RA$2>=6,"Livre","Aberta"),TRUE,"Não escolhida")) | AH62: ='DADOS_CRIACAO'!$H$19 | AK62: =IF(AH62="","",IFS(AH48=AH62,IF('DADOS_INVOC'!$RA$8>=1,"Livre","Aberta"),AI48=AH62,IF('DADOS_INVOC'!$RA$8>=2,"Livre","Aberta"),AJ48=AH62,IF('DADOS_INVOC'!$RA$8>=7,"Livre","Aberta"),AK48=AH62,IF('DADOS_INVOC'!$RA$8>=8,"Livre","Aberta"),AL48=AH62,IF('DADOS_INVOC'!$RA$8>=9,"Livre","Aberta"),AH50=AH62,IF('DADOS_INVOC'!$RA$8>=3,"Livre","Aberta"),AI50=AH62,IF('DADOS_INVOC'!$RA$8>=4,"Livre","Aberta"),AJ50=AH62,IF('DADOS_INVOC'!$RA$8>=5,"Livre","Aberta"),AK50=AH62,IF('DADOS_INVOC'!$RA$8>=6,"Livre","Aberta"),TRUE,"Não escolhida"))
O63: ='DADOS_CRIACAO'!$H$20 | R63: =IF(O63="","",IFS(O48=O63,IF('DADOS_INVOC'!$RA$2>=1,"Livre","Aberta"),P48=O63,IF('DADOS_INVOC'!$RA$2>=2,"Livre","Aberta"),Q48=O63,IF('DADOS_INVOC'!$RA$2>=7,"Livre","Aberta"),R48=O63,IF('DADOS_INVOC'!$RA$2>=8,"Livre","Aberta"),S48=O63,IF('DADOS_INVOC'!$RA$2>=9,"Livre","Aberta"),O50=O63,IF('DADOS_INVOC'!$RA$2>=3,"Livre","Aberta"),P50=O63,IF('DADOS_INVOC'!$RA$2>=4,"Livre","Aberta"),Q50=O63,IF('DADOS_INVOC'!$RA$2>=5,"Livre","Aberta"),R50=O63,IF('DADOS_INVOC'!$RA$2>=6,"Livre","Aberta"),TRUE,"Não escolhida")) | AH63: ='DADOS_CRIACAO'!$H$20 | AK63: =IF(AH63="","",IFS(AH48=AH63,IF('DADOS_INVOC'!$RA$8>=1,"Livre","Aberta"),AI48=AH63,IF('DADOS_INVOC'!$RA$8>=2,"Livre","Aberta"),AJ48=AH63,IF('DADOS_INVOC'!$RA$8>=7,"Livre","Aberta"),AK48=AH63,IF('DADOS_INVOC'!$RA$8>=8,"Livre","Aberta"),AL48=AH63,IF('DADOS_INVOC'!$RA$8>=9,"Livre","Aberta"),AH50=AH63,IF('DADOS_INVOC'!$RA$8>=3,"Livre","Aberta"),AI50=AH63,IF('DADOS_INVOC'!$RA$8>=4,"Livre","Aberta"),AJ50=AH63,IF('DADOS_INVOC'!$RA$8>=5,"Livre","Aberta"),AK50=AH63,IF('DADOS_INVOC'!$RA$8>=6,"Livre","Aberta"),TRUE,"Não escolhida"))
I65: DEFINIÇÃO | AB65: DEFINIÇÃO
I68: =DADOS_INVOC!$IE$2 | AB68: =DADOS_INVOC!$IE$8
I70: =DADOS_INVOC!$PZ$2 | O70: =DADOS_INVOC!$PZ$3 | U70: =DADOS_INVOC!$PZ$4 | AB70: =DADOS_INVOC!$PZ$80 | AH70: =DADOS_INVOC!$PZ$81 | AN70: =DADOS_INVOC!$PZ$82
I71: 0 | M71: =DADOS_INVOC!$PX$2 | O71: 1 | S71: =DADOS_INVOC!$PX$3 | U71: 1 | Y71: =DADOS_INVOC!$PX$4 | AB71: 0 | AF71: =DADOS_INVOC!$PX$80 | AH71: 1 | AL71: =DADOS_INVOC!$PX$81 | AN71: 1 | AR71: =DADOS_INVOC!$PX$82
I72: COMO É | O72: COMO É | U72: COMO É | AB72: COMO É | AH72: COMO É | AN72: COMO É
I76: Projétil | K76: =DADOS_INVOC!$QE$2 | M76: =DADOS_INVOC!$QA$2 | O76: Projétil | Q76: =DADOS_INVOC!$QE$3 | S76: =DADOS_INVOC!$QA$3 | U76: Projétil | W76: =DADOS_INVOC!$QE$4 | Y76: =DADOS_INVOC!$QA$4 | AB76: Projétil | AD76: =DADOS_INVOC!$QE$80 | AF76: =DADOS_INVOC!$QA$80 | AH76: Projétil | AJ76: =DADOS_INVOC!$QE$81 | AL76: =DADOS_INVOC!$QA$81 | AN76: Projétil | AP76: =DADOS_INVOC!$QE$82 | AR76: =DADOS_INVOC!$QA$82
I78: =DADOS_INVOC!$QB$2 | K78: =DADOS_INVOC!$QD$2 | O78: =DADOS_INVOC!$QB$3 | Q78: =DADOS_INVOC!$QD$3 | U78: =DADOS_INVOC!$QB$4 | W78: =DADOS_INVOC!$QD$4 | AB78: =DADOS_INVOC!$QB$80 | AD78: =DADOS_INVOC!$QD$80 | AH78: =DADOS_INVOC!$QB$81 | AJ78: =DADOS_INVOC!$QD$81 | AN78: =DADOS_INVOC!$QB$82 | AP78: =DADOS_INVOC!$QD$82
I79: =DADOS_INVOC!$QJ$2 | O79: =DADOS_INVOC!$QJ$3 | U79: =DADOS_INVOC!$QJ$4 | AB79: =DADOS_INVOC!$QJ$80 | AH79: =DADOS_INVOC!$QJ$81 | AN79: =DADOS_INVOC!$QJ$82
I80: MELHORIAS | M80: =DADOS_INVOC!$QM$2 | O80: MELHORIAS | S80: =DADOS_INVOC!$QM$3 | U80: MELHORIAS | Y80: =DADOS_INVOC!$QM$4 | AB80: MELHORIAS | AF80: =DADOS_INVOC!$QM$80 | AH80: MELHORIAS | AL80: =DADOS_INVOC!$QM$81 | AN80: MELHORIAS | AR80: =DADOS_INVOC!$QM$82
M81: =DADOS_INVOC!$QN$2 | S81: =DADOS_INVOC!$QN$3 | Y81: =DADOS_INVOC!$QN$4 | AF81: =DADOS_INVOC!$QN$80 | AL81: =DADOS_INVOC!$QN$81 | AR81: =DADOS_INVOC!$QN$82
M82: =DADOS_INVOC!$QO$2 | S82: =DADOS_INVOC!$QO$3 | Y82: =DADOS_INVOC!$QO$4 | AF82: =DADOS_INVOC!$QO$80 | AL82: =DADOS_INVOC!$QO$81 | AR82: =DADOS_INVOC!$QO$82
M83: =DADOS_INVOC!$QP$2 | S83: =DADOS_INVOC!$QP$3 | Y83: =DADOS_INVOC!$QP$4 | AF83: =DADOS_INVOC!$QP$80 | AL83: =DADOS_INVOC!$QP$81 | AR83: =DADOS_INVOC!$QP$82
I84: RESTRIÇÕES | M84: =DADOS_INVOC!$QQ$2 | O84: RESTRIÇÕES | S84: =DADOS_INVOC!$QQ$3 | U84: RESTRIÇÕES | Y84: =DADOS_INVOC!$QQ$4 | AB84: RESTRIÇÕES | AF84: =DADOS_INVOC!$QQ$80 | AH84: RESTRIÇÕES | AL84: =DADOS_INVOC!$QQ$81 | AN84: RESTRIÇÕES | AR84: =DADOS_INVOC!$QQ$82
M85: =DADOS_INVOC!$QR$2 | S85: =DADOS_INVOC!$QR$3 | Y85: =DADOS_INVOC!$QR$4 | AF85: =DADOS_INVOC!$QR$80 | AL85: =DADOS_INVOC!$QR$81 | AR85: =DADOS_INVOC!$QR$82
I86: CONTA | J86: =DADOS_INVOC!$QK$2 | O86: CONTA | P86: =DADOS_INVOC!$QK$3 | U86: CONTA | V86: =DADOS_INVOC!$QK$4 | AB86: CONTA | AC86: =DADOS_INVOC!$QK$80 | AH86: CONTA | AI86: =DADOS_INVOC!$QK$81 | AN86: CONTA | AO86: =DADOS_INVOC!$QK$82
I87: AMPLIAR | J87: =DADOS_INVOC!$QL$2 | O87: AMPLIAR | P87: =DADOS_INVOC!$QL$3 | U87: AMPLIAR | V87: =DADOS_INVOC!$QL$4 | AB87: AMPLIAR | AC87: =DADOS_INVOC!$QL$80 | AH87: AMPLIAR | AI87: =DADOS_INVOC!$QL$81 | AN87: AMPLIAR | AO87: =DADOS_INVOC!$QL$82
I89: =DADOS_INVOC!$PY$2 | O89: =DADOS_INVOC!$PY$3 | U89: =DADOS_INVOC!$PY$4 | AB89: =DADOS_INVOC!$PY$80 | AH89: =DADOS_INVOC!$PY$81 | AN89: =DADOS_INVOC!$PY$82
I92: =DADOS_INVOC!$IF$2 | AB92: =DADOS_INVOC!$IF$8
I93: NV 1 · CE 1 | M93: =DADOS_INVOC!$IO$2 | AB93: NV 1 · CE 1 | AF93: =DADOS_INVOC!$IO$8
I94: NV 6 · CE 1 | M94: =DADOS_INVOC!$IP$2 | AB94: NV 6 · CE 1 | AF94: =DADOS_INVOC!$IP$8
I95: NV 10 · CE 2 | M95: =DADOS_INVOC!$IQ$2 | AB95: NV 10 · CE 2 | AF95: =DADOS_INVOC!$IQ$8
I96: NV 14 · CE 3 | M96: =DADOS_INVOC!$IR$2 | AB96: NV 14 · CE 3 | AF96: =DADOS_INVOC!$IR$8
I97: NV 18 · CE 3 | M97: =DADOS_INVOC!$IS$2 | AB97: NV 18 · CE 3 | AF97: =DADOS_INVOC!$IS$8
I98: NV 22 · CE 3 | M98: =DADOS_INVOC!$IT$2 | AB98: NV 22 · CE 3 | AF98: =DADOS_INVOC!$IT$8
I99: NV 26 · CE 3 | M99: =DADOS_INVOC!$IU$2 | AB99: NV 26 · CE 3 | AF99: =DADOS_INVOC!$IU$8
I100: NV 30 · CE 3 | M100: =DADOS_INVOC!$IV$2 | AB100: NV 30 · CE 3 | AF100: =DADOS_INVOC!$IV$8
I102: MAIS HABILIDADES · a segunda básica no nível 11, e as especiais 3 a 8, do nível 8 ao 28 | AB102: MAIS HABILIDADES · a segunda básica no nível 11, e as especiais 3 a 8, do nível 8 ao 28
I104: =DADOS_INVOC!$PZ$5 | O104: =DADOS_INVOC!$PZ$6 | U104: =DADOS_INVOC!$PZ$7 | AB104: =DADOS_INVOC!$PZ$83 | AH104: =DADOS_INVOC!$PZ$84 | AN104: =DADOS_INVOC!$PZ$85
I105: 0 | M105: =DADOS_INVOC!$PX$5 | O105: 1 | S105: =DADOS_INVOC!$PX$6 | U105: 1 | Y105: =DADOS_INVOC!$PX$7 | AB105: 0 | AF105: =DADOS_INVOC!$PX$83 | AH105: 1 | AL105: =DADOS_INVOC!$PX$84 | AN105: 1 | AR105: =DADOS_INVOC!$PX$85
I106: COMO É | O106: COMO É | U106: COMO É | AB106: COMO É | AH106: COMO É | AN106: COMO É
I110: Projétil | K110: =DADOS_INVOC!$QE$5 | M110: =DADOS_INVOC!$QA$5 | O110: Projétil | Q110: =DADOS_INVOC!$QE$6 | S110: =DADOS_INVOC!$QA$6 | U110: Projétil | W110: =DADOS_INVOC!$QE$7 | Y110: =DADOS_INVOC!$QA$7 | AB110: Projétil | AD110: =DADOS_INVOC!$QE$83 | AF110: =DADOS_INVOC!$QA$83 | AH110: Projétil | AJ110: =DADOS_INVOC!$QE$84 | AL110: =DADOS_INVOC!$QA$84 | AN110: Projétil | AP110: =DADOS_INVOC!$QE$85 | AR110: =DADOS_INVOC!$QA$85
I112: =DADOS_INVOC!$QB$5 | K112: =DADOS_INVOC!$QD$5 | O112: =DADOS_INVOC!$QB$6 | Q112: =DADOS_INVOC!$QD$6 | U112: =DADOS_INVOC!$QB$7 | W112: =DADOS_INVOC!$QD$7 | AB112: =DADOS_INVOC!$QB$83 | AD112: =DADOS_INVOC!$QD$83 | AH112: =DADOS_INVOC!$QB$84 | AJ112: =DADOS_INVOC!$QD$84 | AN112: =DADOS_INVOC!$QB$85 | AP112: =DADOS_INVOC!$QD$85
I113: =DADOS_INVOC!$QJ$5 | O113: =DADOS_INVOC!$QJ$6 | U113: =DADOS_INVOC!$QJ$7 | AB113: =DADOS_INVOC!$QJ$83 | AH113: =DADOS_INVOC!$QJ$84 | AN113: =DADOS_INVOC!$QJ$85
I114: MELHORIAS | M114: =DADOS_INVOC!$QM$5 | O114: MELHORIAS | S114: =DADOS_INVOC!$QM$6 | U114: MELHORIAS | Y114: =DADOS_INVOC!$QM$7 | AB114: MELHORIAS | AF114: =DADOS_INVOC!$QM$83 | AH114: MELHORIAS | AL114: =DADOS_INVOC!$QM$84 | AN114: MELHORIAS | AR114: =DADOS_INVOC!$QM$85
M115: =DADOS_INVOC!$QN$5 | S115: =DADOS_INVOC!$QN$6 | Y115: =DADOS_INVOC!$QN$7 | AF115: =DADOS_INVOC!$QN$83 | AL115: =DADOS_INVOC!$QN$84 | AR115: =DADOS_INVOC!$QN$85
M116: =DADOS_INVOC!$QO$5 | S116: =DADOS_INVOC!$QO$6 | Y116: =DADOS_INVOC!$QO$7 | AF116: =DADOS_INVOC!$QO$83 | AL116: =DADOS_INVOC!$QO$84 | AR116: =DADOS_INVOC!$QO$85
M117: =DADOS_INVOC!$QP$5 | S117: =DADOS_INVOC!$QP$6 | Y117: =DADOS_INVOC!$QP$7 | AF117: =DADOS_INVOC!$QP$83 | AL117: =DADOS_INVOC!$QP$84 | AR117: =DADOS_INVOC!$QP$85
I118: RESTRIÇÕES | M118: =DADOS_INVOC!$QQ$5 | O118: RESTRIÇÕES | S118: =DADOS_INVOC!$QQ$6 | U118: RESTRIÇÕES | Y118: =DADOS_INVOC!$QQ$7 | AB118: RESTRIÇÕES | AF118: =DADOS_INVOC!$QQ$83 | AH118: RESTRIÇÕES | AL118: =DADOS_INVOC!$QQ$84 | AN118: RESTRIÇÕES | AR118: =DADOS_INVOC!$QQ$85
M119: =DADOS_INVOC!$QR$5 | S119: =DADOS_INVOC!$QR$6 | Y119: =DADOS_INVOC!$QR$7 | AF119: =DADOS_INVOC!$QR$83 | AL119: =DADOS_INVOC!$QR$84 | AR119: =DADOS_INVOC!$QR$85
I120: CONTA | J120: =DADOS_INVOC!$QK$5 | O120: CONTA | P120: =DADOS_INVOC!$QK$6 | U120: CONTA | V120: =DADOS_INVOC!$QK$7 | AB120: CONTA | AC120: =DADOS_INVOC!$QK$83 | AH120: CONTA | AI120: =DADOS_INVOC!$QK$84 | AN120: CONTA | AO120: =DADOS_INVOC!$QK$85
I121: AMPLIAR | J121: =DADOS_INVOC!$QL$5 | O121: AMPLIAR | P121: =DADOS_INVOC!$QL$6 | U121: AMPLIAR | V121: =DADOS_INVOC!$QL$7 | AB121: AMPLIAR | AC121: =DADOS_INVOC!$QL$83 | AH121: AMPLIAR | AI121: =DADOS_INVOC!$QL$84 | AN121: AMPLIAR | AO121: =DADOS_INVOC!$QL$85
I123: =DADOS_INVOC!$PY$5 | O123: =DADOS_INVOC!$PY$6 | U123: =DADOS_INVOC!$PY$7 | AB123: =DADOS_INVOC!$PY$83 | AH123: =DADOS_INVOC!$PY$84 | AN123: =DADOS_INVOC!$PY$85
I126: =DADOS_INVOC!$PZ$8 | O126: =DADOS_INVOC!$PZ$9 | U126: =DADOS_INVOC!$PZ$10 | AB126: =DADOS_INVOC!$PZ$86 | AH126: =DADOS_INVOC!$PZ$87 | AN126: =DADOS_INVOC!$PZ$88
I127: 1 | M127: =DADOS_INVOC!$PX$8 | O127: 1 | S127: =DADOS_INVOC!$PX$9 | U127: 1 | Y127: =DADOS_INVOC!$PX$10 | AB127: 1 | AF127: =DADOS_INVOC!$PX$86 | AH127: 1 | AL127: =DADOS_INVOC!$PX$87 | AN127: 1 | AR127: =DADOS_INVOC!$PX$88
I128: COMO É | O128: COMO É | U128: COMO É | AB128: COMO É | AH128: COMO É | AN128: COMO É
I132: Projétil | K132: =DADOS_INVOC!$QE$8 | M132: =DADOS_INVOC!$QA$8 | O132: Projétil | Q132: =DADOS_INVOC!$QE$9 | S132: =DADOS_INVOC!$QA$9 | U132: Projétil | W132: =DADOS_INVOC!$QE$10 | Y132: =DADOS_INVOC!$QA$10 | AB132: Projétil | AD132: =DADOS_INVOC!$QE$86 | AF132: =DADOS_INVOC!$QA$86 | AH132: Projétil | AJ132: =DADOS_INVOC!$QE$87 | AL132: =DADOS_INVOC!$QA$87 | AN132: Projétil | AP132: =DADOS_INVOC!$QE$88 | AR132: =DADOS_INVOC!$QA$88
I134: =DADOS_INVOC!$QB$8 | K134: =DADOS_INVOC!$QD$8 | O134: =DADOS_INVOC!$QB$9 | Q134: =DADOS_INVOC!$QD$9 | U134: =DADOS_INVOC!$QB$10 | W134: =DADOS_INVOC!$QD$10 | AB134: =DADOS_INVOC!$QB$86 | AD134: =DADOS_INVOC!$QD$86 | AH134: =DADOS_INVOC!$QB$87 | AJ134: =DADOS_INVOC!$QD$87 | AN134: =DADOS_INVOC!$QB$88 | AP134: =DADOS_INVOC!$QD$88
...

Sheet FICHA PESSOAL
D2: 呪術 | H2: FICHA PESSOAL | AB2: =IF(OR(CARTEIRA!$O$9="",CARTEIRA!$O$9="Coloque o nome do personagem aqui"),"",CARTEIRA!$O$9)
H4: =DADOS!$F$1&" · pertences e histórico do portador" | AB4: =FICHA!AB4
A8: CICLO MALDITO | D8: DOSSIÊ | AW8: MISSÕES E XP | BI8: MAIS MISSÕES
D10: =CARTEIRA!$C$8 | Q10: NOME | AB10: GRAU | AI10: IDADE | AO10: ALTURA | AW10: XP TOTAL | BC10: =IF(DADOS!$CZ$48>=30,"NÍVEL MÁXIMO","FALTA PARA O NÍVEL "&(DADOS!$CZ$48+1))
Q11: =FICHA!AB2 | AB11: Grau 4 | AW11: =DADOS!$CZ$47 | BC11: =IF(DADOS!$CZ$49&""="","—",MAX(0,DADOS!$CZ$49-DADOS!$CZ$47)) | BE11: =IFERROR(SPARKLINE(MAX(0,DADOS!$CZ$47-DADOS!$CZ$50),{"charttype","bar";"max",MAX(1,N(DADOS!$CZ$49)-DADOS!$CZ$50);"color1",DADOS!$CZ$51}),"")
Q14: OLHOS | Y14: CABELO | AG14: PELE | AO14: GÊNERO | AW14: MISSÃO | AX14: XP | AY14: ADICIONAL | AZ14: DESCONTO | BA14: TOTAL | BC14: MISSÃO | BD14: XP | BE14: ADICIONAL | BF14: DESCONTO | BG14: TOTAL | BI14: MISSÃO | BJ14: XP | BK14: ADICIONAL | BL14: DESCONTO | BM14: TOTAL | BO14: MISSÃO | BP14: XP | BQ14: ADICIONAL | BR14: DESCONTO | BS14: TOTAL
BA15: =IF($AX15="","",IFERROR(IF(ROUND(VLOOKUP($AX15,DADOS!$CL$5:$CM$10,2,FALSE)*IF($AY15="",1,VLOOKUP($AY15,DADOS!$CO$5:$CP$7,2,FALSE))*IF($AZ15="",1,VLOOKUP($AZ15,DADOS!$CR$5:$CS$15,2,FALSE)),4)>0,MAX(1,FLOOR(ROUND(VLOOKUP($AX15,DADOS!$CL$5:$CM$10,2,FALSE)*IF($AY15="",1,VLOOKUP($AY15,DADOS!$CO$5:$CP$7,2,FALSE))*IF($AZ15="",1,VLOOKUP($AZ15,DADOS!$CR$5:$CS$15,2,FALSE)),4),1)),0),"")) | BG15: =IF($BD15="","",IFERROR(IF(ROUND(VLOOKUP($BD15,DADOS!$CL$5:$CM$10,2,FALSE)*IF($BE15="",1,VLOOKUP($BE15,DADOS!$CO$5:$CP$7,2,FALSE))*IF($BF15="",1,VLOOKUP($BF15,DADOS!$CR$5:$CS$15,2,FALSE)),4)>0,MAX(1,FLOOR(ROUND(VLOOKUP($BD15,DADOS!$CL$5:$CM$10,2,FALSE)*IF($BE15="",1,VLOOKUP($BE15,DADOS!$CO$5:$CP$7,2,FALSE))*IF($BF15="",1,VLOOKUP($BF15,DADOS!$CR$5:$CS$15,2,FALSE)),4),1)),0),"")) | BM15: =IF($BJ15="","",IFERROR(IF(ROUND(VLOOKUP($BJ15,DADOS!$CL$5:$CM$10,2,FALSE)*IF($BK15="",1,VLOOKUP($BK15,DADOS!$CO$5:$CP$7,2,FALSE))*IF($BL15="",1,VLOOKUP($BL15,DADOS!$CR$5:$CS$15,2,FALSE)),4)>0,MAX(1,FLOOR(ROUND(VLOOKUP($BJ15,DADOS!$CL$5:$CM$10,2,FALSE)*IF($BK15="",1,VLOOKUP($BK15,DADOS!$CO$5:$CP$7,2,FALSE))*IF($BL15="",1,VLOOKUP($BL15,DADOS!$CR$5:$CS$15,2,FALSE)),4),1)),0),"")) | BS15: =IF($BP15="","",IFERROR(IF(ROUND(VLOOKUP($BP15,DADOS!$CL$5:$CM$10,2,FALSE)*IF($BQ15="",1,VLOOKUP($BQ15,DADOS!$CO$5:$CP$7,2,FALSE))*IF($BR15="",1,VLOOKUP($BR15,DADOS!$CR$5:$CS$15,2,FALSE)),4)>0,MAX(1,FLOOR(ROUND(VLOOKUP($BP15,DADOS!$CL$5:$CM$10,2,FALSE)*IF($BQ15="",1,VLOOKUP($BQ15,DADOS!$CO$5:$CP$7,2,FALSE))*IF($BR15="",1,VLOOKUP($BR15,DADOS!$CR$5:$CS$15,2,FALSE)),4),1)),0),""))
BA16: =IF($AX16="","",IFERROR(IF(ROUND(VLOOKUP($AX16,DADOS!$CL$5:$CM$10,2,FALSE)*IF($AY16="",1,VLOOKUP($AY16,DADOS!$CO$5:$CP$7,2,FALSE))*IF($AZ16="",1,VLOOKUP($AZ16,DADOS!$CR$5:$CS$15,2,FALSE)),4)>0,MAX(1,FLOOR(ROUND(VLOOKUP($AX16,DADOS!$CL$5:$CM$10,2,FALSE)*IF($AY16="",1,VLOOKUP($AY16,DADOS!$CO$5:$CP$7,2,FALSE))*IF($AZ16="",1,VLOOKUP($AZ16,DADOS!$CR$5:$CS$15,2,FALSE)),4),1)),0),"")) | BG16: =IF($BD16="","",IFERROR(IF(ROUND(VLOOKUP($BD16,DADOS!$CL$5:$CM$10,2,FALSE)*IF($BE16="",1,VLOOKUP($BE16,DADOS!$CO$5:$CP$7,2,FALSE))*IF($BF16="",1,VLOOKUP($BF16,DADOS!$CR$5:$CS$15,2,FALSE)),4)>0,MAX(1,FLOOR(ROUND(VLOOKUP($BD16,DADOS!$CL$5:$CM$10,2,FALSE)*IF($BE16="",1,VLOOKUP($BE16,DADOS!$CO$5:$CP$7,2,FALSE))*IF($BF16="",1,VLOOKUP($BF16,DADOS!$CR$5:$CS$15,2,FALSE)),4),1)),0),"")) | BM16: =IF($BJ16="","",IFERROR(IF(ROUND(VLOOKUP($BJ16,DADOS!$CL$5:$CM$10,2,FALSE)*IF($BK16="",1,VLOOKUP($BK16,DADOS!$CO$5:$CP$7,2,FALSE))*IF($BL16="",1,VLOOKUP($BL16,DADOS!$CR$5:$CS$15,2,FALSE)),4)>0,MAX(1,FLOOR(ROUND(VLOOKUP($BJ16,DADOS!$CL$5:$CM$10,2,FALSE)*IF($BK16="",1,VLOOKUP($BK16,DADOS!$CO$5:$CP$7,2,FALSE))*IF($BL16="",1,VLOOKUP($BL16,DADOS!$CR$5:$CS$15,2,FALSE)),4),1)),0),"")) | BS16: =IF($BP16="","",IFERROR(IF(ROUND(VLOOKUP($BP16,DADOS!$CL$5:$CM$10,2,FALSE)*IF($BQ16="",1,VLOOKUP($BQ16,DADOS!$CO$5:$CP$7,2,FALSE))*IF($BR16="",1,VLOOKUP($BR16,DADOS!$CR$5:$CS$15,2,FALSE)),4)>0,MAX(1,FLOOR(ROUND(VLOOKUP($BP16,DADOS!$CL$5:$CM$10,2,FALSE)*IF($BQ16="",1,VLOOKUP($BQ16,DADOS!$CO$5:$CP$7,2,FALSE))*IF($BR16="",1,VLOOKUP($BR16,DADOS!$CR$5:$CS$15,2,FALSE)),4),1)),0),""))
BA17: =IF($AX17="","",IFERROR(IF(ROUND(VLOOKUP($AX17,DADOS!$CL$5:$CM$10,2,FALSE)*IF($AY17="",1,VLOOKUP($AY17,DADOS!$CO$5:$CP$7,2,FALSE))*IF($AZ17="",1,VLOOKUP($AZ17,DADOS!$CR$5:$CS$15,2,FALSE)),4)>0,MAX(1,FLOOR(ROUND(VLOOKUP($AX17,DADOS!$CL$5:$CM$10,2,FALSE)*IF($AY17="",1,VLOOKUP($AY17,DADOS!$CO$5:$CP$7,2,FALSE))*IF($AZ17="",1,VLOOKUP($AZ17,DADOS!$CR$5:$CS$15,2,FALSE)),4),1)),0),"")) | BG17: =IF($BD17="","",IFERROR(IF(ROUND(VLOOKUP($BD17,DADOS!$CL$5:$CM$10,2,FALSE)*IF($BE17="",1,VLOOKUP($BE17,DADOS!$CO$5:$CP$7,2,FALSE))*IF($BF17="",1,VLOOKUP($BF17,DADOS!$CR$5:$CS$15,2,FALSE)),4)>0,MAX(1,FLOOR(ROUND(VLOOKUP($BD17,DADOS!$CL$5:$CM$10,2,FALSE)*IF($BE17="",1,VLOOKUP($BE17,DADOS!$CO$5:$CP$7,2,FALSE))*IF($BF17="",1,VLOOKUP($BF17,DADOS!$CR$5:$CS$15,2,FALSE)),4),1)),0),"")) | BM17: =IF($BJ17="","",IFERROR(IF(ROUND(VLOOKUP($BJ17,DADOS!$CL$5:$CM$10,2,FALSE)*IF($BK17="",1,VLOOKUP($BK17,DADOS!$CO$5:$CP$7,2,FALSE))*IF($BL17="",1,VLOOKUP($BL17,DADOS!$CR$5:$CS$15,2,FALSE)),4)>0,MAX(1,FLOOR(ROUND(VLOOKUP($BJ17,DADOS!$CL$5:$CM$10,2,FALSE)*IF($BK17="",1,VLOOKUP($BK17,DADOS!$CO$5:$CP$7,2,FALSE))*IF($BL17="",1,VLOOKUP($BL17,DADOS!$CR$5:$CS$15,2,FALSE)),4),1)),0),"")) | BS17: =IF($BP17="","",IFERROR(IF(ROUND(VLOOKUP($BP17,DADOS!$CL$5:$CM$10,2,FALSE)*IF($BQ17="",1,VLOOKUP($BQ17,DADOS!$CO$5:$CP$7,2,FALSE))*IF($BR17="",1,VLOOKUP($BR17,DADOS!$CR$5:$CS$15,2,FALSE)),4)>0,MAX(1,FLOOR(ROUND(VLOOKUP($BP17,DADOS!$CL$5:$CM$10,2,FALSE)*IF($BQ17="",1,VLOOKUP($BQ17,DADOS!$CO$5:$CP$7,2,FALSE))*IF($BR17="",1,VLOOKUP($BR17,DADOS!$CR$5:$CS$15,2,FALSE)),4),1)),0),""))
Q18: APARÊNCIA | AI18: CICATRIZES | BA18: =IF($AX18="","",IFERROR(IF(ROUND(VLOOKUP($AX18,DADOS!$CL$5:$CM$10,2,FALSE)*IF($AY18="",1,VLOOKUP($AY18,DADOS!$CO$5:$CP$7,2,FALSE))*IF($AZ18="",1,VLOOKUP($AZ18,DADOS!$CR$5:$CS$15,2,FALSE)),4)>0,MAX(1,FLOOR(ROUND(VLOOKUP($AX18,DADOS!$CL$5:$CM$10,2,FALSE)*IF($AY18="",1,VLOOKUP($AY18,DADOS!$CO$5:$CP$7,2,FALSE))*IF($AZ18="",1,VLOOKUP($AZ18,DADOS!$CR$5:$CS$15,2,FALSE)),4),1)),0),"")) | BG18: =IF($BD18="","",IFERROR(IF(ROUND(VLOOKUP($BD18,DADOS!$CL$5:$CM$10,2,FALSE)*IF($BE18="",1,VLOOKUP($BE18,DADOS!$CO$5:$CP$7,2,FALSE))*IF($BF18="",1,VLOOKUP($BF18,DADOS!$CR$5:$CS$15,2,FALSE)),4)>0,MAX(1,FLOOR(ROUND(VLOOKUP($BD18,DADOS!$CL$5:$CM$10,2,FALSE)*IF($BE18="",1,VLOOKUP($BE18,DADOS!$CO$5:$CP$7,2,FALSE))*IF($BF18="",1,VLOOKUP($BF18,DADOS!$CR$5:$CS$15,2,FALSE)),4),1)),0),"")) | BM18: =IF($BJ18="","",IFERROR(IF(ROUND(VLOOKUP($BJ18,DADOS!$CL$5:$CM$10,2,FALSE)*IF($BK18="",1,VLOOKUP($BK18,DADOS!$CO$5:$CP$7,2,FALSE))*IF($BL18="",1,VLOOKUP($BL18,DADOS!$CR$5:$CS$15,2,FALSE)),4)>0,MAX(1,FLOOR(ROUND(VLOOKUP($BJ18,DADOS!$CL$5:$CM$10,2,FALSE)*IF($BK18="",1,VLOOKUP($BK18,DADOS!$CO$5:$CP$7,2,FALSE))*IF($BL18="",1,VLOOKUP($BL18,DADOS!$CR$5:$CS$15,2,FALSE)),4),1)),0),"")) | BS18: =IF($BP18="","",IFERROR(IF(ROUND(VLOOKUP($BP18,DADOS!$CL$5:$CM$10,2,FALSE)*IF($BQ18="",1,VLOOKUP($BQ18,DADOS!$CO$5:$CP$7,2,FALSE))*IF($BR18="",1,VLOOKUP($BR18,DADOS!$CR$5:$CS$15,2,FALSE)),4)>0,MAX(1,FLOOR(ROUND(VLOOKUP($BP18,DADOS!$CL$5:$CM$10,2,FALSE)*IF($BQ18="",1,VLOOKUP($BQ18,DADOS!$CO$5:$CP$7,2,FALSE))*IF($BR18="",1,VLOOKUP($BR18,DADOS!$CR$5:$CS$15,2,FALSE)),4),1)),0),""))
BA19: =IF($AX19="","",IFERROR(IF(ROUND(VLOOKUP($AX19,DADOS!$CL$5:$CM$10,2,FALSE)*IF($AY19="",1,VLOOKUP($AY19,DADOS!$CO$5:$CP$7,2,FALSE))*IF($AZ19="",1,VLOOKUP($AZ19,DADOS!$CR$5:$CS$15,2,FALSE)),4)>0,MAX(1,FLOOR(ROUND(VLOOKUP($AX19,DADOS!$CL$5:$CM$10,2,FALSE)*IF($AY19="",1,VLOOKUP($AY19,DADOS!$CO$5:$CP$7,2,FALSE))*IF($AZ19="",1,VLOOKUP($AZ19,DADOS!$CR$5:$CS$15,2,FALSE)),4),1)),0),"")) | BG19: =IF($BD19="","",IFERROR(IF(ROUND(VLOOKUP($BD19,DADOS!$CL$5:$CM$10,2,FALSE)*IF($BE19="",1,VLOOKUP($BE19,DADOS!$CO$5:$CP$7,2,FALSE))*IF($BF19="",1,VLOOKUP($BF19,DADOS!$CR$5:$CS$15,2,FALSE)),4)>0,MAX(1,FLOOR(ROUND(VLOOKUP($BD19,DADOS!$CL$5:$CM$10,2,FALSE)*IF($BE19="",1,VLOOKUP($BE19,DADOS!$CO$5:$CP$7,2,FALSE))*IF($BF19="",1,VLOOKUP($BF19,DADOS!$CR$5:$CS$15,2,FALSE)),4),1)),0),"")) | BM19: =IF($BJ19="","",IFERROR(IF(ROUND(VLOOKUP($BJ19,DADOS!$CL$5:$CM$10,2,FALSE)*IF($BK19="",1,VLOOKUP($BK19,DADOS!$CO$5:$CP$7,2,FALSE))*IF($BL19="",1,VLOOKUP($BL19,DADOS!$CR$5:$CS$15,2,FALSE)),4)>0,MAX(1,FLOOR(ROUND(VLOOKUP($BJ19,DADOS!$CL$5:$CM$10,2,FALSE)*IF($BK19="",1,VLOOKUP($BK19,DADOS!$CO$5:$CP$7,2,FALSE))*IF($BL19="",1,VLOOKUP($BL19,DADOS!$CR$5:$CS$15,2,FALSE)),4),1)),0),"")) | BS19: =IF($BP19="","",IFERROR(IF(ROUND(VLOOKUP($BP19,DADOS!$CL$5:$CM$10,2,FALSE)*IF($BQ19="",1,VLOOKUP($BQ19,DADOS!$CO$5:$CP$7,2,FALSE))*IF($BR19="",1,VLOOKUP($BR19,DADOS!$CR$5:$CS$15,2,FALSE)),4)>0,MAX(1,FLOOR(ROUND(VLOOKUP($BP19,DADOS!$CL$5:$CM$10,2,FALSE)*IF($BQ19="",1,VLOOKUP($BQ19,DADOS!$CO$5:$CP$7,2,FALSE))*IF($BR19="",1,VLOOKUP($BR19,DADOS!$CR$5:$CS$15,2,FALSE)),4),1)),0),""))
BA20: =IF($AX20="","",IFERROR(IF(ROUND(VLOOKUP($AX20,DADOS!$CL$5:$CM$10,2,FALSE)*IF($AY20="",1,VLOOKUP($AY20,DADOS!$CO$5:$CP$7,2,FALSE))*IF($AZ20="",1,VLOOKUP($AZ20,DADOS!$CR$5:$CS$15,2,FALSE)),4)>0,MAX(1,FLOOR(ROUND(VLOOKUP($AX20,DADOS!$CL$5:$CM$10,2,FALSE)*IF($AY20="",1,VLOOKUP($AY20,DADOS!$CO$5:$CP$7,2,FALSE))*IF($AZ20="",1,VLOOKUP($AZ20,DADOS!$CR$5:$CS$15,2,FALSE)),4),1)),0),"")) | BG20: =IF($BD20="","",IFERROR(IF(ROUND(VLOOKUP($BD20,DADOS!$CL$5:$CM$10,2,FALSE)*IF($BE20="",1,VLOOKUP($BE20,DADOS!$CO$5:$CP$7,2,FALSE))*IF($BF20="",1,VLOOKUP($BF20,DADOS!$CR$5:$CS$15,2,FALSE)),4)>0,MAX(1,FLOOR(ROUND(VLOOKUP($BD20,DADOS!$CL$5:$CM$10,2,FALSE)*IF($BE20="",1,VLOOKUP($BE20,DADOS!$CO$5:$CP$7,2,FALSE))*IF($BF20="",1,VLOOKUP($BF20,DADOS!$CR$5:$CS$15,2,FALSE)),4),1)),0),"")) | BM20: =IF($BJ20="","",IFERROR(IF(ROUND(VLOOKUP($BJ20,DADOS!$CL$5:$CM$10,2,FALSE)*IF($BK20="",1,VLOOKUP($BK20,DADOS!$CO$5:$CP$7,2,FALSE))*IF($BL20="",1,VLOOKUP($BL20,DADOS!$CR$5:$CS$15,2,FALSE)),4)>0,MAX(1,FLOOR(ROUND(VLOOKUP($BJ20,DADOS!$CL$5:$CM$10,2,FALSE)*IF($BK20="",1,VLOOKUP($BK20,DADOS!$CO$5:$CP$7,2,FALSE))*IF($BL20="",1,VLOOKUP($BL20,DADOS!$CR$5:$CS$15,2,FALSE)),4),1)),0),"")) | BS20: =IF($BP20="","",IFERROR(IF(ROUND(VLOOKUP($BP20,DADOS!$CL$5:$CM$10,2,FALSE)*IF($BQ20="",1,VLOOKUP($BQ20,DADOS!$CO$5:$CP$7,2,FALSE))*IF($BR20="",1,VLOOKUP($BR20,DADOS!$CR$5:$CS$15,2,FALSE)),4)>0,MAX(1,FLOOR(ROUND(VLOOKUP($BP20,DADOS!$CL$5:$CM$10,2,FALSE)*IF($BQ20="",1,VLOOKUP($BQ20,DADOS!$CO$5:$CP$7,2,FALSE))*IF($BR20="",1,VLOOKUP($BR20,DADOS!$CR$5:$CS$15,2,FALSE)),4),1)),0),""))
BA21: =IF($AX21="","",IFERROR(IF(ROUND(VLOOKUP($AX21,DADOS!$CL$5:$CM$10,2,FALSE)*IF($AY21="",1,VLOOKUP($AY21,DADOS!$CO$5:$CP$7,2,FALSE))*IF($AZ21="",1,VLOOKUP($AZ21,DADOS!$CR$5:$CS$15,2,FALSE)),4)>0,MAX(1,FLOOR(ROUND(VLOOKUP($AX21,DADOS!$CL$5:$CM$10,2,FALSE)*IF($AY21="",1,VLOOKUP($AY21,DADOS!$CO$5:$CP$7,2,FALSE))*IF($AZ21="",1,VLOOKUP($AZ21,DADOS!$CR$5:$CS$15,2,FALSE)),4),1)),0),"")) | BG21: =IF($BD21="","",IFERROR(IF(ROUND(VLOOKUP($BD21,DADOS!$CL$5:$CM$10,2,FALSE)*IF($BE21="",1,VLOOKUP($BE21,DADOS!$CO$5:$CP$7,2,FALSE))*IF($BF21="",1,VLOOKUP($BF21,DADOS!$CR$5:$CS$15,2,FALSE)),4)>0,MAX(1,FLOOR(ROUND(VLOOKUP($BD21,DADOS!$CL$5:$CM$10,2,FALSE)*IF($BE21="",1,VLOOKUP($BE21,DADOS!$CO$5:$CP$7,2,FALSE))*IF($BF21="",1,VLOOKUP($BF21,DADOS!$CR$5:$CS$15,2,FALSE)),4),1)),0),"")) | BM21: =IF($BJ21="","",IFERROR(IF(ROUND(VLOOKUP($BJ21,DADOS!$CL$5:$CM$10,2,FALSE)*IF($BK21="",1,VLOOKUP($BK21,DADOS!$CO$5:$CP$7,2,FALSE))*IF($BL21="",1,VLOOKUP($BL21,DADOS!$CR$5:$CS$15,2,FALSE)),4)>0,MAX(1,FLOOR(ROUND(VLOOKUP($BJ21,DADOS!$CL$5:$CM$10,2,FALSE)*IF($BK21="",1,VLOOKUP($BK21,DADOS!$CO$5:$CP$7,2,FALSE))*IF($BL21="",1,VLOOKUP($BL21,DADOS!$CR$5:$CS$15,2,FALSE)),4),1)),0),"")) | BS21: =IF($BP21="","",IFERROR(IF(ROUND(VLOOKUP($BP21,DADOS!$CL$5:$CM$10,2,FALSE)*IF($BQ21="",1,VLOOKUP($BQ21,DADOS!$CO$5:$CP$7,2,FALSE))*IF($BR21="",1,VLOOKUP($BR21,DADOS!$CR$5:$CS$15,2,FALSE)),4)>0,MAX(1,FLOOR(ROUND(VLOOKUP($BP21,DADOS!$CL$5:$CM$10,2,FALSE)*IF($BQ21="",1,VLOOKUP($BQ21,DADOS!$CO$5:$CP$7,2,FALSE))*IF($BR21="",1,VLOOKUP($BR21,DADOS!$CR$5:$CS$15,2,FALSE)),4),1)),0),""))
Q22: TRAÇO · UMA FRASE DA SUA HISTÓRIA | BA22: =IF($AX22="","",IFERROR(IF(ROUND(VLOOKUP($AX22,DADOS!$CL$5:$CM$10,2,FALSE)*IF($AY22="",1,VLOOKUP($AY22,DADOS!$CO$5:$CP$7,2,FALSE))*IF($AZ22="",1,VLOOKUP($AZ22,DADOS!$CR$5:$CS$15,2,FALSE)),4)>0,MAX(1,FLOOR(ROUND(VLOOKUP($AX22,DADOS!$CL$5:$CM$10,2,FALSE)*IF($AY22="",1,VLOOKUP($AY22,DADOS!$CO$5:$CP$7,2,FALSE))*IF($AZ22="",1,VLOOKUP($AZ22,DADOS!$CR$5:$CS$15,2,FALSE)),4),1)),0),"")) | BG22: =IF($BD22="","",IFERROR(IF(ROUND(VLOOKUP($BD22,DADOS!$CL$5:$CM$10,2,FALSE)*IF($BE22="",1,VLOOKUP($BE22,DADOS!$CO$5:$CP$7,2,FALSE))*IF($BF22="",1,VLOOKUP($BF22,DADOS!$CR$5:$CS$15,2,FALSE)),4)>0,MAX(1,FLOOR(ROUND(VLOOKUP($BD22,DADOS!$CL$5:$CM$10,2,FALSE)*IF($BE22="",1,VLOOKUP($BE22,DADOS!$CO$5:$CP$7,2,FALSE))*IF($BF22="",1,VLOOKUP($BF22,DADOS!$CR$5:$CS$15,2,FALSE)),4),1)),0),"")) | BM22: =IF($BJ22="","",IFERROR(IF(ROUND(VLOOKUP($BJ22,DADOS!$CL$5:$CM$10,2,FALSE)*IF($BK22="",1,VLOOKUP($BK22,DADOS!$CO$5:$CP$7,2,FALSE))*IF($BL22="",1,VLOOKUP($BL22,DADOS!$CR$5:$CS$15,2,FALSE)),4)>0,MAX(1,FLOOR(ROUND(VLOOKUP($BJ22,DADOS!$CL$5:$CM$10,2,FALSE)*IF($BK22="",1,VLOOKUP($BK22,DADOS!$CO$5:$CP$7,2,FALSE))*IF($BL22="",1,VLOOKUP($BL22,DADOS!$CR$5:$CS$15,2,FALSE)),4),1)),0),"")) | BS22: =IF($BP22="","",IFERROR(IF(ROUND(VLOOKUP($BP22,DADOS!$CL$5:$CM$10,2,FALSE)*IF($BQ22="",1,VLOOKUP($BQ22,DADOS!$CO$5:$CP$7,2,FALSE))*IF($BR22="",1,VLOOKUP($BR22,DADOS!$CR$5:$CS$15,2,FALSE)),4)>0,MAX(1,FLOOR(ROUND(VLOOKUP($BP22,DADOS!$CL$5:$CM$10,2,FALSE)*IF($BQ22="",1,VLOOKUP($BQ22,DADOS!$CO$5:$CP$7,2,FALSE))*IF($BR22="",1,VLOOKUP($BR22,DADOS!$CR$5:$CS$15,2,FALSE)),4),1)),0),""))
BA23: =IF($AX23="","",IFERROR(IF(ROUND(VLOOKUP($AX23,DADOS!$CL$5:$CM$10,2,FALSE)*IF($AY23="",1,VLOOKUP($AY23,DADOS!$CO$5:$CP$7,2,FALSE))*IF($AZ23="",1,VLOOKUP($AZ23,DADOS!$CR$5:$CS$15,2,FALSE)),4)>0,MAX(1,FLOOR(ROUND(VLOOKUP($AX23,DADOS!$CL$5:$CM$10,2,FALSE)*IF($AY23="",1,VLOOKUP($AY23,DADOS!$CO$5:$CP$7,2,FALSE))*IF($AZ23="",1,VLOOKUP($AZ23,DADOS!$CR$5:$CS$15,2,FALSE)),4),1)),0),"")) | BG23: =IF($BD23="","",IFERROR(IF(ROUND(VLOOKUP($BD23,DADOS!$CL$5:$CM$10,2,FALSE)*IF($BE23="",1,VLOOKUP($BE23,DADOS!$CO$5:$CP$7,2,FALSE))*IF($BF23="",1,VLOOKUP($BF23,DADOS!$CR$5:$CS$15,2,FALSE)),4)>0,MAX(1,FLOOR(ROUND(VLOOKUP($BD23,DADOS!$CL$5:$CM$10,2,FALSE)*IF($BE23="",1,VLOOKUP($BE23,DADOS!$CO$5:$CP$7,2,FALSE))*IF($BF23="",1,VLOOKUP($BF23,DADOS!$CR$5:$CS$15,2,FALSE)),4),1)),0),"")) | BM23: =IF($BJ23="","",IFERROR(IF(ROUND(VLOOKUP($BJ23,DADOS!$CL$5:$CM$10,2,FALSE)*IF($BK23="",1,VLOOKUP($BK23,DADOS!$CO$5:$CP$7,2,FALSE))*IF($BL23="",1,VLOOKUP($BL23,DADOS!$CR$5:$CS$15,2,FALSE)),4)>0,MAX(1,FLOOR(ROUND(VLOOKUP($BJ23,DADOS!$CL$5:$CM$10,2,FALSE)*IF($BK23="",1,VLOOKUP($BK23,DADOS!$CO$5:$CP$7,2,FALSE))*IF($BL23="",1,VLOOKUP($BL23,DADOS!$CR$5:$CS$15,2,FALSE)),4),1)),0),"")) | BS23: =IF($BP23="","",IFERROR(IF(ROUND(VLOOKUP($BP23,DADOS!$CL$5:$CM$10,2,FALSE)*IF($BQ23="",1,VLOOKUP($BQ23,DADOS!$CO$5:$CP$7,2,FALSE))*IF($BR23="",1,VLOOKUP($BR23,DADOS!$CR$5:$CS$15,2,FALSE)),4)>0,MAX(1,FLOOR(ROUND(VLOOKUP($BP23,DADOS!$CL$5:$CM$10,2,FALSE)*IF($BQ23="",1,VLOOKUP($BQ23,DADOS!$CO$5:$CP$7,2,FALSE))*IF($BR23="",1,VLOOKUP($BR23,DADOS!$CR$5:$CS$15,2,FALSE)),4),1)),0),""))
BA24: =IF($AX24="","",IFERROR(IF(ROUND(VLOOKUP($AX24,DADOS!$CL$5:$CM$10,2,FALSE)*IF($AY24="",1,VLOOKUP($AY24,DADOS!$CO$5:$CP$7,2,FALSE))*IF($AZ24="",1,VLOOKUP($AZ24,DADOS!$CR$5:$CS$15,2,FALSE)),4)>0,MAX(1,FLOOR(ROUND(VLOOKUP($AX24,DADOS!$CL$5:$CM$10,2,FALSE)*IF($AY24="",1,VLOOKUP($AY24,DADOS!$CO$5:$CP$7,2,FALSE))*IF($AZ24="",1,VLOOKUP($AZ24,DADOS!$CR$5:$CS$15,2,FALSE)),4),1)),0),"")) | BG24: =IF($BD24="","",IFERROR(IF(ROUND(VLOOKUP($BD24,DADOS!$CL$5:$CM$10,2,FALSE)*IF($BE24="",1,VLOOKUP($BE24,DADOS!$CO$5:$CP$7,2,FALSE))*IF($BF24="",1,VLOOKUP($BF24,DADOS!$CR$5:$CS$15,2,FALSE)),4)>0,MAX(1,FLOOR(ROUND(VLOOKUP($BD24,DADOS!$CL$5:$CM$10,2,FALSE)*IF($BE24="",1,VLOOKUP($BE24,DADOS!$CO$5:$CP$7,2,FALSE))*IF($BF24="",1,VLOOKUP($BF24,DADOS!$CR$5:$CS$15,2,FALSE)),4),1)),0),"")) | BM24: =IF($BJ24="","",IFERROR(IF(ROUND(VLOOKUP($BJ24,DADOS!$CL$5:$CM$10,2,FALSE)*IF($BK24="",1,VLOOKUP($BK24,DADOS!$CO$5:$CP$7,2,FALSE))*IF($BL24="",1,VLOOKUP($BL24,DADOS!$CR$5:$CS$15,2,FALSE)),4)>0,MAX(1,FLOOR(ROUND(VLOOKUP($BJ24,DADOS!$CL$5:$CM$10,2,FALSE)*IF($BK24="",1,VLOOKUP($BK24,DADOS!$CO$5:$CP$7,2,FALSE))*IF($BL24="",1,VLOOKUP($BL24,DADOS!$CR$5:$CS$15,2,FALSE)),4),1)),0),"")) | BS24: =IF($BP24="","",IFERROR(IF(ROUND(VLOOKUP($BP24,DADOS!$CL$5:$CM$10,2,FALSE)*IF($BQ24="",1,VLOOKUP($BQ24,DADOS!$CO$5:$CP$7,2,FALSE))*IF($BR24="",1,VLOOKUP($BR24,DADOS!$CR$5:$CS$15,2,FALSE)),4)>0,MAX(1,FLOOR(ROUND(VLOOKUP($BP24,DADOS!$CL$5:$CM$10,2,FALSE)*IF($BQ24="",1,VLOOKUP($BQ24,DADOS!$CO$5:$CP$7,2,FALSE))*IF($BR24="",1,VLOOKUP($BR24,DADOS!$CR$5:$CS$15,2,FALSE)),4),1)),0),""))
BA25: =IF($AX25="","",IFERROR(IF(ROUND(VLOOKUP($AX25,DADOS!$CL$5:$CM$10,2,FALSE)*IF($AY25="",1,VLOOKUP($AY25,DADOS!$CO$5:$CP$7,2,FALSE))*IF($AZ25="",1,VLOOKUP($AZ25,DADOS!$CR$5:$CS$15,2,FALSE)),4)>0,MAX(1,FLOOR(ROUND(VLOOKUP($AX25,DADOS!$CL$5:$CM$10,2,FALSE)*IF($AY25="",1,VLOOKUP($AY25,DADOS!$CO$5:$CP$7,2,FALSE))*IF($AZ25="",1,VLOOKUP($AZ25,DADOS!$CR$5:$CS$15,2,FALSE)),4),1)),0),"")) | BG25: =IF($BD25="","",IFERROR(IF(ROUND(VLOOKUP($BD25,DADOS!$CL$5:$CM$10,2,FALSE)*IF($BE25="",1,VLOOKUP($BE25,DADOS!$CO$5:$CP$7,2,FALSE))*IF($BF25="",1,VLOOKUP($BF25,DADOS!$CR$5:$CS$15,2,FALSE)),4)>0,MAX(1,FLOOR(ROUND(VLOOKUP($BD25,DADOS!$CL$5:$CM$10,2,FALSE)*IF($BE25="",1,VLOOKUP($BE25,DADOS!$CO$5:$CP$7,2,FALSE))*IF($BF25="",1,VLOOKUP($BF25,DADOS!$CR$5:$CS$15,2,FALSE)),4),1)),0),"")) | BM25: =IF($BJ25="","",IFERROR(IF(ROUND(VLOOKUP($BJ25,DADOS!$CL$5:$CM$10,2,FALSE)*IF($BK25="",1,VLOOKUP($BK25,DADOS!$CO$5:$CP$7,2,FALSE))*IF($BL25="",1,VLOOKUP($BL25,DADOS!$CR$5:$CS$15,2,FALSE)),4)>0,MAX(1,FLOOR(ROUND(VLOOKUP($BJ25,DADOS!$CL$5:$CM$10,2,FALSE)*IF($BK25="",1,VLOOKUP($BK25,DADOS!$CO$5:$CP$7,2,FALSE))*IF($BL25="",1,VLOOKUP($BL25,DADOS!$CR$5:$CS$15,2,FALSE)),4),1)),0),"")) | BS25: =IF($BP25="","",IFERROR(IF(ROUND(VLOOKUP($BP25,DADOS!$CL$5:$CM$10,2,FALSE)*IF($BQ25="",1,VLOOKUP($BQ25,DADOS!$CO$5:$CP$7,2,FALSE))*IF($BR25="",1,VLOOKUP($BR25,DADOS!$CR$5:$CS$15,2,FALSE)),4)>0,MAX(1,FLOOR(ROUND(VLOOKUP($BP25,DADOS!$CL$5:$CM$10,2,FALSE)*IF($BQ25="",1,VLOOKUP($BQ25,DADOS!$CO$5:$CP$7,2,FALSE))*IF($BR25="",1,VLOOKUP($BR25,DADOS!$CR$5:$CS$15,2,FALSE)),4),1)),0),""))
Q26: HISTÓRIA | BA26: =IF($AX26="","",IFERROR(IF(ROUND(VLOOKUP($AX26,DADOS!$CL$5:$CM$10,2,FALSE)*IF($AY26="",1,VLOOKUP($AY26,DADOS!$CO$5:$CP$7,2,FALSE))*IF($AZ26="",1,VLOOKUP($AZ26,DADOS!$CR$5:$CS$15,2,FALSE)),4)>0,MAX(1,FLOOR(ROUND(VLOOKUP($AX26,DADOS!$CL$5:$CM$10,2,FALSE)*IF($AY26="",1,VLOOKUP($AY26,DADOS!$CO$5:$CP$7,2,FALSE))*IF($AZ26="",1,VLOOKUP($AZ26,DADOS!$CR$5:$CS$15,2,FALSE)),4),1)),0),"")) | BG26: =IF($BD26="","",IFERROR(IF(ROUND(VLOOKUP($BD26,DADOS!$CL$5:$CM$10,2,FALSE)*IF($BE26="",1,VLOOKUP($BE26,DADOS!$CO$5:$CP$7,2,FALSE))*IF($BF26="",1,VLOOKUP($BF26,DADOS!$CR$5:$CS$15,2,FALSE)),4)>0,MAX(1,FLOOR(ROUND(VLOOKUP($BD26,DADOS!$CL$5:$CM$10,2,FALSE)*IF($BE26="",1,VLOOKUP($BE26,DADOS!$CO$5:$CP$7,2,FALSE))*IF($BF26="",1,VLOOKUP($BF26,DADOS!$CR$5:$CS$15,2,FALSE)),4),1)),0),"")) | BM26: =IF($BJ26="","",IFERROR(IF(ROUND(VLOOKUP($BJ26,DADOS!$CL$5:$CM$10,2,FALSE)*IF($BK26="",1,VLOOKUP($BK26,DADOS!$CO$5:$CP$7,2,FALSE))*IF($BL26="",1,VLOOKUP($BL26,DADOS!$CR$5:$CS$15,2,FALSE)),4)>0,MAX(1,FLOOR(ROUND(VLOOKUP($BJ26,DADOS!$CL$5:$CM$10,2,FALSE)*IF($BK26="",1,VLOOKUP($BK26,DADOS!$CO$5:$CP$7,2,FALSE))*IF($BL26="",1,VLOOKUP($BL26,DADOS!$CR$5:$CS$15,2,FALSE)),4),1)),0),"")) | BS26: =IF($BP26="","",IFERROR(IF(ROUND(VLOOKUP($BP26,DADOS!$CL$5:$CM$10,2,FALSE)*IF($BQ26="",1,VLOOKUP($BQ26,DADOS!$CO$5:$CP$7,2,FALSE))*IF($BR26="",1,VLOOKUP($BR26,DADOS!$CR$5:$CS$15,2,FALSE)),4)>0,MAX(1,FLOOR(ROUND(VLOOKUP($BP26,DADOS!$CL$5:$CM$10,2,FALSE)*IF($BQ26="",1,VLOOKUP($BQ26,DADOS!$CO$5:$CP$7,2,FALSE))*IF($BR26="",1,VLOOKUP($BR26,DADOS!$CR$5:$CS$15,2,FALSE)),4),1)),0),""))
BA27: =IF($AX27="","",IFERROR(IF(ROUND(VLOOKUP($AX27,DADOS!$CL$5:$CM$10,2,FALSE)*IF($AY27="",1,VLOOKUP($AY27,DADOS!$CO$5:$CP$7,2,FALSE))*IF($AZ27="",1,VLOOKUP($AZ27,DADOS!$CR$5:$CS$15,2,FALSE)),4)>0,MAX(1,FLOOR(ROUND(VLOOKUP($AX27,DADOS!$CL$5:$CM$10,2,FALSE)*IF($AY27="",1,VLOOKUP($AY27,DADOS!$CO$5:$CP$7,2,FALSE))*IF($AZ27="",1,VLOOKUP($AZ27,DADOS!$CR$5:$CS$15,2,FALSE)),4),1)),0),"")) | BG27: =IF($BD27="","",IFERROR(IF(ROUND(VLOOKUP($BD27,DADOS!$CL$5:$CM$10,2,FALSE)*IF($BE27="",1,VLOOKUP($BE27,DADOS!$CO$5:$CP$7,2,FALSE))*IF($BF27="",1,VLOOKUP($BF27,DADOS!$CR$5:$CS$15,2,FALSE)),4)>0,MAX(1,FLOOR(ROUND(VLOOKUP($BD27,DADOS!$CL$5:$CM$10,2,FALSE)*IF($BE27="",1,VLOOKUP($BE27,DADOS!$CO$5:$CP$7,2,FALSE))*IF($BF27="",1,VLOOKUP($BF27,DADOS!$CR$5:$CS$15,2,FALSE)),4),1)),0),"")) | BM27: =IF($BJ27="","",IFERROR(IF(ROUND(VLOOKUP($BJ27,DADOS!$CL$5:$CM$10,2,FALSE)*IF($BK27="",1,VLOOKUP($BK27,DADOS!$CO$5:$CP$7,2,FALSE))*IF($BL27="",1,VLOOKUP($BL27,DADOS!$CR$5:$CS$15,2,FALSE)),4)>0,MAX(1,FLOOR(ROUND(VLOOKUP($BJ27,DADOS!$CL$5:$CM$10,2,FALSE)*IF($BK27="",1,VLOOKUP($BK27,DADOS!$CO$5:$CP$7,2,FALSE))*IF($BL27="",1,VLOOKUP($BL27,DADOS!$CR$5:$CS$15,2,FALSE)),4),1)),0),"")) | BS27: =IF($BP27="","",IFERROR(IF(ROUND(VLOOKUP($BP27,DADOS!$CL$5:$CM$10,2,FALSE)*IF($BQ27="",1,VLOOKUP($BQ27,DADOS!$CO$5:$CP$7,2,FALSE))*IF($BR27="",1,VLOOKUP($BR27,DADOS!$CR$5:$CS$15,2,FALSE)),4)>0,MAX(1,FLOOR(ROUND(VLOOKUP($BP27,DADOS!$CL$5:$CM$10,2,FALSE)*IF($BQ27="",1,VLOOKUP($BQ27,DADOS!$CO$5:$CP$7,2,FALSE))*IF($BR27="",1,VLOOKUP($BR27,DADOS!$CR$5:$CS$15,2,FALSE)),4),1)),0),""))
BA28: =IF($AX28="","",IFERROR(IF(ROUND(VLOOKUP($AX28,DADOS!$CL$5:$CM$10,2,FALSE)*IF($AY28="",1,VLOOKUP($AY28,DADOS!$CO$5:$CP$7,2,FALSE))*IF($AZ28="",1,VLOOKUP($AZ28,DADOS!$CR$5:$CS$15,2,FALSE)),4)>0,MAX(1,FLOOR(ROUND(VLOOKUP($AX28,DADOS!$CL$5:$CM$10,2,FALSE)*IF($AY28="",1,VLOOKUP($AY28,DADOS!$CO$5:$CP$7,2,FALSE))*IF($AZ28="",1,VLOOKUP($AZ28,DADOS!$CR$5:$CS$15,2,FALSE)),4),1)),0),"")) | BG28: =IF($BD28="","",IFERROR(IF(ROUND(VLOOKUP($BD28,DADOS!$CL$5:$CM$10,2,FALSE)*IF($BE28="",1,VLOOKUP($BE28,DADOS!$CO$5:$CP$7,2,FALSE))*IF($BF28="",1,VLOOKUP($BF28,DADOS!$CR$5:$CS$15,2,FALSE)),4)>0,MAX(1,FLOOR(ROUND(VLOOKUP($BD28,DADOS!$CL$5:$CM$10,2,FALSE)*IF($BE28="",1,VLOOKUP($BE28,DADOS!$CO$5:$CP$7,2,FALSE))*IF($BF28="",1,VLOOKUP($BF28,DADOS!$CR$5:$CS$15,2,FALSE)),4),1)),0),"")) | BM28: =IF($BJ28="","",IFERROR(IF(ROUND(VLOOKUP($BJ28,DADOS!$CL$5:$CM$10,2,FALSE)*IF($BK28="",1,VLOOKUP($BK28,DADOS!$CO$5:$CP$7,2,FALSE))*IF($BL28="",1,VLOOKUP($BL28,DADOS!$CR$5:$CS$15,2,FALSE)),4)>0,MAX(1,FLOOR(ROUND(VLOOKUP($BJ28,DADOS!$CL$5:$CM$10,2,FALSE)*IF($BK28="",1,VLOOKUP($BK28,DADOS!$CO$5:$CP$7,2,FALSE))*IF($BL28="",1,VLOOKUP($BL28,DADOS!$CR$5:$CS$15,2,FALSE)),4),1)),0),"")) | BS28: =IF($BP28="","",IFERROR(IF(ROUND(VLOOKUP($BP28,DADOS!$CL$5:$CM$10,2,FALSE)*IF($BQ28="",1,VLOOKUP($BQ28,DADOS!$CO$5:$CP$7,2,FALSE))*IF($BR28="",1,VLOOKUP($BR28,DADOS!$CR$5:$CS$15,2,FALSE)),4)>0,MAX(1,FLOOR(ROUND(VLOOKUP($BP28,DADOS!$CL$5:$CM$10,2,FALSE)*IF($BQ28="",1,VLOOKUP($BQ28,DADOS!$CO$5:$CP$7,2,FALSE))*IF($BR28="",1,VLOOKUP($BR28,DADOS!$CR$5:$CS$15,2,FALSE)),4),1)),0),""))
BA29: =IF($AX29="","",IFERROR(IF(ROUND(VLOOKUP($AX29,DADOS!$CL$5:$CM$10,2,FALSE)*IF($AY29="",1,VLOOKUP($AY29,DADOS!$CO$5:$CP$7,2,FALSE))*IF($AZ29="",1,VLOOKUP($AZ29,DADOS!$CR$5:$CS$15,2,FALSE)),4)>0,MAX(1,FLOOR(ROUND(VLOOKUP($AX29,DADOS!$CL$5:$CM$10,2,FALSE)*IF($AY29="",1,VLOOKUP($AY29,DADOS!$CO$5:$CP$7,2,FALSE))*IF($AZ29="",1,VLOOKUP($AZ29,DADOS!$CR$5:$CS$15,2,FALSE)),4),1)),0),"")) | BG29: =IF($BD29="","",IFERROR(IF(ROUND(VLOOKUP($BD29,DADOS!$CL$5:$CM$10,2,FALSE)*IF($BE29="",1,VLOOKUP($BE29,DADOS!$CO$5:$CP$7,2,FALSE))*IF($BF29="",1,VLOOKUP($BF29,DADOS!$CR$5:$CS$15,2,FALSE)),4)>0,MAX(1,FLOOR(ROUND(VLOOKUP($BD29,DADOS!$CL$5:$CM$10,2,FALSE)*IF($BE29="",1,VLOOKUP($BE29,DADOS!$CO$5:$CP$7,2,FALSE))*IF($BF29="",1,VLOOKUP($BF29,DADOS!$CR$5:$CS$15,2,FALSE)),4),1)),0),"")) | BM29: =IF($BJ29="","",IFERROR(IF(ROUND(VLOOKUP($BJ29,DADOS!$CL$5:$CM$10,2,FALSE)*IF($BK29="",1,VLOOKUP($BK29,DADOS!$CO$5:$CP$7,2,FALSE))*IF($BL29="",1,VLOOKUP($BL29,DADOS!$CR$5:$CS$15,2,FALSE)),4)>0,MAX(1,FLOOR(ROUND(VLOOKUP($BJ29,DADOS!$CL$5:$CM$10,2,FALSE)*IF($BK29="",1,VLOOKUP($BK29,DADOS!$CO$5:$CP$7,2,FALSE))*IF($BL29="",1,VLOOKUP($BL29,DADOS!$CR$5:$CS$15,2,FALSE)),4),1)),0),"")) | BS29: =IF($BP29="","",IFERROR(IF(ROUND(VLOOKUP($BP29,DADOS!$CL$5:$CM$10,2,FALSE)*IF($BQ29="",1,VLOOKUP($BQ29,DADOS!$CO$5:$CP$7,2,FALSE))*IF($BR29="",1,VLOOKUP($BR29,DADOS!$CR$5:$CS$15,2,FALSE)),4)>0,MAX(1,FLOOR(ROUND(VLOOKUP($BP29,DADOS!$CL$5:$CM$10,2,FALSE)*IF($BQ29="",1,VLOOKUP($BQ29,DADOS!$CO$5:$CP$7,2,FALSE))*IF($BR29="",1,VLOOKUP($BR29,DADOS!$CR$5:$CS$15,2,FALSE)),4),1)),0),""))
D30: PERSONALIDADE | BA30: =IF($AX30="","",IFERROR(IF(ROUND(VLOOKUP($AX30,DADOS!$CL$5:$CM$10,2,FALSE)*IF($AY30="",1,VLOOKUP($AY30,DADOS!$CO$5:$CP$7,2,FALSE))*IF($AZ30="",1,VLOOKUP($AZ30,DADOS!$CR$5:$CS$15,2,FALSE)),4)>0,MAX(1,FLOOR(ROUND(VLOOKUP($AX30,DADOS!$CL$5:$CM$10,2,FALSE)*IF($AY30="",1,VLOOKUP($AY30,DADOS!$CO$5:$CP$7,2,FALSE))*IF($AZ30="",1,VLOOKUP($AZ30,DADOS!$CR$5:$CS$15,2,FALSE)),4),1)),0),"")) | BG30: =IF($BD30="","",IFERROR(IF(ROUND(VLOOKUP($BD30,DADOS!$CL$5:$CM$10,2,FALSE)*IF($BE30="",1,VLOOKUP($BE30,DADOS!$CO$5:$CP$7,2,FALSE))*IF($BF30="",1,VLOOKUP($BF30,DADOS!$CR$5:$CS$15,2,FALSE)),4)>0,MAX(1,FLOOR(ROUND(VLOOKUP($BD30,DADOS!$CL$5:$CM$10,2,FALSE)*IF($BE30="",1,VLOOKUP($BE30,DADOS!$CO$5:$CP$7,2,FALSE))*IF($BF30="",1,VLOOKUP($BF30,DADOS!$CR$5:$CS$15,2,FALSE)),4),1)),0),"")) | BM30: =IF($BJ30="","",IFERROR(IF(ROUND(VLOOKUP($BJ30,DADOS!$CL$5:$CM$10,2,FALSE)*IF($BK30="",1,VLOOKUP($BK30,DADOS!$CO$5:$CP$7,2,FALSE))*IF($BL30="",1,VLOOKUP($BL30,DADOS!$CR$5:$CS$15,2,FALSE)),4)>0,MAX(1,FLOOR(ROUND(VLOOKUP($BJ30,DADOS!$CL$5:$CM$10,2,FALSE)*IF($BK30="",1,VLOOKUP($BK30,DADOS!$CO$5:$CP$7,2,FALSE))*IF($BL30="",1,VLOOKUP($BL30,DADOS!$CR$5:$CS$15,2,FALSE)),4),1)),0),"")) | BS30: =IF($BP30="","",IFERROR(IF(ROUND(VLOOKUP($BP30,DADOS!$CL$5:$CM$10,2,FALSE)*IF($BQ30="",1,VLOOKUP($BQ30,DADOS!$CO$5:$CP$7,2,FALSE))*IF($BR30="",1,VLOOKUP($BR30,DADOS!$CR$5:$CS$15,2,FALSE)),4)>0,MAX(1,FLOOR(ROUND(VLOOKUP($BP30,DADOS!$CL$5:$CM$10,2,FALSE)*IF($BQ30="",1,VLOOKUP($BQ30,DADOS!$CO$5:$CP$7,2,FALSE))*IF($BR30="",1,VLOOKUP($BR30,DADOS!$CR$5:$CS$15,2,FALSE)),4),1)),0),""))
BA31: =IF($AX31="","",IFERROR(IF(ROUND(VLOOKUP($AX31,DADOS!$CL$5:$CM$10,2,FALSE)*IF($AY31="",1,VLOOKUP($AY31,DADOS!$CO$5:$CP$7,2,FALSE))*IF($AZ31="",1,VLOOKUP($AZ31,DADOS!$CR$5:$CS$15,2,FALSE)),4)>0,MAX(1,FLOOR(ROUND(VLOOKUP($AX31,DADOS!$CL$5:$CM$10,2,FALSE)*IF($AY31="",1,VLOOKUP($AY31,DADOS!$CO$5:$CP$7,2,FALSE))*IF($AZ31="",1,VLOOKUP($AZ31,DADOS!$CR$5:$CS$15,2,FALSE)),4),1)),0),"")) | BG31: =IF($BD31="","",IFERROR(IF(ROUND(VLOOKUP($BD31,DADOS!$CL$5:$CM$10,2,FALSE)*IF($BE31="",1,VLOOKUP($BE31,DADOS!$CO$5:$CP$7,2,FALSE))*IF($BF31="",1,VLOOKUP($BF31,DADOS!$CR$5:$CS$15,2,FALSE)),4)>0,MAX(1,FLOOR(ROUND(VLOOKUP($BD31,DADOS!$CL$5:$CM$10,2,FALSE)*IF($BE31="",1,VLOOKUP($BE31,DADOS!$CO$5:$CP$7,2,FALSE))*IF($BF31="",1,VLOOKUP($BF31,DADOS!$CR$5:$CS$15,2,FALSE)),4),1)),0),"")) | BM31: =IF($BJ31="","",IFERROR(IF(ROUND(VLOOKUP($BJ31,DADOS!$CL$5:$CM$10,2,FALSE)*IF($BK31="",1,VLOOKUP($BK31,DADOS!$CO$5:$CP$7,2,FALSE))*IF($BL31="",1,VLOOKUP($BL31,DADOS!$CR$5:$CS$15,2,FALSE)),4)>0,MAX(1,FLOOR(ROUND(VLOOKUP($BJ31,DADOS!$CL$5:$CM$10,2,FALSE)*IF($BK31="",1,VLOOKUP($BK31,DADOS!$CO$5:$CP$7,2,FALSE))*IF($BL31="",1,VLOOKUP($BL31,DADOS!$CR$5:$CS$15,2,FALSE)),4),1)),0),"")) | BS31: =IF($BP31="","",IFERROR(IF(ROUND(VLOOKUP($BP31,DADOS!$CL$5:$CM$10,2,FALSE)*IF($BQ31="",1,VLOOKUP($BQ31,DADOS!$CO$5:$CP$7,2,FALSE))*IF($BR31="",1,VLOOKUP($BR31,DADOS!$CR$5:$CS$15,2,FALSE)),4)>0,MAX(1,FLOOR(ROUND(VLOOKUP($BP31,DADOS!$CL$5:$CM$10,2,FALSE)*IF($BQ31="",1,VLOOKUP($BQ31,DADOS!$CO$5:$CP$7,2,FALSE))*IF($BR31="",1,VLOOKUP($BR31,DADOS!$CR$5:$CS$15,2,FALSE)),4),1)),0),""))
BA32: =IF($AX32="","",IFERROR(IF(ROUND(VLOOKUP($AX32,DADOS!$CL$5:$CM$10,2,FALSE)*IF($AY32="",1,VLOOKUP($AY32,DADOS!$CO$5:$CP$7,2,FALSE))*IF($AZ32="",1,VLOOKUP($AZ32,DADOS!$CR$5:$CS$15,2,FALSE)),4)>0,MAX(1,FLOOR(ROUND(VLOOKUP($AX32,DADOS!$CL$5:$CM$10,2,FALSE)*IF($AY32="",1,VLOOKUP($AY32,DADOS!$CO$5:$CP$7,2,FALSE))*IF($AZ32="",1,VLOOKUP($AZ32,DADOS!$CR$5:$CS$15,2,FALSE)),4),1)),0),"")) | BG32: =IF($BD32="","",IFERROR(IF(ROUND(VLOOKUP($BD32,DADOS!$CL$5:$CM$10,2,FALSE)*IF($BE32="",1,VLOOKUP($BE32,DADOS!$CO$5:$CP$7,2,FALSE))*IF($BF32="",1,VLOOKUP($BF32,DADOS!$CR$5:$CS$15,2,FALSE)),4)>0,MAX(1,FLOOR(ROUND(VLOOKUP($BD32,DADOS!$CL$5:$CM$10,2,FALSE)*IF($BE32="",1,VLOOKUP($BE32,DADOS!$CO$5:$CP$7,2,FALSE))*IF($BF32="",1,VLOOKUP($BF32,DADOS!$CR$5:$CS$15,2,FALSE)),4),1)),0),"")) | BM32: =IF($BJ32="","",IFERROR(IF(ROUND(VLOOKUP($BJ32,DADOS!$CL$5:$CM$10,2,FALSE)*IF($BK32="",1,VLOOKUP($BK32,DADOS!$CO$5:$CP$7,2,FALSE))*IF($BL32="",1,VLOOKUP($BL32,DADOS!$CR$5:$CS$15,2,FALSE)),4)>0,MAX(1,FLOOR(ROUND(VLOOKUP($BJ32,DADOS!$CL$5:$CM$10,2,FALSE)*IF($BK32="",1,VLOOKUP($BK32,DADOS!$CO$5:$CP$7,2,FALSE))*IF($BL32="",1,VLOOKUP($BL32,DADOS!$CR$5:$CS$15,2,FALSE)),4),1)),0),"")) | BS32: =IF($BP32="","",IFERROR(IF(ROUND(VLOOKUP($BP32,DADOS!$CL$5:$CM$10,2,FALSE)*IF($BQ32="",1,VLOOKUP($BQ32,DADOS!$CO$5:$CP$7,2,FALSE))*IF($BR32="",1,VLOOKUP($BR32,DADOS!$CR$5:$CS$15,2,FALSE)),4)>0,MAX(1,FLOOR(ROUND(VLOOKUP($BP32,DADOS!$CL$5:$CM$10,2,FALSE)*IF($BQ32="",1,VLOOKUP($BQ32,DADOS!$CO$5:$CP$7,2,FALSE))*IF($BR32="",1,VLOOKUP($BR32,DADOS!$CR$5:$CS$15,2,FALSE)),4),1)),0),""))
A33: FICHA PESSOAL | BA33: =IF($AX33="","",IFERROR(IF(ROUND(VLOOKUP($AX33,DADOS!$CL$5:$CM$10,2,FALSE)*IF($AY33="",1,VLOOKUP($AY33,DADOS!$CO$5:$CP$7,2,FALSE))*IF($AZ33="",1,VLOOKUP($AZ33,DADOS!$CR$5:$CS$15,2,FALSE)),4)>0,MAX(1,FLOOR(ROUND(VLOOKUP($AX33,DADOS!$CL$5:$CM$10,2,FALSE)*IF($AY33="",1,VLOOKUP($AY33,DADOS!$CO$5:$CP$7,2,FALSE))*IF($AZ33="",1,VLOOKUP($AZ33,DADOS!$CR$5:$CS$15,2,FALSE)),4),1)),0),"")) | BG33: =IF($BD33="","",IFERROR(IF(ROUND(VLOOKUP($BD33,DADOS!$CL$5:$CM$10,2,FALSE)*IF($BE33="",1,VLOOKUP($BE33,DADOS!$CO$5:$CP$7,2,FALSE))*IF($BF33="",1,VLOOKUP($BF33,DADOS!$CR$5:$CS$15,2,FALSE)),4)>0,MAX(1,FLOOR(ROUND(VLOOKUP($BD33,DADOS!$CL$5:$CM$10,2,FALSE)*IF($BE33="",1,VLOOKUP($BE33,DADOS!$CO$5:$CP$7,2,FALSE))*IF($BF33="",1,VLOOKUP($BF33,DADOS!$CR$5:$CS$15,2,FALSE)),4),1)),0),"")) | BM33: =IF($BJ33="","",IFERROR(IF(ROUND(VLOOKUP($BJ33,DADOS!$CL$5:$CM$10,2,FALSE)*IF($BK33="",1,VLOOKUP($BK33,DADOS!$CO$5:$CP$7,2,FALSE))*IF($BL33="",1,VLOOKUP($BL33,DADOS!$CR$5:$CS$15,2,FALSE)),4)>0,MAX(1,FLOOR(ROUND(VLOOKUP($BJ33,DADOS!$CL$5:$CM$10,2,FALSE)*IF($BK33="",1,VLOOKUP($BK33,DADOS!$CO$5:$CP$7,2,FALSE))*IF($BL33="",1,VLOOKUP($BL33,DADOS!$CR$5:$CS$15,2,FALSE)),4),1)),0),"")) | BS33: =IF($BP33="","",IFERROR(IF(ROUND(VLOOKUP($BP33,DADOS!$CL$5:$CM$10,2,FALSE)*IF($BQ33="",1,VLOOKUP($BQ33,DADOS!$CO$5:$CP$7,2,FALSE))*IF($BR33="",1,VLOOKUP($BR33,DADOS!$CR$5:$CS$15,2,FALSE)),4)>0,MAX(1,FLOOR(ROUND(VLOOKUP($BP33,DADOS!$CL$5:$CM$10,2,FALSE)*IF($BQ33="",1,VLOOKUP($BQ33,DADOS!$CO$5:$CP$7,2,FALSE))*IF($BR33="",1,VLOOKUP($BR33,DADOS!$CR$5:$CS$15,2,FALSE)),4),1)),0),""))
Q34: LAÇOS E ANOTAÇÕES | BA34: =IF($AX34="","",IFERROR(IF(ROUND(VLOOKUP($AX34,DADOS!$CL$5:$CM$10,2,FALSE)*IF($AY34="",1,VLOOKUP($AY34,DADOS!$CO$5:$CP$7,2,FALSE))*IF($AZ34="",1,VLOOKUP($AZ34,DADOS!$CR$5:$CS$15,2,FALSE)),4)>0,MAX(1,FLOOR(ROUND(VLOOKUP($AX34,DADOS!$CL$5:$CM$10,2,FALSE)*IF($AY34="",1,VLOOKUP($AY34,DADOS!$CO$5:$CP$7,2,FALSE))*IF($AZ34="",1,VLOOKUP($AZ34,DADOS!$CR$5:$CS$15,2,FALSE)),4),1)),0),"")) | BG34: =IF($BD34="","",IFERROR(IF(ROUND(VLOOKUP($BD34,DADOS!$CL$5:$CM$10,2,FALSE)*IF($BE34="",1,VLOOKUP($BE34,DADOS!$CO$5:$CP$7,2,FALSE))*IF($BF34="",1,VLOOKUP($BF34,DADOS!$CR$5:$CS$15,2,FALSE)),4)>0,MAX(1,FLOOR(ROUND(VLOOKUP($BD34,DADOS!$CL$5:$CM$10,2,FALSE)*IF($BE34="",1,VLOOKUP($BE34,DADOS!$CO$5:$CP$7,2,FALSE))*IF($BF34="",1,VLOOKUP($BF34,DADOS!$CR$5:$CS$15,2,FALSE)),4),1)),0),"")) | BM34: =IF($BJ34="","",IFERROR(IF(ROUND(VLOOKUP($BJ34,DADOS!$CL$5:$CM$10,2,FALSE)*IF($BK34="",1,VLOOKUP($BK34,DADOS!$CO$5:$CP$7,2,FALSE))*IF($BL34="",1,VLOOKUP($BL34,DADOS!$CR$5:$CS$15,2,FALSE)),4)>0,MAX(1,FLOOR(ROUND(VLOOKUP($BJ34,DADOS!$CL$5:$CM$10,2,FALSE)*IF($BK34="",1,VLOOKUP($BK34,DADOS!$CO$5:$CP$7,2,FALSE))*IF($BL34="",1,VLOOKUP($BL34,DADOS!$CR$5:$CS$15,2,FALSE)),4),1)),0),"")) | BS34: =IF($BP34="","",IFERROR(IF(ROUND(VLOOKUP($BP34,DADOS!$CL$5:$CM$10,2,FALSE)*IF($BQ34="",1,VLOOKUP($BQ34,DADOS!$CO$5:$CP$7,2,FALSE))*IF($BR34="",1,VLOOKUP($BR34,DADOS!$CR$5:$CS$15,2,FALSE)),4)>0,MAX(1,FLOOR(ROUND(VLOOKUP($BP34,DADOS!$CL$5:$CM$10,2,FALSE)*IF($BQ34="",1,VLOOKUP($BQ34,DADOS!$CO$5:$CP$7,2,FALSE))*IF($BR34="",1,VLOOKUP($BR34,DADOS!$CR$5:$CS$15,2,FALSE)),4),1)),0),""))
BA35: =IF($AX35="","",IFERROR(IF(ROUND(VLOOKUP($AX35,DADOS!$CL$5:$CM$10,2,FALSE)*IF($AY35="",1,VLOOKUP($AY35,DADOS!$CO$5:$CP$7,2,FALSE))*IF($AZ35="",1,VLOOKUP($AZ35,DADOS!$CR$5:$CS$15,2,FALSE)),4)>0,MAX(1,FLOOR(ROUND(VLOOKUP($AX35,DADOS!$CL$5:$CM$10,2,FALSE)*IF($AY35="",1,VLOOKUP($AY35,DADOS!$CO$5:$CP$7,2,FALSE))*IF($AZ35="",1,VLOOKUP($AZ35,DADOS!$CR$5:$CS$15,2,FALSE)),4),1)),0),"")) | BG35: =IF($BD35="","",IFERROR(IF(ROUND(VLOOKUP($BD35,DADOS!$CL$5:$CM$10,2,FALSE)*IF($BE35="",1,VLOOKUP($BE35,DADOS!$CO$5:$CP$7,2,FALSE))*IF($BF35="",1,VLOOKUP($BF35,DADOS!$CR$5:$CS$15,2,FALSE)),4)>0,MAX(1,FLOOR(ROUND(VLOOKUP($BD35,DADOS!$CL$5:$CM$10,2,FALSE)*IF($BE35="",1,VLOOKUP($BE35,DADOS!$CO$5:$CP$7,2,FALSE))*IF($BF35="",1,VLOOKUP($BF35,DADOS!$CR$5:$CS$15,2,FALSE)),4),1)),0),"")) | BM35: =IF($BJ35="","",IFERROR(IF(ROUND(VLOOKUP($BJ35,DADOS!$CL$5:$CM$10,2,FALSE)*IF($BK35="",1,VLOOKUP($BK35,DADOS!$CO$5:$CP$7,2,FALSE))*IF($BL35="",1,VLOOKUP($BL35,DADOS!$CR$5:$CS$15,2,FALSE)),4)>0,MAX(1,FLOOR(ROUND(VLOOKUP($BJ35,DADOS!$CL$5:$CM$10,2,FALSE)*IF($BK35="",1,VLOOKUP($BK35,DADOS!$CO$5:$CP$7,2,FALSE))*IF($BL35="",1,VLOOKUP($BL35,DADOS!$CR$5:$CS$15,2,FALSE)),4),1)),0),"")) | BS35: =IF($BP35="","",IFERROR(IF(ROUND(VLOOKUP($BP35,DADOS!$CL$5:$CM$10,2,FALSE)*IF($BQ35="",1,VLOOKUP($BQ35,DADOS!$CO$5:$CP$7,2,FALSE))*IF($BR35="",1,VLOOKUP($BR35,DADOS!$CR$5:$CS$15,2,FALSE)),4)>0,MAX(1,FLOOR(ROUND(VLOOKUP($BP35,DADOS!$CL$5:$CM$10,2,FALSE)*IF($BQ35="",1,VLOOKUP($BQ35,DADOS!$CO$5:$CP$7,2,FALSE))*IF($BR35="",1,VLOOKUP($BR35,DADOS!$CR$5:$CS$15,2,FALSE)),4),1)),0),""))
BA36: =IF($AX36="","",IFERROR(IF(ROUND(VLOOKUP($AX36,DADOS!$CL$5:$CM$10,2,FALSE)*IF($AY36="",1,VLOOKUP($AY36,DADOS!$CO$5:$CP$7,2,FALSE))*IF($AZ36="",1,VLOOKUP($AZ36,DADOS!$CR$5:$CS$15,2,FALSE)),4)>0,MAX(1,FLOOR(ROUND(VLOOKUP($AX36,DADOS!$CL$5:$CM$10,2,FALSE)*IF($AY36="",1,VLOOKUP($AY36,DADOS!$CO$5:$CP$7,2,FALSE))*IF($AZ36="",1,VLOOKUP($AZ36,DADOS!$CR$5:$CS$15,2,FALSE)),4),1)),0),"")) | BG36: =IF($BD36="","",IFERROR(IF(ROUND(VLOOKUP($BD36,DADOS!$CL$5:$CM$10,2,FALSE)*IF($BE36="",1,VLOOKUP($BE36,DADOS!$CO$5:$CP$7,2,FALSE))*IF($BF36="",1,VLOOKUP($BF36,DADOS!$CR$5:$CS$15,2,FALSE)),4)>0,MAX(1,FLOOR(ROUND(VLOOKUP($BD36,DADOS!$CL$5:$CM$10,2,FALSE)*IF($BE36="",1,VLOOKUP($BE36,DADOS!$CO$5:$CP$7,2,FALSE))*IF($BF36="",1,VLOOKUP($BF36,DADOS!$CR$5:$CS$15,2,FALSE)),4),1)),0),"")) | BM36: =IF($BJ36="","",IFERROR(IF(ROUND(VLOOKUP($BJ36,DADOS!$CL$5:$CM$10,2,FALSE)*IF($BK36="",1,VLOOKUP($BK36,DADOS!$CO$5:$CP$7,2,FALSE))*IF($BL36="",1,VLOOKUP($BL36,DADOS!$CR$5:$CS$15,2,FALSE)),4)>0,MAX(1,FLOOR(ROUND(VLOOKUP($BJ36,DADOS!$CL$5:$CM$10,2,FALSE)*IF($BK36="",1,VLOOKUP($BK36,DADOS!$CO$5:$CP$7,2,FALSE))*IF($BL36="",1,VLOOKUP($BL36,DADOS!$CR$5:$CS$15,2,FALSE)),4),1)),0),"")) | BS36: =IF($BP36="","",IFERROR(IF(ROUND(VLOOKUP($BP36,DADOS!$CL$5:$CM$10,2,FALSE)*IF($BQ36="",1,VLOOKUP($BQ36,DADOS!$CO$5:$CP$7,2,FALSE))*IF($BR36="",1,VLOOKUP($BR36,DADOS!$CR$5:$CS$15,2,FALSE)),4)>0,MAX(1,FLOOR(ROUND(VLOOKUP($BP36,DADOS!$CL$5:$CM$10,2,FALSE)*IF($BQ36="",1,VLOOKUP($BQ36,DADOS!$CO$5:$CP$7,2,FALSE))*IF($BR36="",1,VLOOKUP($BR36,DADOS!$CR$5:$CS$15,2,FALSE)),4),1)),0),""))
BA37: =IF($AX37="","",IFERROR(IF(ROUND(VLOOKUP($AX37,DADOS!$CL$5:$CM$10,2,FALSE)*IF($AY37="",1,VLOOKUP($AY37,DADOS!$CO$5:$CP$7,2,FALSE))*IF($AZ37="",1,VLOOKUP($AZ37,DADOS!$CR$5:$CS$15,2,FALSE)),4)>0,MAX(1,FLOOR(ROUND(VLOOKUP($AX37,DADOS!$CL$5:$CM$10,2,FALSE)*IF($AY37="",1,VLOOKUP($AY37,DADOS!$CO$5:$CP$7,2,FALSE))*IF($AZ37="",1,VLOOKUP($AZ37,DADOS!$CR$5:$CS$15,2,FALSE)),4),1)),0),"")) | BG37: =IF($BD37="","",IFERROR(IF(ROUND(VLOOKUP($BD37,DADOS!$CL$5:$CM$10,2,FALSE)*IF($BE37="",1,VLOOKUP($BE37,DADOS!$CO$5:$CP$7,2,FALSE))*IF($BF37="",1,VLOOKUP($BF37,DADOS!$CR$5:$CS$15,2,FALSE)),4)>0,MAX(1,FLOOR(ROUND(VLOOKUP($BD37,DADOS!$CL$5:$CM$10,2,FALSE)*IF($BE37="",1,VLOOKUP($BE37,DADOS!$CO$5:$CP$7,2,FALSE))*IF($BF37="",1,VLOOKUP($BF37,DADOS!$CR$5:$CS$15,2,FALSE)),4),1)),0),"")) | BM37: =IF($BJ37="","",IFERROR(IF(ROUND(VLOOKUP($BJ37,DADOS!$CL$5:$CM$10,2,FALSE)*IF($BK37="",1,VLOOKUP($BK37,DADOS!$CO$5:$CP$7,2,FALSE))*IF($BL37="",1,VLOOKUP($BL37,DADOS!$CR$5:$CS$15,2,FALSE)),4)>0,MAX(1,FLOOR(ROUND(VLOOKUP($BJ37,DADOS!$CL$5:$CM$10,2,FALSE)*IF($BK37="",1,VLOOKUP($BK37,DADOS!$CO$5:$CP$7,2,FALSE))*IF($BL37="",1,VLOOKUP($BL37,DADOS!$CR$5:$CS$15,2,FALSE)),4),1)),0),"")) | BS37: =IF($BP37="","",IFERROR(IF(ROUND(VLOOKUP($BP37,DADOS!$CL$5:$CM$10,2,FALSE)*IF($BQ37="",1,VLOOKUP($BQ37,DADOS!$CO$5:$CP$7,2,FALSE))*IF($BR37="",1,VLOOKUP($BR37,DADOS!$CR$5:$CS$15,2,FALSE)),4)>0,MAX(1,FLOOR(ROUND(VLOOKUP($BP37,DADOS!$CL$5:$CM$10,2,FALSE)*IF($BQ37="",1,VLOOKUP($BQ37,DADOS!$CO$5:$CP$7,2,FALSE))*IF($BR37="",1,VLOOKUP($BR37,DADOS!$CR$5:$CS$15,2,FALSE)),4),1)),0),""))
BA38: =IF($AX38="","",IFERROR(IF(ROUND(VLOOKUP($AX38,DADOS!$CL$5:$CM$10,2,FALSE)*IF($AY38="",1,VLOOKUP($AY38,DADOS!$CO$5:$CP$7,2,FALSE))*IF($AZ38="",1,VLOOKUP($AZ38,DADOS!$CR$5:$CS$15,2,FALSE)),4)>0,MAX(1,FLOOR(ROUND(VLOOKUP($AX38,DADOS!$CL$5:$CM$10,2,FALSE)*IF($AY38="",1,VLOOKUP($AY38,DADOS!$CO$5:$CP$7,2,FALSE))*IF($AZ38="",1,VLOOKUP($AZ38,DADOS!$CR$5:$CS$15,2,FALSE)),4),1)),0),"")) | BG38: =IF($BD38="","",IFERROR(IF(ROUND(VLOOKUP($BD38,DADOS!$CL$5:$CM$10,2,FALSE)*IF($BE38="",1,VLOOKUP($BE38,DADOS!$CO$5:$CP$7,2,FALSE))*IF($BF38="",1,VLOOKUP($BF38,DADOS!$CR$5:$CS$15,2,FALSE)),4)>0,MAX(1,FLOOR(ROUND(VLOOKUP($BD38,DADOS!$CL$5:$CM$10,2,FALSE)*IF($BE38="",1,VLOOKUP($BE38,DADOS!$CO$5:$CP$7,2,FALSE))*IF($BF38="",1,VLOOKUP($BF38,DADOS!$CR$5:$CS$15,2,FALSE)),4),1)),0),"")) | BM38: =IF($BJ38="","",IFERROR(IF(ROUND(VLOOKUP($BJ38,DADOS!$CL$5:$CM$10,2,FALSE)*IF($BK38="",1,VLOOKUP($BK38,DADOS!$CO$5:$CP$7,2,FALSE))*IF($BL38="",1,VLOOKUP($BL38,DADOS!$CR$5:$CS$15,2,FALSE)),4)>0,MAX(1,FLOOR(ROUND(VLOOKUP($BJ38,DADOS!$CL$5:$CM$10,2,FALSE)*IF($BK38="",1,VLOOKUP($BK38,DADOS!$CO$5:$CP$7,2,FALSE))*IF($BL38="",1,VLOOKUP($BL38,DADOS!$CR$5:$CS$15,2,FALSE)),4),1)),0),"")) | BS38: =IF($BP38="","",IFERROR(IF(ROUND(VLOOKUP($BP38,DADOS!$CL$5:$CM$10,2,FALSE)*IF($BQ38="",1,VLOOKUP($BQ38,DADOS!$CO$5:$CP$7,2,FALSE))*IF($BR38="",1,VLOOKUP($BR38,DADOS!$CR$5:$CS$15,2,FALSE)),4)>0,MAX(1,FLOOR(ROUND(VLOOKUP($BP38,DADOS!$CL$5:$CM$10,2,FALSE)*IF($BQ38="",1,VLOOKUP($BQ38,DADOS!$CO$5:$CP$7,2,FALSE))*IF($BR38="",1,VLOOKUP($BR38,DADOS!$CR$5:$CS$15,2,FALSE)),4),1)),0),""))
BA39: =IF($AX39="","",IFERROR(IF(ROUND(VLOOKUP($AX39,DADOS!$CL$5:$CM$10,2,FALSE)*IF($AY39="",1,VLOOKUP($AY39,DADOS!$CO$5:$CP$7,2,FALSE))*IF($AZ39="",1,VLOOKUP($AZ39,DADOS!$CR$5:$CS$15,2,FALSE)),4)>0,MAX(1,FLOOR(ROUND(VLOOKUP($AX39,DADOS!$CL$5:$CM$10,2,FALSE)*IF($AY39="",1,VLOOKUP($AY39,DADOS!$CO$5:$CP$7,2,FALSE))*IF($AZ39="",1,VLOOKUP($AZ39,DADOS!$CR$5:$CS$15,2,FALSE)),4),1)),0),"")) | BG39: =IF($BD39="","",IFERROR(IF(ROUND(VLOOKUP($BD39,DADOS!$CL$5:$CM$10,2,FALSE)*IF($BE39="",1,VLOOKUP($BE39,DADOS!$CO$5:$CP$7,2,FALSE))*IF($BF39="",1,VLOOKUP($BF39,DADOS!$CR$5:$CS$15,2,FALSE)),4)>0,MAX(1,FLOOR(ROUND(VLOOKUP($BD39,DADOS!$CL$5:$CM$10,2,FALSE)*IF($BE39="",1,VLOOKUP($BE39,DADOS!$CO$5:$CP$7,2,FALSE))*IF($BF39="",1,VLOOKUP($BF39,DADOS!$CR$5:$CS$15,2,FALSE)),4),1)),0),"")) | BM39: =IF($BJ39="","",IFERROR(IF(ROUND(VLOOKUP($BJ39,DADOS!$CL$5:$CM$10,2,FALSE)*IF($BK39="",1,VLOOKUP($BK39,DADOS!$CO$5:$CP$7,2,FALSE))*IF($BL39="",1,VLOOKUP($BL39,DADOS!$CR$5:$CS$15,2,FALSE)),4)>0,MAX(1,FLOOR(ROUND(VLOOKUP($BJ39,DADOS!$CL$5:$CM$10,2,FALSE)*IF($BK39="",1,VLOOKUP($BK39,DADOS!$CO$5:$CP$7,2,FALSE))*IF($BL39="",1,VLOOKUP($BL39,DADOS!$CR$5:$CS$15,2,FALSE)),4),1)),0),"")) | BS39: =IF($BP39="","",IFERROR(IF(ROUND(VLOOKUP($BP39,DADOS!$CL$5:$CM$10,2,FALSE)*IF($BQ39="",1,VLOOKUP($BQ39,DADOS!$CO$5:$CP$7,2,FALSE))*IF($BR39="",1,VLOOKUP($BR39,DADOS!$CR$5:$CS$15,2,FALSE)),4)>0,MAX(1,FLOOR(ROUND(VLOOKUP($BP39,DADOS!$CL$5:$CM$10,2,FALSE)*IF($BQ39="",1,VLOOKUP($BQ39,DADOS!$CO$5:$CP$7,2,FALSE))*IF($BR39="",1,VLOOKUP($BR39,DADOS!$CR$5:$CS$15,2,FALSE)),4),1)),0),""))
D40: ORIGEM | R40: PERÍCIA DA ORIGEM · UMA DESTAS | AH40: ROTA DE CRIAÇÃO | BA40: =IF($AX40="","",IFERROR(IF(ROUND(VLOOKUP($AX40,DADOS!$CL$5:$CM$10,2,FALSE)*IF($AY40="",1,VLOOKUP($AY40,DADOS!$CO$5:$CP$7,2,FALSE))*IF($AZ40="",1,VLOOKUP($AZ40,DADOS!$CR$5:$CS$15,2,FALSE)),4)>0,MAX(1,FLOOR(ROUND(VLOOKUP($AX40,DADOS!$CL$5:$CM$10,2,FALSE)*IF($AY40="",1,VLOOKUP($AY40,DADOS!$CO$5:$CP$7,2,FALSE))*IF($AZ40="",1,VLOOKUP($AZ40,DADOS!$CR$5:$CS$15,2,FALSE)),4),1)),0),"")) | BG40: =IF($BD40="","",IFERROR(IF(ROUND(VLOOKUP($BD40,DADOS!$CL$5:$CM$10,2,FALSE)*IF($BE40="",1,VLOOKUP($BE40,DADOS!$CO$5:$CP$7,2,FALSE))*IF($BF40="",1,VLOOKUP($BF40,DADOS!$CR$5:$CS$15,2,FALSE)),4)>0,MAX(1,FLOOR(ROUND(VLOOKUP($BD40,DADOS!$CL$5:$CM$10,2,FALSE)*IF($BE40="",1,VLOOKUP($BE40,DADOS!$CO$5:$CP$7,2,FALSE))*IF($BF40="",1,VLOOKUP($BF40,DADOS!$CR$5:$CS$15,2,FALSE)),4),1)),0),"")) | BM40: =IF($BJ40="","",IFERROR(IF(ROUND(VLOOKUP($BJ40,DADOS!$CL$5:$CM$10,2,FALSE)*IF($BK40="",1,VLOOKUP($BK40,DADOS!$CO$5:$CP$7,2,FALSE))*IF($BL40="",1,VLOOKUP($BL40,DADOS!$CR$5:$CS$15,2,FALSE)),4)>0,MAX(1,FLOOR(ROUND(VLOOKUP($BJ40,DADOS!$CL$5:$CM$10,2,FALSE)*IF($BK40="",1,VLOOKUP($BK40,DADOS!$CO$5:$CP$7,2,FALSE))*IF($BL40="",1,VLOOKUP($BL40,DADOS!$CR$5:$CS$15,2,FALSE)),4),1)),0),"")) | BS40: =IF($BP40="","",IFERROR(IF(ROUND(VLOOKUP($BP40,DADOS!$CL$5:$CM$10,2,FALSE)*IF($BQ40="",1,VLOOKUP($BQ40,DADOS!$CO$5:$CP$7,2,FALSE))*IF($BR40="",1,VLOOKUP($BR40,DADOS!$CR$5:$CS$15,2,FALSE)),4)>0,MAX(1,FLOOR(ROUND(VLOOKUP($BP40,DADOS!$CL$5:$CM$10,2,FALSE)*IF($BQ40="",1,VLOOKUP($BQ40,DADOS!$CO$5:$CP$7,2,FALSE))*IF($BR40="",1,VLOOKUP($BR40,DADOS!$CR$5:$CS$15,2,FALSE)),4),1)),0),""))
D41: =IF(FICHA!$X$11="","escolha na FICHA",FICHA!$X$11) | R41: =IFERROR(VLOOKUP(DADOS!$CZ$52,'DADOS_CUSTOM'!$BG$2:$BI$34,2,FALSE),"—") | AH41: =IF(DADOS!$CZ$53=1,"Manejos (Sem Técnica)",IFERROR(VLOOKUP(DADOS!$CZ$52,'DADOS_CUSTOM'!$BG$2:$BI$34,3,FALSE),"—")) | BA41: =IF($AX41="","",IFERROR(IF(ROUND(VLOOKUP($AX41,DADOS!$CL$5:$CM$10,2,FALSE)*IF($AY41="",1,VLOOKUP($AY41,DADOS!$CO$5:$CP$7,2,FALSE))*IF($AZ41="",1,VLOOKUP($AZ41,DADOS!$CR$5:$CS$15,2,FALSE)),4)>0,MAX(1,FLOOR(ROUND(VLOOKUP($AX41,DADOS!$CL$5:$CM$10,2,FALSE)*IF($AY41="",1,VLOOKUP($AY41,DADOS!$CO$5:$CP$7,2,FALSE))*IF($AZ41="",1,VLOOKUP($AZ41,DADOS!$CR$5:$CS$15,2,FALSE)),4),1)),0),"")) | BG41: =IF($BD41="","",IFERROR(IF(ROUND(VLOOKUP($BD41,DADOS!$CL$5:$CM$10,2,FALSE)*IF($BE41="",1,VLOOKUP($BE41,DADOS!$CO$5:$CP$7,2,FALSE))*IF($BF41="",1,VLOOKUP($BF41,DADOS!$CR$5:$CS$15,2,FALSE)),4)>0,MAX(1,FLOOR(ROUND(VLOOKUP($BD41,DADOS!$CL$5:$CM$10,2,FALSE)*IF($BE41="",1,VLOOKUP($BE41,DADOS!$CO$5:$CP$7,2,FALSE))*IF($BF41="",1,VLOOKUP($BF41,DADOS!$CR$5:$CS$15,2,FALSE)),4),1)),0),"")) | BM41: =IF($BJ41="","",IFERROR(IF(ROUND(VLOOKUP($BJ41,DADOS!$CL$5:$CM$10,2,FALSE)*IF($BK41="",1,VLOOKUP($BK41,DADOS!$CO$5:$CP$7,2,FALSE))*IF($BL41="",1,VLOOKUP($BL41,DADOS!$CR$5:$CS$15,2,FALSE)),4)>0,MAX(1,FLOOR(ROUND(VLOOKUP($BJ41,DADOS!$CL$5:$CM$10,2,FALSE)*IF($BK41="",1,VLOOKUP($BK41,DADOS!$CO$5:$CP$7,2,FALSE))*IF($BL41="",1,VLOOKUP($BL41,DADOS!$CR$5:$CS$15,2,FALSE)),4),1)),0),"")) | BS41: =IF($BP41="","",IFERROR(IF(ROUND(VLOOKUP($BP41,DADOS!$CL$5:$CM$10,2,FALSE)*IF($BQ41="",1,VLOOKUP($BQ41,DADOS!$CO$5:$CP$7,2,FALSE))*IF($BR41="",1,VLOOKUP($BR41,DADOS!$CR$5:$CS$15,2,FALSE)),4)>0,MAX(1,FLOOR(ROUND(VLOOKUP($BP41,DADOS!$CL$5:$CM$10,2,FALSE)*IF($BQ41="",1,VLOOKUP($BQ41,DADOS!$CO$5:$CP$7,2,FALSE))*IF($BR41="",1,VLOOKUP($BR41,DADOS!$CR$5:$CS$15,2,FALSE)),4),1)),0),""))
D42: DESCRIÇÕES RETRÁTEIS · use − para recolher e + para abrir | BA42: =IF($AX42="","",IFERROR(IF(ROUND(VLOOKUP($AX42,DADOS!$CL$5:$CM$10,2,FALSE)*IF($AY42="",1,VLOOKUP($AY42,DADOS!$CO$5:$CP$7,2,FALSE))*IF($AZ42="",1,VLOOKUP($AZ42,DADOS!$CR$5:$CS$15,2,FALSE)),4)>0,MAX(1,FLOOR(ROUND(VLOOKUP($AX42,DADOS!$CL$5:$CM$10,2,FALSE)*IF($AY42="",1,VLOOKUP($AY42,DADOS!$CO$5:$CP$7,2,FALSE))*IF($AZ42="",1,VLOOKUP($AZ42,DADOS!$CR$5:$CS$15,2,FALSE)),4),1)),0),"")) | BG42: =IF($BD42="","",IFERROR(IF(ROUND(VLOOKUP($BD42,DADOS!$CL$5:$CM$10,2,FALSE)*IF($BE42="",1,VLOOKUP($BE42,DADOS!$CO$5:$CP$7,2,FALSE))*IF($BF42="",1,VLOOKUP($BF42,DADOS!$CR$5:$CS$15,2,FALSE)),4)>0,MAX(1,FLOOR(ROUND(VLOOKUP($BD42,DADOS!$CL$5:$CM$10,2,FALSE)*IF($BE42="",1,VLOOKUP($BE42,DADOS!$CO$5:$CP$7,2,FALSE))*IF($BF42="",1,VLOOKUP($BF42,DADOS!$CR$5:$CS$15,2,FALSE)),4),1)),0),"")) | BM42: =IF($BJ42="","",IFERROR(IF(ROUND(VLOOKUP($BJ42,DADOS!$CL$5:$CM$10,2,FALSE)*IF($BK42="",1,VLOOKUP($BK42,DADOS!$CO$5:$CP$7,2,FALSE))*IF($BL42="",1,VLOOKUP($BL42,DADOS!$CR$5:$CS$15,2,FALSE)),4)>0,MAX(1,FLOOR(ROUND(VLOOKUP($BJ42,DADOS!$CL$5:$CM$10,2,FALSE)*IF($BK42="",1,VLOOKUP($BK42,DADOS!$CO$5:$CP$7,2,FALSE))*IF($BL42="",1,VLOOKUP($BL42,DADOS!$CR$5:$CS$15,2,FALSE)),4),1)),0),"")) | BS42: =IF($BP42="","",IFERROR(IF(ROUND(VLOOKUP($BP42,DADOS!$CL$5:$CM$10,2,FALSE)*IF($BQ42="",1,VLOOKUP($BQ42,DADOS!$CO$5:$CP$7,2,FALSE))*IF($BR42="",1,VLOOKUP($BR42,DADOS!$CR$5:$CS$15,2,FALSE)),4)>0,MAX(1,FLOOR(ROUND(VLOOKUP($BP42,DADOS!$CL$5:$CM$10,2,FALSE)*IF($BQ42="",1,VLOOKUP($BQ42,DADOS!$CO$5:$CP$7,2,FALSE))*IF($BR42="",1,VLOOKUP($BR42,DADOS!$CR$5:$CS$15,2,FALSE)),4),1)),0),""))
D43: MARCANTE | R43: MENOR 1 | AH43: MENOR 2 | BA43: =IF($AX43="","",IFERROR(IF(ROUND(VLOOKUP($AX43,DADOS!$CL$5:$CM$10,2,FALSE)*IF($AY43="",1,VLOOKUP($AY43,DADOS!$CO$5:$CP$7,2,FALSE))*IF($AZ43="",1,VLOOKUP($AZ43,DADOS!$CR$5:$CS$15,2,FALSE)),4)>0,MAX(1,FLOOR(ROUND(VLOOKUP($AX43,DADOS!$CL$5:$CM$10,2,FALSE)*IF($AY43="",1,VLOOKUP($AY43,DADOS!$CO$5:$CP$7,2,FALSE))*IF($AZ43="",1,VLOOKUP($AZ43,DADOS!$CR$5:$CS$15,2,FALSE)),4),1)),0),"")) | BG43: =IF($BD43="","",IFERROR(IF(ROUND(VLOOKUP($BD43,DADOS!$CL$5:$CM$10,2,FALSE)*IF($BE43="",1,VLOOKUP($BE43,DADOS!$CO$5:$CP$7,2,FALSE))*IF($BF43="",1,VLOOKUP($BF43,DADOS!$CR$5:$CS$15,2,FALSE)),4)>0,MAX(1,FLOOR(ROUND(VLOOKUP($BD43,DADOS!$CL$5:$CM$10,2,FALSE)*IF($BE43="",1,VLOOKUP($BE43,DADOS!$CO$5:$CP$7,2,FALSE))*IF($BF43="",1,VLOOKUP($BF43,DADOS!$CR$5:$CS$15,2,FALSE)),4),1)),0),"")) | BM43: =IF($BJ43="","",IFERROR(IF(ROUND(VLOOKUP($BJ43,DADOS!$CL$5:$CM$10,2,FALSE)*IF($BK43="",1,VLOOKUP($BK43,DADOS!$CO$5:$CP$7,2,FALSE))*IF($BL43="",1,VLOOKUP($BL43,DADOS!$CR$5:$CS$15,2,FALSE)),4)>0,MAX(1,FLOOR(ROUND(VLOOKUP($BJ43,DADOS!$CL$5:$CM$10,2,FALSE)*IF($BK43="",1,VLOOKUP($BK43,DADOS!$CO$5:$CP$7,2,FALSE))*IF($BL43="",1,VLOOKUP($BL43,DADOS!$CR$5:$CS$15,2,FALSE)),4),1)),0),"")) | BS43: =IF($BP43="","",IFERROR(IF(ROUND(VLOOKUP($BP43,DADOS!$CL$5:$CM$10,2,FALSE)*IF($BQ43="",1,VLOOKUP($BQ43,DADOS!$CO$5:$CP$7,2,FALSE))*IF($BR43="",1,VLOOKUP($BR43,DADOS!$CR$5:$CS$15,2,FALSE)),4)>0,MAX(1,FLOOR(ROUND(VLOOKUP($BP43,DADOS!$CL$5:$CM$10,2,FALSE)*IF($BQ43="",1,VLOOKUP($BQ43,DADOS!$CO$5:$CP$7,2,FALSE))*IF($BR43="",1,VLOOKUP($BR43,DADOS!$CR$5:$CS$15,2,FALSE)),4),1)),0),""))
BA44: =IF($AX44="","",IFERROR(IF(ROUND(VLOOKUP($AX44,DADOS!$CL$5:$CM$10,2,FALSE)*IF($AY44="",1,VLOOKUP($AY44,DADOS!$CO$5:$CP$7,2,FALSE))*IF($AZ44="",1,VLOOKUP($AZ44,DADOS!$CR$5:$CS$15,2,FALSE)),4)>0,MAX(1,FLOOR(ROUND(VLOOKUP($AX44,DADOS!$CL$5:$CM$10,2,FALSE)*IF($AY44="",1,VLOOKUP($AY44,DADOS!$CO$5:$CP$7,2,FALSE))*IF($AZ44="",1,VLOOKUP($AZ44,DADOS!$CR$5:$CS$15,2,FALSE)),4),1)),0),"")) | BG44: =IF($BD44="","",IFERROR(IF(ROUND(VLOOKUP($BD44,DADOS!$CL$5:$CM$10,2,FALSE)*IF($BE44="",1,VLOOKUP($BE44,DADOS!$CO$5:$CP$7,2,FALSE))*IF($BF44="",1,VLOOKUP($BF44,DADOS!$CR$5:$CS$15,2,FALSE)),4)>0,MAX(1,FLOOR(ROUND(VLOOKUP($BD44,DADOS!$CL$5:$CM$10,2,FALSE)*IF($BE44="",1,VLOOKUP($BE44,DADOS!$CO$5:$CP$7,2,FALSE))*IF($BF44="",1,VLOOKUP($BF44,DADOS!$CR$5:$CS$15,2,FALSE)),4),1)),0),"")) | BM44: =IF($BJ44="","",IFERROR(IF(ROUND(VLOOKUP($BJ44,DADOS!$CL$5:$CM$10,2,FALSE)*IF($BK44="",1,VLOOKUP($BK44,DADOS!$CO$5:$CP$7,2,FALSE))*IF($BL44="",1,VLOOKUP($BL44,DADOS!$CR$5:$CS$15,2,FALSE)),4)>0,MAX(1,FLOOR(ROUND(VLOOKUP($BJ44,DADOS!$CL$5:$CM$10,2,FALSE)*IF($BK44="",1,VLOOKUP($BK44,DADOS!$CO$5:$CP$7,2,FALSE))*IF($BL44="",1,VLOOKUP($BL44,DADOS!$CR$5:$CS$15,2,FALSE)),4),1)),0),"")) | BS44: =IF($BP44="","",IFERROR(IF(ROUND(VLOOKUP($BP44,DADOS!$CL$5:$CM$10,2,FALSE)*IF($BQ44="",1,VLOOKUP($BQ44,DADOS!$CO$5:$CP$7,2,FALSE))*IF($BR44="",1,VLOOKUP($BR44,DADOS!$CR$5:$CS$15,2,FALSE)),4)>0,MAX(1,FLOOR(ROUND(VLOOKUP($BP44,DADOS!$CL$5:$CM$10,2,FALSE)*IF($BQ44="",1,VLOOKUP($BQ44,DADOS!$CO$5:$CP$7,2,FALSE))*IF($BR44="",1,VLOOKUP($BR44,DADOS!$CR$5:$CS$15,2,FALSE)),4),1)),0),""))
D45: =IF(OR($D$44="",$D$44="✎ Criada com o mestre"),"",IFERROR(VLOOKUP($D$44,'DADOS_CUSTOM'!$AZ$2:$BE$107,6,FALSE),"")) | R45: =IF(OR($R$44="",$R$44="✎ Criada com o mestre"),"",IFERROR(VLOOKUP($R$44,'DADOS_CUSTOM'!$AZ$2:$BE$107,6,FALSE),"")) | AH45: =IF(OR($AH$44="",$AH$44="✎ Criada com o mestre"),"",IFERROR(VLOOKUP($AH$44,'DADOS_CUSTOM'!$AZ$2:$BE$107,6,FALSE),"")) | BA45: =IF($AX45="","",IFERROR(IF(ROUND(VLOOKUP($AX45,DADOS!$CL$5:$CM$10,2,FALSE)*IF($AY45="",1,VLOOKUP($AY45,DADOS!$CO$5:$CP$7,2,FALSE))*IF($AZ45="",1,VLOOKUP($AZ45,DADOS!$CR$5:$CS$15,2,FALSE)),4)>0,MAX(1,FLOOR(ROUND(VLOOKUP($AX45,DADOS!$CL$5:$CM$10,2,FALSE)*IF($AY45="",1,VLOOKUP($AY45,DADOS!$CO$5:$CP$7,2,FALSE))*IF($AZ45="",1,VLOOKUP($AZ45,DADOS!$CR$5:$CS$15,2,FALSE)),4),1)),0),"")) | BG45: =IF($BD45="","",IFERROR(IF(ROUND(VLOOKUP($BD45,DADOS!$CL$5:$CM$10,2,FALSE)*IF($BE45="",1,VLOOKUP($BE45,DADOS!$CO$5:$CP$7,2,FALSE))*IF($BF45="",1,VLOOKUP($BF45,DADOS!$CR$5:$CS$15,2,FALSE)),4)>0,MAX(1,FLOOR(ROUND(VLOOKUP($BD45,DADOS!$CL$5:$CM$10,2,FALSE)*IF($BE45="",1,VLOOKUP($BE45,DADOS!$CO$5:$CP$7,2,FALSE))*IF($BF45="",1,VLOOKUP($BF45,DADOS!$CR$5:$CS$15,2,FALSE)),4),1)),0),"")) | BM45: =IF($BJ45="","",IFERROR(IF(ROUND(VLOOKUP($BJ45,DADOS!$CL$5:$CM$10,2,FALSE)*IF($BK45="",1,VLOOKUP($BK45,DADOS!$CO$5:$CP$7,2,FALSE))*IF($BL45="",1,VLOOKUP($BL45,DADOS!$CR$5:$CS$15,2,FALSE)),4)>0,MAX(1,FLOOR(ROUND(VLOOKUP($BJ45,DADOS!$CL$5:$CM$10,2,FALSE)*IF($BK45="",1,VLOOKUP($BK45,DADOS!$CO$5:$CP$7,2,FALSE))*IF($BL45="",1,VLOOKUP($BL45,DADOS!$CR$5:$CS$15,2,FALSE)),4),1)),0),"")) | BS45: =IF($BP45="","",IFERROR(IF(ROUND(VLOOKUP($BP45,DADOS!$CL$5:$CM$10,2,FALSE)*IF($BQ45="",1,VLOOKUP($BQ45,DADOS!$CO$5:$CP$7,2,FALSE))*IF($BR45="",1,VLOOKUP($BR45,DADOS!$CR$5:$CS$15,2,FALSE)),4)>0,MAX(1,FLOOR(ROUND(VLOOKUP($BP45,DADOS!$CL$5:$CM$10,2,FALSE)*IF($BQ45="",1,VLOOKUP($BQ45,DADOS!$CO$5:$CP$7,2,FALSE))*IF($BR45="",1,VLOOKUP($BR45,DADOS!$CR$5:$CS$15,2,FALSE)),4),1)),0),""))
BA46: =IF($AX46="","",IFERROR(IF(ROUND(VLOOKUP($AX46,DADOS!$CL$5:$CM$10,2,FALSE)*IF($AY46="",1,VLOOKUP($AY46,DADOS!$CO$5:$CP$7,2,FALSE))*IF($AZ46="",1,VLOOKUP($AZ46,DADOS!$CR$5:$CS$15,2,FALSE)),4)>0,MAX(1,FLOOR(ROUND(VLOOKUP($AX46,DADOS!$CL$5:$CM$10,2,FALSE)*IF($AY46="",1,VLOOKUP($AY46,DADOS!$CO$5:$CP$7,2,FALSE))*IF($AZ46="",1,VLOOKUP($AZ46,DADOS!$CR$5:$CS$15,2,FALSE)),4),1)),0),"")) | BG46: =IF($BD46="","",IFERROR(IF(ROUND(VLOOKUP($BD46,DADOS!$CL$5:$CM$10,2,FALSE)*IF($BE46="",1,VLOOKUP($BE46,DADOS!$CO$5:$CP$7,2,FALSE))*IF($BF46="",1,VLOOKUP($BF46,DADOS!$CR$5:$CS$15,2,FALSE)),4)>0,MAX(1,FLOOR(ROUND(VLOOKUP($BD46,DADOS!$CL$5:$CM$10,2,FALSE)*IF($BE46="",1,VLOOKUP($BE46,DADOS!$CO$5:$CP$7,2,FALSE))*IF($BF46="",1,VLOOKUP($BF46,DADOS!$CR$5:$CS$15,2,FALSE)),4),1)),0),"")) | BM46: =IF($BJ46="","",IFERROR(IF(ROUND(VLOOKUP($BJ46,DADOS!$CL$5:$CM$10,2,FALSE)*IF($BK46="",1,VLOOKUP($BK46,DADOS!$CO$5:$CP$7,2,FALSE))*IF($BL46="",1,VLOOKUP($BL46,DADOS!$CR$5:$CS$15,2,FALSE)),4)>0,MAX(1,FLOOR(ROUND(VLOOKUP($BJ46,DADOS!$CL$5:$CM$10,2,FALSE)*IF($BK46="",1,VLOOKUP($BK46,DADOS!$CO$5:$CP$7,2,FALSE))*IF($BL46="",1,VLOOKUP($BL46,DADOS!$CR$5:$CS$15,2,FALSE)),4),1)),0),"")) | BS46: =IF($BP46="","",IFERROR(IF(ROUND(VLOOKUP($BP46,DADOS!$CL$5:$CM$10,2,FALSE)*IF($BQ46="",1,VLOOKUP($BQ46,DADOS!$CO$5:$CP$7,2,FALSE))*IF($BR46="",1,VLOOKUP($BR46,DADOS!$CR$5:$CS$15,2,FALSE)),4)>0,MAX(1,FLOOR(ROUND(VLOOKUP($BP46,DADOS!$CL$5:$CM$10,2,FALSE)*IF($BQ46="",1,VLOOKUP($BQ46,DADOS!$CO$5:$CP$7,2,FALSE))*IF($BR46="",1,VLOOKUP($BR46,DADOS!$CR$5:$CS$15,2,FALSE)),4),1)),0),""))
BA47: =IF($AX47="","",IFERROR(IF(ROUND(VLOOKUP($AX47,DADOS!$CL$5:$CM$10,2,FALSE)*IF($AY47="",1,VLOOKUP($AY47,DADOS!$CO$5:$CP$7,2,FALSE))*IF($AZ47="",1,VLOOKUP($AZ47,DADOS!$CR$5:$CS$15,2,FALSE)),4)>0,MAX(1,FLOOR(ROUND(VLOOKUP($AX47,DADOS!$CL$5:$CM$10,2,FALSE)*IF($AY47="",1,VLOOKUP($AY47,DADOS!$CO$5:$CP$7,2,FALSE))*IF($AZ47="",1,VLOOKUP($AZ47,DADOS!$CR$5:$CS$15,2,FALSE)),4),1)),0),"")) | BG47: =IF($BD47="","",IFERROR(IF(ROUND(VLOOKUP($BD47,DADOS!$CL$5:$CM$10,2,FALSE)*IF($BE47="",1,VLOOKUP($BE47,DADOS!$CO$5:$CP$7,2,FALSE))*IF($BF47="",1,VLOOKUP($BF47,DADOS!$CR$5:$CS$15,2,FALSE)),4)>0,MAX(1,FLOOR(ROUND(VLOOKUP($BD47,DADOS!$CL$5:$CM$10,2,FALSE)*IF($BE47="",1,VLOOKUP($BE47,DADOS!$CO$5:$CP$7,2,FALSE))*IF($BF47="",1,VLOOKUP($BF47,DADOS!$CR$5:$CS$15,2,FALSE)),4),1)),0),"")) | BM47: =IF($BJ47="","",IFERROR(IF(ROUND(VLOOKUP($BJ47,DADOS!$CL$5:$CM$10,2,FALSE)*IF($BK47="",1,VLOOKUP($BK47,DADOS!$CO$5:$CP$7,2,FALSE))*IF($BL47="",1,VLOOKUP($BL47,DADOS!$CR$5:$CS$15,2,FALSE)),4)>0,MAX(1,FLOOR(ROUND(VLOOKUP($BJ47,DADOS!$CL$5:$CM$10,2,FALSE)*IF($BK47="",1,VLOOKUP($BK47,DADOS!$CO$5:$CP$7,2,FALSE))*IF($BL47="",1,VLOOKUP($BL47,DADOS!$CR$5:$CS$15,2,FALSE)),4),1)),0),"")) | BS47: =IF($BP47="","",IFERROR(IF(ROUND(VLOOKUP($BP47,DADOS!$CL$5:$CM$10,2,FALSE)*IF($BQ47="",1,VLOOKUP($BQ47,DADOS!$CO$5:$CP$7,2,FALSE))*IF($BR47="",1,VLOOKUP($BR47,DADOS!$CR$5:$CS$15,2,FALSE)),4)>0,MAX(1,FLOOR(ROUND(VLOOKUP($BP47,DADOS!$CL$5:$CM$10,2,FALSE)*IF($BQ47="",1,VLOOKUP($BQ47,DADOS!$CO$5:$CP$7,2,FALSE))*IF($BR47="",1,VLOOKUP($BR47,DADOS!$CR$5:$CS$15,2,FALSE)),4),1)),0),""))
BA48: =IF($AX48="","",IFERROR(IF(ROUND(VLOOKUP($AX48,DADOS!$CL$5:$CM$10,2,FALSE)*IF($AY48="",1,VLOOKUP($AY48,DADOS!$CO$5:$CP$7,2,FALSE))*IF($AZ48="",1,VLOOKUP($AZ48,DADOS!$CR$5:$CS$15,2,FALSE)),4)>0,MAX(1,FLOOR(ROUND(VLOOKUP($AX48,DADOS!$CL$5:$CM$10,2,FALSE)*IF($AY48="",1,VLOOKUP($AY48,DADOS!$CO$5:$CP$7,2,FALSE))*IF($AZ48="",1,VLOOKUP($AZ48,DADOS!$CR$5:$CS$15,2,FALSE)),4),1)),0),"")) | BG48: =IF($BD48="","",IFERROR(IF(ROUND(VLOOKUP($BD48,DADOS!$CL$5:$CM$10,2,FALSE)*IF($BE48="",1,VLOOKUP($BE48,DADOS!$CO$5:$CP$7,2,FALSE))*IF($BF48="",1,VLOOKUP($BF48,DADOS!$CR$5:$CS$15,2,FALSE)),4)>0,MAX(1,FLOOR(ROUND(VLOOKUP($BD48,DADOS!$CL$5:$CM$10,2,FALSE)*IF($BE48="",1,VLOOKUP($BE48,DADOS!$CO$5:$CP$7,2,FALSE))*IF($BF48="",1,VLOOKUP($BF48,DADOS!$CR$5:$CS$15,2,FALSE)),4),1)),0),"")) | BM48: =IF($BJ48="","",IFERROR(IF(ROUND(VLOOKUP($BJ48,DADOS!$CL$5:$CM$10,2,FALSE)*IF($BK48="",1,VLOOKUP($BK48,DADOS!$CO$5:$CP$7,2,FALSE))*IF($BL48="",1,VLOOKUP($BL48,DADOS!$CR$5:$CS$15,2,FALSE)),4)>0,MAX(1,FLOOR(ROUND(VLOOKUP($BJ48,DADOS!$CL$5:$CM$10,2,FALSE)*IF($BK48="",1,VLOOKUP($BK48,DADOS!$CO$5:$CP$7,2,FALSE))*IF($BL48="",1,VLOOKUP($BL48,DADOS!$CR$5:$CS$15,2,FALSE)),4),1)),0),"")) | BS48: =IF($BP48="","",IFERROR(IF(ROUND(VLOOKUP($BP48,DADOS!$CL$5:$CM$10,2,FALSE)*IF($BQ48="",1,VLOOKUP($BQ48,DADOS!$CO$5:$CP$7,2,FALSE))*IF($BR48="",1,VLOOKUP($BR48,DADOS!$CR$5:$CS$15,2,FALSE)),4)>0,MAX(1,FLOOR(ROUND(VLOOKUP($BP48,DADOS!$CL$5:$CM$10,2,FALSE)*IF($BQ48="",1,VLOOKUP($BQ48,DADOS!$CO$5:$CP$7,2,FALSE))*IF($BR48="",1,VLOOKUP($BR48,DADOS!$CR$5:$CS$15,2,FALSE)),4),1)),0),""))
BA49: =IF($AX49="","",IFERROR(IF(ROUND(VLOOKUP($AX49,DADOS!$CL$5:$CM$10,2,FALSE)*IF($AY49="",1,VLOOKUP($AY49,DADOS!$CO$5:$CP$7,2,FALSE))*IF($AZ49="",1,VLOOKUP($AZ49,DADOS!$CR$5:$CS$15,2,FALSE)),4)>0,MAX(1,FLOOR(ROUND(VLOOKUP($AX49,DADOS!$CL$5:$CM$10,2,FALSE)*IF($AY49="",1,VLOOKUP($AY49,DADOS!$CO$5:$CP$7,2,FALSE))*IF($AZ49="",1,VLOOKUP($AZ49,DADOS!$CR$5:$CS$15,2,FALSE)),4),1)),0),"")) | BG49: =IF($BD49="","",IFERROR(IF(ROUND(VLOOKUP($BD49,DADOS!$CL$5:$CM$10,2,FALSE)*IF($BE49="",1,VLOOKUP($BE49,DADOS!$CO$5:$CP$7,2,FALSE))*IF($BF49="",1,VLOOKUP($BF49,DADOS!$CR$5:$CS$15,2,FALSE)),4)>0,MAX(1,FLOOR(ROUND(VLOOKUP($BD49,DADOS!$CL$5:$CM$10,2,FALSE)*IF($BE49="",1,VLOOKUP($BE49,DADOS!$CO$5:$CP$7,2,FALSE))*IF($BF49="",1,VLOOKUP($BF49,DADOS!$CR$5:$CS$15,2,FALSE)),4),1)),0),"")) | BM49: =IF($BJ49="","",IFERROR(IF(ROUND(VLOOKUP($BJ49,DADOS!$CL$5:$CM$10,2,FALSE)*IF($BK49="",1,VLOOKUP($BK49,DADOS!$CO$5:$CP$7,2,FALSE))*IF($BL49="",1,VLOOKUP($BL49,DADOS!$CR$5:$CS$15,2,FALSE)),4)>0,MAX(1,FLOOR(ROUND(VLOOKUP($BJ49,DADOS!$CL$5:$CM$10,2,FALSE)*IF($BK49="",1,VLOOKUP($BK49,DADOS!$CO$5:$CP$7,2,FALSE))*IF($BL49="",1,VLOOKUP($BL49,DADOS!$CR$5:$CS$15,2,FALSE)),4),1)),0),"")) | BS49: =IF($BP49="","",IFERROR(IF(ROUND(VLOOKUP($BP49,DADOS!$CL$5:$CM$10,2,FALSE)*IF($BQ49="",1,VLOOKUP($BQ49,DADOS!$CO$5:$CP$7,2,FALSE))*IF($BR49="",1,VLOOKUP($BR49,DADOS!$CR$5:$CS$15,2,FALSE)),4)>0,MAX(1,FLOOR(ROUND(VLOOKUP($BP49,DADOS!$CL$5:$CM$10,2,FALSE)*IF($BQ49="",1,VLOOKUP($BQ49,DADOS!$CO$5:$CP$7,2,FALSE))*IF($BR49="",1,VLOOKUP($BR49,DADOS!$CR$5:$CS$15,2,FALSE)),4),1)),0),""))
BA50: =IF($AX50="","",IFERROR(IF(ROUND(VLOOKUP($AX50,DADOS!$CL$5:$CM$10,2,FALSE)*IF($AY50="",1,VLOOKUP($AY50,DADOS!$CO$5:$CP$7,2,FALSE))*IF($AZ50="",1,VLOOKUP($AZ50,DADOS!$CR$5:$CS$15,2,FALSE)),4)>0,MAX(1,FLOOR(ROUND(VLOOKUP($AX50,DADOS!$CL$5:$CM$10,2,FALSE)*IF($AY50="",1,VLOOKUP($AY50,DADOS!$CO$5:$CP$7,2,FALSE))*IF($AZ50="",1,VLOOKUP($AZ50,DADOS!$CR$5:$CS$15,2,FALSE)),4),1)),0),"")) | BG50: =IF($BD50="","",IFERROR(IF(ROUND(VLOOKUP($BD50,DADOS!$CL$5:$CM$10,2,FALSE)*IF($BE50="",1,VLOOKUP($BE50,DADOS!$CO$5:$CP$7,2,FALSE))*IF($BF50="",1,VLOOKUP($BF50,DADOS!$CR$5:$CS$15,2,FALSE)),4)>0,MAX(1,FLOOR(ROUND(VLOOKUP($BD50,DADOS!$CL$5:$CM$10,2,FALSE)*IF($BE50="",1,VLOOKUP($BE50,DADOS!$CO$5:$CP$7,2,FALSE))*IF($BF50="",1,VLOOKUP($BF50,DADOS!$CR$5:$CS$15,2,FALSE)),4),1)),0),"")) | BM50: =IF($BJ50="","",IFERROR(IF(ROUND(VLOOKUP($BJ50,DADOS!$CL$5:$CM$10,2,FALSE)*IF($BK50="",1,VLOOKUP($BK50,DADOS!$CO$5:$CP$7,2,FALSE))*IF($BL50="",1,VLOOKUP($BL50,DADOS!$CR$5:$CS$15,2,FALSE)),4)>0,MAX(1,FLOOR(ROUND(VLOOKUP($BJ50,DADOS!$CL$5:$CM$10,2,FALSE)*IF($BK50="",1,VLOOKUP($BK50,DADOS!$CO$5:$CP$7,2,FALSE))*IF($BL50="",1,VLOOKUP($BL50,DADOS!$CR$5:$CS$15,2,FALSE)),4),1)),0),"")) | BS50: =IF($BP50="","",IFERROR(IF(ROUND(VLOOKUP($BP50,DADOS!$CL$5:$CM$10,2,FALSE)*IF($BQ50="",1,VLOOKUP($BQ50,DADOS!$CO$5:$CP$7,2,FALSE))*IF($BR50="",1,VLOOKUP($BR50,DADOS!$CR$5:$CS$15,2,FALSE)),4)>0,MAX(1,FLOOR(ROUND(VLOOKUP($BP50,DADOS!$CL$5:$CM$10,2,FALSE)*IF($BQ50="",1,VLOOKUP($BQ50,DADOS!$CO$5:$CP$7,2,FALSE))*IF($BR50="",1,VLOOKUP($BR50,DADOS!$CR$5:$CS$15,2,FALSE)),4),1)),0),""))
D51: =IF(AND('FICHA PESSOAL'!$D$44<>"",COUNTIF('DADOS_CUSTOM'!$CP$2:$CP$160,'FICHA PESSOAL'!$D$44)=0),"⚠ Marcante inválida para esta Origem; escolha uma opção do menu.",IF($D$44="","escolha no menu acima",IFERROR(VLOOKUP($D$44,'DADOS_CUSTOM'!$AZ$2:$BE$107,5,FALSE)&IF(COUNTIF('DADOS_CUSTOM'!$C$2:$C$26,VLOOKUP('FICHA PESSOAL'!$D$44,'DADOS_CUSTOM'!$AZ$2:$BE$107,1,FALSE))>0," · custom"," · do livro"),"criada com o mestre · escreva o texto acima"))) | R51: =IF($R$44="","escolha no menu acima",IFERROR(VLOOKUP($R$44,'DADOS_CUSTOM'!$AZ$2:$BE$107,5,FALSE)&IF(COUNTIF('DADOS_CUSTOM'!$C$2:$C$26,VLOOKUP('FICHA PESSOAL'!$R$44,'DADOS_CUSTOM'!$AZ$2:$BE$107,1,FALSE))>0," · custom"," · do livro"),"criada com o mestre · escreva o texto acima")) | AH51: =IF($AH$44="","escolha no menu acima",IFERROR(VLOOKUP($AH$44,'DADOS_CUSTOM'!$AZ$2:$BE$107,5,FALSE)&IF(COUNTIF('DADOS_CUSTOM'!$C$2:$C$26,VLOOKUP('FICHA PESSOAL'!$AH$44,'DADOS_CUSTOM'!$AZ$2:$BE$107,1,FALSE))>0," · custom"," · do livro"),"criada com o mestre · escreva o texto acima")) | BA51: =IF($AX51="","",IFERROR(IF(ROUND(VLOOKUP($AX51,DADOS!$CL$5:$CM$10,2,FALSE)*IF($AY51="",1,VLOOKUP($AY51,DADOS!$CO$5:$CP$7,2,FALSE))*IF($AZ51="",1,VLOOKUP($AZ51,DADOS!$CR$5:$CS$15,2,FALSE)),4)>0,MAX(1,FLOOR(ROUND(VLOOKUP($AX51,DADOS!$CL$5:$CM$10,2,FALSE)*IF($AY51="",1,VLOOKUP($AY51,DADOS!$CO$5:$CP$7,2,FALSE))*IF($AZ51="",1,VLOOKUP($AZ51,DADOS!$CR$5:$CS$15,2,FALSE)),4),1)),0),"")) | BG51: =IF($BD51="","",IFERROR(IF(ROUND(VLOOKUP($BD51,DADOS!$CL$5:$CM$10,2,FALSE)*IF($BE51="",1,VLOOKUP($BE51,DADOS!$CO$5:$CP$7,2,FALSE))*IF($BF51="",1,VLOOKUP($BF51,DADOS!$CR$5:$CS$15,2,FALSE)),4)>0,MAX(1,FLOOR(ROUND(VLOOKUP($BD51,DADOS!$CL$5:$CM$10,2,FALSE)*IF($BE51="",1,VLOOKUP($BE51,DADOS!$CO$5:$CP$7,2,FALSE))*IF($BF51="",1,VLOOKUP($BF51,DADOS!$CR$5:$CS$15,2,FALSE)),4),1)),0),"")) | BM51: =IF($BJ51="","",IFERROR(IF(ROUND(VLOOKUP($BJ51,DADOS!$CL$5:$CM$10,2,FALSE)*IF($BK51="",1,VLOOKUP($BK51,DADOS!$CO$5:$CP$7,2,FALSE))*IF($BL51="",1,VLOOKUP($BL51,DADOS!$CR$5:$CS$15,2,FALSE)),4)>0,MAX(1,FLOOR(ROUND(VLOOKUP($BJ51,DADOS!$CL$5:$CM$10,2,FALSE)*IF($BK51="",1,VLOOKUP($BK51,DADOS!$CO$5:$CP$7,2,FALSE))*IF($BL51="",1,VLOOKUP($BL51,DADOS!$CR$5:$CS$15,2,FALSE)),4),1)),0),"")) | BS51: =IF($BP51="","",IFERROR(IF(ROUND(VLOOKUP($BP51,DADOS!$CL$5:$CM$10,2,FALSE)*IF($BQ51="",1,VLOOKUP($BQ51,DADOS!$CO$5:$CP$7,2,FALSE))*IF($BR51="",1,VLOOKUP($BR51,DADOS!$CR$5:$CS$15,2,FALSE)),4)>0,MAX(1,FLOOR(ROUND(VLOOKUP($BP51,DADOS!$CL$5:$CM$10,2,FALSE)*IF($BQ51="",1,VLOOKUP($BQ51,DADOS!$CO$5:$CP$7,2,FALSE))*IF($BR51="",1,VLOOKUP($BR51,DADOS!$CR$5:$CS$15,2,FALSE)),4),1)),0),""))
BA52: =IF($AX52="","",IFERROR(IF(ROUND(VLOOKUP($AX52,DADOS!$CL$5:$CM$10,2,FALSE)*IF($AY52="",1,VLOOKUP($AY52,DADOS!$CO$5:$CP$7,2,FALSE))*IF($AZ52="",1,VLOOKUP($AZ52,DADOS!$CR$5:$CS$15,2,FALSE)),4)>0,MAX(1,FLOOR(ROUND(VLOOKUP($AX52,DADOS!$CL$5:$CM$10,2,FALSE)*IF($AY52="",1,VLOOKUP($AY52,DADOS!$CO$5:$CP$7,2,FALSE))*IF($AZ52="",1,VLOOKUP($AZ52,DADOS!$CR$5:$CS$15,2,FALSE)),4),1)),0),"")) | BG52: =IF($BD52="","",IFERROR(IF(ROUND(VLOOKUP($BD52,DADOS!$CL$5:$CM$10,2,FALSE)*IF($BE52="",1,VLOOKUP($BE52,DADOS!$CO$5:$CP$7,2,FALSE))*IF($BF52="",1,VLOOKUP($BF52,DADOS!$CR$5:$CS$15,2,FALSE)),4)>0,MAX(1,FLOOR(ROUND(VLOOKUP($BD52,DADOS!$CL$5:$CM$10,2,FALSE)*IF($BE52="",1,VLOOKUP($BE52,DADOS!$CO$5:$CP$7,2,FALSE))*IF($BF52="",1,VLOOKUP($BF52,DADOS!$CR$5:$CS$15,2,FALSE)),4),1)),0),"")) | BM52: =IF($BJ52="","",IFERROR(IF(ROUND(VLOOKUP($BJ52,DADOS!$CL$5:$CM$10,2,FALSE)*IF($BK52="",1,VLOOKUP($BK52,DADOS!$CO$5:$CP$7,2,FALSE))*IF($BL52="",1,VLOOKUP($BL52,DADOS!$CR$5:$CS$15,2,FALSE)),4)>0,MAX(1,FLOOR(ROUND(VLOOKUP($BJ52,DADOS!$CL$5:$CM$10,2,FALSE)*IF($BK52="",1,VLOOKUP($BK52,DADOS!$CO$5:$CP$7,2,FALSE))*IF($BL52="",1,VLOOKUP($BL52,DADOS!$CR$5:$CS$15,2,FALSE)),4),1)),0),"")) | BS52: =IF($BP52="","",IFERROR(IF(ROUND(VLOOKUP($BP52,DADOS!$CL$5:$CM$10,2,FALSE)*IF($BQ52="",1,VLOOKUP($BQ52,DADOS!$CO$5:$CP$7,2,FALSE))*IF($BR52="",1,VLOOKUP($BR52,DADOS!$CR$5:$CS$15,2,FALSE)),4)>0,MAX(1,FLOOR(ROUND(VLOOKUP($BP52,DADOS!$CL$5:$CM$10,2,FALSE)*IF($BQ52="",1,VLOOKUP($BQ52,DADOS!$CO$5:$CP$7,2,FALSE))*IF($BR52="",1,VLOOKUP($BR52,DADOS!$CR$5:$CS$15,2,FALSE)),4),1)),0),""))
D53: LEGADOS DE HISTÓRIA · SEM EFEITO NA FICHA | AH53: OFÍCIO COMPATÍVEL | BA53: =IF($AX53="","",IFERROR(IF(ROUND(VLOOKUP($AX53,DADOS!$CL$5:$CM$10,2,FALSE)*IF($AY53="",1,VLOOKUP($AY53,DADOS!$CO$5:$CP$7,2,FALSE))*IF($AZ53="",1,VLOOKUP($AZ53,DADOS!$CR$5:$CS$15,2,FALSE)),4)>0,MAX(1,FLOOR(ROUND(VLOOKUP($AX53,DADOS!$CL$5:$CM$10,2,FALSE)*IF($AY53="",1,VLOOKUP($AY53,DADOS!$CO$5:$CP$7,2,FALSE))*IF($AZ53="",1,VLOOKUP($AZ53,DADOS!$CR$5:$CS$15,2,FALSE)),4),1)),0),"")) | BG53: =IF($BD53="","",IFERROR(IF(ROUND(VLOOKUP($BD53,DADOS!$CL$5:$CM$10,2,FALSE)*IF($BE53="",1,VLOOKUP($BE53,DADOS!$CO$5:$CP$7,2,FALSE))*IF($BF53="",1,VLOOKUP($BF53,DADOS!$CR$5:$CS$15,2,FALSE)),4)>0,MAX(1,FLOOR(ROUND(VLOOKUP($BD53,DADOS!$CL$5:$CM$10,2,FALSE)*IF($BE53="",1,VLOOKUP($BE53,DADOS!$CO$5:$CP$7,2,FALSE))*IF($BF53="",1,VLOOKUP($BF53,DADOS!$CR$5:$CS$15,2,FALSE)),4),1)),0),"")) | BM53: =IF($BJ53="","",IFERROR(IF(ROUND(VLOOKUP($BJ53,DADOS!$CL$5:$CM$10,2,FALSE)*IF($BK53="",1,VLOOKUP($BK53,DADOS!$CO$5:$CP$7,2,FALSE))*IF($BL53="",1,VLOOKUP($BL53,DADOS!$CR$5:$CS$15,2,FALSE)),4)>0,MAX(1,FLOOR(ROUND(VLOOKUP($BJ53,DADOS!$CL$5:$CM$10,2,FALSE)*IF($BK53="",1,VLOOKUP($BK53,DADOS!$CO$5:$CP$7,2,FALSE))*IF($BL53="",1,VLOOKUP($BL53,DADOS!$CR$5:$CS$15,2,FALSE)),4),1)),0),"")) | BS53: =IF($BP53="","",IFERROR(IF(ROUND(VLOOKUP($BP53,DADOS!$CL$5:$CM$10,2,FALSE)*IF($BQ53="",1,VLOOKUP($BQ53,DADOS!$CO$5:$CP$7,2,FALSE))*IF($BR53="",1,VLOOKUP($BR53,DADOS!$CR$5:$CS$15,2,FALSE)),4)>0,MAX(1,FLOOR(ROUND(VLOOKUP($BP53,DADOS!$CL$5:$CM$10,2,FALSE)*IF($BQ53="",1,VLOOKUP($BQ53,DADOS!$CO$5:$CP$7,2,FALSE))*IF($BR53="",1,VLOOKUP($BR53,DADOS!$CR$5:$CS$15,2,FALSE)),4),1)),0),""))
AH54: =IF('DADOS_CUSTOM'!$B$121,'DADOS_CUSTOM'!$B$124,"") | BA54: =IF($AX54="","",IFERROR(IF(ROUND(VLOOKUP($AX54,DADOS!$CL$5:$CM$10,2,FALSE)*IF($AY54="",1,VLOOKUP($AY54,DADOS!$CO$5:$CP$7,2,FALSE))*IF($AZ54="",1,VLOOKUP($AZ54,DADOS!$CR$5:$CS$15,2,FALSE)),4)>0,MAX(1,FLOOR(ROUND(VLOOKUP($AX54,DADOS!$CL$5:$CM$10,2,FALSE)*IF($AY54="",1,VLOOKUP($AY54,DADOS!$CO$5:$CP$7,2,FALSE))*IF($AZ54="",1,VLOOKUP($AZ54,DADOS!$CR$5:$CS$15,2,FALSE)),4),1)),0),"")) | BG54: =IF($BD54="","",IFERROR(IF(ROUND(VLOOKUP($BD54,DADOS!$CL$5:$CM$10,2,FALSE)*IF($BE54="",1,VLOOKUP($BE54,DADOS!$CO$5:$CP$7,2,FALSE))*IF($BF54="",1,VLOOKUP($BF54,DADOS!$CR$5:$CS$15,2,FALSE)),4)>0,MAX(1,FLOOR(ROUND(VLOOKUP($BD54,DADOS!$CL$5:$CM$10,2,FALSE)*IF($BE54="",1,VLOOKUP($BE54,DADOS!$CO$5:$CP$7,2,FALSE))*IF($BF54="",1,VLOOKUP($BF54,DADOS!$CR$5:$CS$15,2,FALSE)),4),1)),0),"")) | BM54: =IF($BJ54="","",IFERROR(IF(ROUND(VLOOKUP($BJ54,DADOS!$CL$5:$CM$10,2,FALSE)*IF($BK54="",1,VLOOKUP($BK54,DADOS!$CO$5:$CP$7,2,FALSE))*IF($BL54="",1,VLOOKUP($BL54,DADOS!$CR$5:$CS$15,2,FALSE)),4)>0,MAX(1,FLOOR(ROUND(VLOOKUP($BJ54,DADOS!$CL$5:$CM$10,2,FALSE)*IF($BK54="",1,VLOOKUP($BK54,DADOS!$CO$5:$CP$7,2,FALSE))*IF($BL54="",1,VLOOKUP($BL54,DADOS!$CR$5:$CS$15,2,FALSE)),4),1)),0),"")) | BS54: =IF($BP54="","",IFERROR(IF(ROUND(VLOOKUP($BP54,DADOS!$CL$5:$CM$10,2,FALSE)*IF($BQ54="",1,VLOOKUP($BQ54,DADOS!$CO$5:$CP$7,2,FALSE))*IF($BR54="",1,VLOOKUP($BR54,DADOS!$CR$5:$CS$15,2,FALSE)),4)>0,MAX(1,FLOOR(ROUND(VLOOKUP($BP54,DADOS!$CL$5:$CM$10,2,FALSE)*IF($BQ54="",1,VLOOKUP($BQ54,DADOS!$CO$5:$CP$7,2,FALSE))*IF($BR54="",1,VLOOKUP($BR54,DADOS!$CR$5:$CS$15,2,FALSE)),4),1)),0),""))
AH55: =IF('DADOS_CUSTOM'!$B$121,IF('DADOS_CUSTOM'!$B$124="—","sem ofício de reparo definido","ofício definido na CONFIGURAÇÃO"),IF(DADOS!$CZ$52="Corpo Amaldiçoado",IF($AH$54="","escolha o ofício que repara o seu corpo","o que repara o seu corpo"),"só no Corpo Amaldiçoado")) | BA55: =IF($AX55="","",IFERROR(IF(ROUND(VLOOKUP($AX55,DADOS!$CL$5:$CM$10,2,FALSE)*IF($AY55="",1,VLOOKUP($AY55,DADOS!$CO$5:$CP$7,2,FALSE))*IF($AZ55="",1,VLOOKUP($AZ55,DADOS!$CR$5:$CS$15,2,FALSE)),4)>0,MAX(1,FLOOR(ROUND(VLOOKUP($AX55,DADOS!$CL$5:$CM$10,2,FALSE)*IF($AY55="",1,VLOOKUP($AY55,DADOS!$CO$5:$CP$7,2,FALSE))*IF($AZ55="",1,VLOOKUP($AZ55,DADOS!$CR$5:$CS$15,2,FALSE)),4),1)),0),"")) | BG55: =IF($BD55="","",IFERROR(IF(ROUND(VLOOKUP($BD55,DADOS!$CL$5:$CM$10,2,FALSE)*IF($BE55="",1,VLOOKUP($BE55,DADOS!$CO$5:$CP$7,2,FALSE))*IF($BF55="",1,VLOOKUP($BF55,DADOS!$CR$5:$CS$15,2,FALSE)),4)>0,MAX(1,FLOOR(ROUND(VLOOKUP($BD55,DADOS!$CL$5:$CM$10,2,FALSE)*IF($BE55="",1,VLOOKUP($BE55,DADOS!$CO$5:$CP$7,2,FALSE))*IF($BF55="",1,VLOOKUP($BF55,DADOS!$CR$5:$CS$15,2,FALSE)),4),1)),0),"")) | BM55: =IF($BJ55="","",IFERROR(IF(ROUND(VLOOKUP($BJ55,DADOS!$CL$5:$CM$10,2,FALSE)*IF($BK55="",1,VLOOKUP($BK55,DADOS!$CO$5:$CP$7,2,FALSE))*IF($BL55="",1,VLOOKUP($BL55,DADOS!$CR$5:$CS$15,2,FALSE)),4)>0,MAX(1,FLOOR(ROUND(VLOOKUP($BJ55,DADOS!$CL$5:$CM$10,2,FALSE)*IF($BK55="",1,VLOOKUP($BK55,DADOS!$CO$5:$CP$7,2,FALSE))*IF($BL55="",1,VLOOKUP($BL55,DADOS!$CR$5:$CS$15,2,FALSE)),4),1)),0),"")) | BS55: =IF($BP55="","",IFERROR(IF(ROUND(VLOOKUP($BP55,DADOS!$CL$5:$CM$10,2,FALSE)*IF($BQ55="",1,VLOOKUP($BQ55,DADOS!$CO$5:$CP$7,2,FALSE))*IF($BR55="",1,VLOOKUP($BR55,DADOS!$CR$5:$CS$15,2,FALSE)),4)>0,MAX(1,FLOOR(ROUND(VLOOKUP($BP55,DADOS!$CL$5:$CM$10,2,FALSE)*IF($BQ55="",1,VLOOKUP($BQ55,DADOS!$CO$5:$CP$7,2,FALSE))*IF($BR55="",1,VLOOKUP($BR55,DADOS!$CR$5:$CS$15,2,FALSE)),4),1)),0),""))
BA56: =IF($AX56="","",IFERROR(IF(ROUND(VLOOKUP($AX56,DADOS!$CL$5:$CM$10,2,FALSE)*IF($AY56="",1,VLOOKUP($AY56,DADOS!$CO$5:$CP$7,2,FALSE))*IF($AZ56="",1,VLOOKUP($AZ56,DADOS!$CR$5:$CS$15,2,FALSE)),4)>0,MAX(1,FLOOR(ROUND(VLOOKUP($AX56,DADOS!$CL$5:$CM$10,2,FALSE)*IF($AY56="",1,VLOOKUP($AY56,DADOS!$CO$5:$CP$7,2,FALSE))*IF($AZ56="",1,VLOOKUP($AZ56,DADOS!$CR$5:$CS$15,2,FALSE)),4),1)),0),"")) | BG56: =IF($BD56="","",IFERROR(IF(ROUND(VLOOKUP($BD56,DADOS!$CL$5:$CM$10,2,FALSE)*IF($BE56="",1,VLOOKUP($BE56,DADOS!$CO$5:$CP$7,2,FALSE))*IF($BF56="",1,VLOOKUP($BF56,DADOS!$CR$5:$CS$15,2,FALSE)),4)>0,MAX(1,FLOOR(ROUND(VLOOKUP($BD56,DADOS!$CL$5:$CM$10,2,FALSE)*IF($BE56="",1,VLOOKUP($BE56,DADOS!$CO$5:$CP$7,2,FALSE))*IF($BF56="",1,VLOOKUP($BF56,DADOS!$CR$5:$CS$15,2,FALSE)),4),1)),0),"")) | BM56: =IF($BJ56="","",IFERROR(IF(ROUND(VLOOKUP($BJ56,DADOS!$CL$5:$CM$10,2,FALSE)*IF($BK56="",1,VLOOKUP($BK56,DADOS!$CO$5:$CP$7,2,FALSE))*IF($BL56="",1,VLOOKUP($BL56,DADOS!$CR$5:$CS$15,2,FALSE)),4)>0,MAX(1,FLOOR(ROUND(VLOOKUP($BJ56,DADOS!$CL$5:$CM$10,2,FALSE)*IF($BK56="",1,VLOOKUP($BK56,DADOS!$CO$5:$CP$7,2,FALSE))*IF($BL56="",1,VLOOKUP($BL56,DADOS!$CR$5:$CS$15,2,FALSE)),4),1)),0),"")) | BS56: =IF($BP56="","",IFERROR(IF(ROUND(VLOOKUP($BP56,DADOS!$CL$5:$CM$10,2,FALSE)*IF($BQ56="",1,VLOOKUP($BQ56,DADOS!$CO$5:$CP$7,2,FALSE))*IF($BR56="",1,VLOOKUP($BR56,DADOS!$CR$5:$CS$15,2,FALSE)),4)>0,MAX(1,FLOOR(ROUND(VLOOKUP($BP56,DADOS!$CL$5:$CM$10,2,FALSE)*IF($BQ56="",1,VLOOKUP($BQ56,DADOS!$CO$5:$CP$7,2,FALSE))*IF($BR56="",1,VLOOKUP($BR56,DADOS!$CR$5:$CS$15,2,FALSE)),4),1)),0),""))
D57: =IF('DADOS_CUSTOM'!$B$121,"TALENTO DE CATEGORIA DE EFEITO 4 · REGISTRO DA ORIGEM CUSTOM","TALENTO DE CATEGORIA DE EFEITO 4 · SÓ NA RESTRIÇÃO CORPORAL") | BA57: =IF($AX57="","",IFERROR(IF(ROUND(VLOOKUP($AX57,DADOS!$CL$5:$CM$10,2,FALSE)*IF($AY57="",1,VLOOKUP($AY57,DADOS!$CO$5:$CP$7,2,FALSE))*IF($AZ57="",1,VLOOKUP($AZ57,DADOS!$CR$5:$CS$15,2,FALSE)),4)>0,MAX(1,FLOOR(ROUND(VLOOKUP($AX57,DADOS!$CL$5:$CM$10,2,FALSE)*IF($AY57="",1,VLOOKUP($AY57,DADOS!$CO$5:$CP$7,2,FALSE))*IF($AZ57="",1,VLOOKUP($AZ57,DADOS!$CR$5:$CS$15,2,FALSE)),4),1)),0),"")) | BG57: =IF($BD57="","",IFERROR(IF(ROUND(VLOOKUP($BD57,DADOS!$CL$5:$CM$10,2,FALSE)*IF($BE57="",1,VLOOKUP($BE57,DADOS!$CO$5:$CP$7,2,FALSE))*IF($BF57="",1,VLOOKUP($BF57,DADOS!$CR$5:$CS$15,2,FALSE)),4)>0,MAX(1,FLOOR(ROUND(VLOOKUP($BD57,DADOS!$CL$5:$CM$10,2,FALSE)*IF($BE57="",1,VLOOKUP($BE57,DADOS!$CO$5:$CP$7,2,FALSE))*IF($BF57="",1,VLOOKUP($BF57,DADOS!$CR$5:$CS$15,2,FALSE)),4),1)),0),"")) | BM57: =IF($BJ57="","",IFERROR(IF(ROUND(VLOOKUP($BJ57,DADOS!$CL$5:$CM$10,2,FALSE)*IF($BK57="",1,VLOOKUP($BK57,DADOS!$CO$5:$CP$7,2,FALSE))*IF($BL57="",1,VLOOKUP($BL57,DADOS!$CR$5:$CS$15,2,FALSE)),4)>0,MAX(1,FLOOR(ROUND(VLOOKUP($BJ57,DADOS!$CL$5:$CM$10,2,FALSE)*IF($BK57="",1,VLOOKUP($BK57,DADOS!$CO$5:$CP$7,2,FALSE))*IF($BL57="",1,VLOOKUP($BL57,DADOS!$CR$5:$CS$15,2,FALSE)),4),1)),0),"")) | BS57: =IF($BP57="","",IFERROR(IF(ROUND(VLOOKUP($BP57,DADOS!$CL$5:$CM$10,2,FALSE)*IF($BQ57="",1,VLOOKUP($BQ57,DADOS!$CO$5:$CP$7,2,FALSE))*IF($BR57="",1,VLOOKUP($BR57,DADOS!$CR$5:$CS$15,2,FALSE)),4)>0,MAX(1,FLOOR(ROUND(VLOOKUP($BP57,DADOS!$CL$5:$CM$10,2,FALSE)*IF($BQ57="",1,VLOOKUP($BQ57,DADOS!$CO$5:$CP$7,2,FALSE))*IF($BR57="",1,VLOOKUP($BR57,DADOS!$CR$5:$CS$15,2,FALSE)),4),1)),0),""))
D58: =IF('DADOS_CUSTOM'!$B$121,'DADOS_CUSTOM'!$B$125,"") | BA58: =IF($AX58="","",IFERROR(IF(ROUND(VLOOKUP($AX58,DADOS!$CL$5:$CM$10,2,FALSE)*IF($AY58="",1,VLOOKUP($AY58,DADOS!$CO$5:$CP$7,2,FALSE))*IF($AZ58="",1,VLOOKUP($AZ58,DADOS!$CR$5:$CS$15,2,FALSE)),4)>0,MAX(1,FLOOR(ROUND(VLOOKUP($AX58,DADOS!$CL$5:$CM$10,2,FALSE)*IF($AY58="",1,VLOOKUP($AY58,DADOS!$CO$5:$CP$7,2,FALSE))*IF($AZ58="",1,VLOOKUP($AZ58,DADOS!$CR$5:$CS$15,2,FALSE)),4),1)),0),"")) | BG58: =IF($BD58="","",IFERROR(IF(ROUND(VLOOKUP($BD58,DADOS!$CL$5:$CM$10,2,FALSE)*IF($BE58="",1,VLOOKUP($BE58,DADOS!$CO$5:$CP$7,2,FALSE))*IF($BF58="",1,VLOOKUP($BF58,DADOS!$CR$5:$CS$15,2,FALSE)),4)>0,MAX(1,FLOOR(ROUND(VLOOKUP($BD58,DADOS!$CL$5:$CM$10,2,FALSE)*IF($BE58="",1,VLOOKUP($BE58,DADOS!$CO$5:$CP$7,2,FALSE))*IF($BF58="",1,VLOOKUP($BF58,DADOS!$CR$5:$CS$15,2,FALSE)),4),1)),0),"")) | BM58: =IF($BJ58="","",IFERROR(IF(ROUND(VLOOKUP($BJ58,DADOS!$CL$5:$CM$10,2,FALSE)*IF($BK58="",1,VLOOKUP($BK58,DADOS!$CO$5:$CP$7,2,FALSE))*IF($BL58="",1,VLOOKUP($BL58,DADOS!$CR$5:$CS$15,2,FALSE)),4)>0,MAX(1,FLOOR(ROUND(VLOOKUP($BJ58,DADOS!$CL$5:$CM$10,2,FALSE)*IF($BK58="",1,VLOOKUP($BK58,DADOS!$CO$5:$CP$7,2,FALSE))*IF($BL58="",1,VLOOKUP($BL58,DADOS!$CR$5:$CS$15,2,FALSE)),4),1)),0),"")) | BS58: =IF($BP58="","",IFERROR(IF(ROUND(VLOOKUP($BP58,DADOS!$CL$5:$CM$10,2,FALSE)*IF($BQ58="",1,VLOOKUP($BQ58,DADOS!$CO$5:$CP$7,2,FALSE))*IF($BR58="",1,VLOOKUP($BR58,DADOS!$CR$5:$CS$15,2,FALSE)),4)>0,MAX(1,FLOOR(ROUND(VLOOKUP($BP58,DADOS!$CL$5:$CM$10,2,FALSE)*IF($BQ58="",1,VLOOKUP($BQ58,DADOS!$CO$5:$CP$7,2,FALSE))*IF($BR58="",1,VLOOKUP($BR58,DADOS!$CR$5:$CS$15,2,FALSE)),4),1)),0),""))
BA59: =IF($AX59="","",IFERROR(IF(ROUND(VLOOKUP($AX59,DADOS!$CL$5:$CM$10,2,FALSE)*IF($AY59="",1,VLOOKUP($AY59,DADOS!$CO$5:$CP$7,2,FALSE))*IF($AZ59="",1,VLOOKUP($AZ59,DADOS!$CR$5:$CS$15,2,FALSE)),4)>0,MAX(1,FLOOR(ROUND(VLOOKUP($AX59,DADOS!$CL$5:$CM$10,2,FALSE)*IF($AY59="",1,VLOOKUP($AY59,DADOS!$CO$5:$CP$7,2,FALSE))*IF($AZ59="",1,VLOOKUP($AZ59,DADOS!$CR$5:$CS$15,2,FALSE)),4),1)),0),"")) | BG59: =IF($BD59="","",IFERROR(IF(ROUND(VLOOKUP($BD59,DADOS!$CL$5:$CM$10,2,FALSE)*IF($BE59="",1,VLOOKUP($BE59,DADOS!$CO$5:$CP$7,2,FALSE))*IF($BF59="",1,VLOOKUP($BF59,DADOS!$CR$5:$CS$15,2,FALSE)),4)>0,MAX(1,FLOOR(ROUND(VLOOKUP($BD59,DADOS!$CL$5:$CM$10,2,FALSE)*IF($BE59="",1,VLOOKUP($BE59,DADOS!$CO$5:$CP$7,2,FALSE))*IF($BF59="",1,VLOOKUP($BF59,DADOS!$CR$5:$CS$15,2,FALSE)),4),1)),0),"")) | BM59: =IF($BJ59="","",IFERROR(IF(ROUND(VLOOKUP($BJ59,DADOS!$CL$5:$CM$10,2,FALSE)*IF($BK59="",1,VLOOKUP($BK59,DADOS!$CO$5:$CP$7,2,FALSE))*IF($BL59="",1,VLOOKUP($BL59,DADOS!$CR$5:$CS$15,2,FALSE)),4)>0,MAX(1,FLOOR(ROUND(VLOOKUP($BJ59,DADOS!$CL$5:$CM$10,2,FALSE)*IF($BK59="",1,VLOOKUP($BK59,DADOS!$CO$5:$CP$7,2,FALSE))*IF($BL59="",1,VLOOKUP($BL59,DADOS!$CR$5:$CS$15,2,FALSE)),4),1)),0),"")) | BS59: =IF($BP59="","",IFERROR(IF(ROUND(VLOOKUP($BP59,DADOS!$CL$5:$CM$10,2,FALSE)*IF($BQ59="",1,VLOOKUP($BQ59,DADOS!$CO$5:$CP$7,2,FALSE))*IF($BR59="",1,VLOOKUP($BR59,DADOS!$CR$5:$CS$15,2,FALSE)),4)>0,MAX(1,FLOOR(ROUND(VLOOKUP($BP59,DADOS!$CL$5:$CM$10,2,FALSE)*IF($BQ59="",1,VLOOKUP($BQ59,DADOS!$CO$5:$CP$7,2,FALSE))*IF($BR59="",1,VLOOKUP($BR59,DADOS!$CR$5:$CS$15,2,FALSE)),4),1)),0),""))
BA60: =IF($AX60="","",IFERROR(IF(ROUND(VLOOKUP($AX60,DADOS!$CL$5:$CM$10,2,FALSE)*IF($AY60="",1,VLOOKUP($AY60,DADOS!$CO$5:$CP$7,2,FALSE))*IF($AZ60="",1,VLOOKUP($AZ60,DADOS!$CR$5:$CS$15,2,FALSE)),4)>0,MAX(1,FLOOR(ROUND(VLOOKUP($AX60,DADOS!$CL$5:$CM$10,2,FALSE)*IF($AY60="",1,VLOOKUP($AY60,DADOS!$CO$5:$CP$7,2,FALSE))*IF($AZ60="",1,VLOOKUP($AZ60,DADOS!$CR$5:$CS$15,2,FALSE)),4),1)),0),"")) | BG60: =IF($BD60="","",IFERROR(IF(ROUND(VLOOKUP($BD60,DADOS!$CL$5:$CM$10,2,FALSE)*IF($BE60="",1,VLOOKUP($BE60,DADOS!$CO$5:$CP$7,2,FALSE))*IF($BF60="",1,VLOOKUP($BF60,DADOS!$CR$5:$CS$15,2,FALSE)),4)>0,MAX(1,FLOOR(ROUND(VLOOKUP($BD60,DADOS!$CL$5:$CM$10,2,FALSE)*IF($BE60="",1,VLOOKUP($BE60,DADOS!$CO$5:$CP$7,2,FALSE))*IF($BF60="",1,VLOOKUP($BF60,DADOS!$CR$5:$CS$15,2,FALSE)),4),1)),0),"")) | BM60: =IF($BJ60="","",IFERROR(IF(ROUND(VLOOKUP($BJ60,DADOS!$CL$5:$CM$10,2,FALSE)*IF($BK60="",1,VLOOKUP($BK60,DADOS!$CO$5:$CP$7,2,FALSE))*IF($BL60="",1,VLOOKUP($BL60,DADOS!$CR$5:$CS$15,2,FALSE)),4)>0,MAX(1,FLOOR(ROUND(VLOOKUP($BJ60,DADOS!$CL$5:$CM$10,2,FALSE)*IF($BK60="",1,VLOOKUP($BK60,DADOS!$CO$5:$CP$7,2,FALSE))*IF($BL60="",1,VLOOKUP($BL60,DADOS!$CR$5:$CS$15,2,FALSE)),4),1)),0),"")) | BS60: =IF($BP60="","",IFERROR(IF(ROUND(VLOOKUP($BP60,DADOS!$CL$5:$CM$10,2,FALSE)*IF($BQ60="",1,VLOOKUP($BQ60,DADOS!$CO$5:$CP$7,2,FALSE))*IF($BR60="",1,VLOOKUP($BR60,DADOS!$CR$5:$CS$15,2,FALSE)),4)>0,MAX(1,FLOOR(ROUND(VLOOKUP($BP60,DADOS!$CL$5:$CM$10,2,FALSE)*IF($BQ60="",1,VLOOKUP($BQ60,DADOS!$CO$5:$CP$7,2,FALSE))*IF($BR60="",1,VLOOKUP($BR60,DADOS!$CR$5:$CS$15,2,FALSE)),4),1)),0),""))
D61: EM USO | BA61: =IF($AX61="","",IFERROR(IF(ROUND(VLOOKUP($AX61,DADOS!$CL$5:$CM$10,2,FALSE)*IF($AY61="",1,VLOOKUP($AY61,DADOS!$CO$5:$CP$7,2,FALSE))*IF($AZ61="",1,VLOOKUP($AZ61,DADOS!$CR$5:$CS$15,2,FALSE)),4)>0,MAX(1,FLOOR(ROUND(VLOOKUP($AX61,DADOS!$CL$5:$CM$10,2,FALSE)*IF($AY61="",1,VLOOKUP($AY61,DADOS!$CO$5:$CP$7,2,FALSE))*IF($AZ61="",1,VLOOKUP($AZ61,DADOS!$CR$5:$CS$15,2,FALSE)),4),1)),0),"")) | BG61: =IF($BD61="","",IFERROR(IF(ROUND(VLOOKUP($BD61,DADOS!$CL$5:$CM$10,2,FALSE)*IF($BE61="",1,VLOOKUP($BE61,DADOS!$CO$5:$CP$7,2,FALSE))*IF($BF61="",1,VLOOKUP($BF61,DADOS!$CR$5:$CS$15,2,FALSE)),4)>0,MAX(1,FLOOR(ROUND(VLOOKUP($BD61,DADOS!$CL$5:$CM$10,2,FALSE)*IF($BE61="",1,VLOOKUP($BE61,DADOS!$CO$5:$CP$7,2,FALSE))*IF($BF61="",1,VLOOKUP($BF61,DADOS!$CR$5:$CS$15,2,FALSE)),4),1)),0),"")) | BM61: =IF($BJ61="","",IFERROR(IF(ROUND(VLOOKUP($BJ61,DADOS!$CL$5:$CM$10,2,FALSE)*IF($BK61="",1,VLOOKUP($BK61,DADOS!$CO$5:$CP$7,2,FALSE))*IF($BL61="",1,VLOOKUP($BL61,DADOS!$CR$5:$CS$15,2,FALSE)),4)>0,MAX(1,FLOOR(ROUND(VLOOKUP($BJ61,DADOS!$CL$5:$CM$10,2,FALSE)*IF($BK61="",1,VLOOKUP($BK61,DADOS!$CO$5:$CP$7,2,FALSE))*IF($BL61="",1,VLOOKUP($BL61,DADOS!$CR$5:$CS$15,2,FALSE)),4),1)),0),"")) | BS61: =IF($BP61="","",IFERROR(IF(ROUND(VLOOKUP($BP61,DADOS!$CL$5:$CM$10,2,FALSE)*IF($BQ61="",1,VLOOKUP($BQ61,DADOS!$CO$5:$CP$7,2,FALSE))*IF($BR61="",1,VLOOKUP($BR61,DADOS!$CR$5:$CS$15,2,FALSE)),4)>0,MAX(1,FLOOR(ROUND(VLOOKUP($BP61,DADOS!$CL$5:$CM$10,2,FALSE)*IF($BQ61="",1,VLOOKUP($BQ61,DADOS!$CO$5:$CP$7,2,FALSE))*IF($BR61="",1,VLOOKUP($BR61,DADOS!$CR$5:$CS$15,2,FALSE)),4),1)),0),""))
BA62: =IF($AX62="","",IFERROR(IF(ROUND(VLOOKUP($AX62,DADOS!$CL$5:$CM$10,2,FALSE)*IF($AY62="",1,VLOOKUP($AY62,DADOS!$CO$5:$CP$7,2,FALSE))*IF($AZ62="",1,VLOOKUP($AZ62,DADOS!$CR$5:$CS$15,2,FALSE)),4)>0,MAX(1,FLOOR(ROUND(VLOOKUP($AX62,DADOS!$CL$5:$CM$10,2,FALSE)*IF($AY62="",1,VLOOKUP($AY62,DADOS!$CO$5:$CP$7,2,FALSE))*IF($AZ62="",1,VLOOKUP($AZ62,DADOS!$CR$5:$CS$15,2,FALSE)),4),1)),0),"")) | BG62: =IF($BD62="","",IFERROR(IF(ROUND(VLOOKUP($BD62,DADOS!$CL$5:$CM$10,2,FALSE)*IF($BE62="",1,VLOOKUP($BE62,DADOS!$CO$5:$CP$7,2,FALSE))*IF($BF62="",1,VLOOKUP($BF62,DADOS!$CR$5:$CS$15,2,FALSE)),4)>0,MAX(1,FLOOR(ROUND(VLOOKUP($BD62,DADOS!$CL$5:$CM$10,2,FALSE)*IF($BE62="",1,VLOOKUP($BE62,DADOS!$CO$5:$CP$7,2,FALSE))*IF($BF62="",1,VLOOKUP($BF62,DADOS!$CR$5:$CS$15,2,FALSE)),4),1)),0),"")) | BM62: =IF($BJ62="","",IFERROR(IF(ROUND(VLOOKUP($BJ62,DADOS!$CL$5:$CM$10,2,FALSE)*IF($BK62="",1,VLOOKUP($BK62,DADOS!$CO$5:$CP$7,2,FALSE))*IF($BL62="",1,VLOOKUP($BL62,DADOS!$CR$5:$CS$15,2,FALSE)),4)>0,MAX(1,FLOOR(ROUND(VLOOKUP($BJ62,DADOS!$CL$5:$CM$10,2,FALSE)*IF($BK62="",1,VLOOKUP($BK62,DADOS!$CO$5:$CP$7,2,FALSE))*IF($BL62="",1,VLOOKUP($BL62,DADOS!$CR$5:$CS$15,2,FALSE)),4),1)),0),"")) | BS62: =IF($BP62="","",IFERROR(IF(ROUND(VLOOKUP($BP62,DADOS!$CL$5:$CM$10,2,FALSE)*IF($BQ62="",1,VLOOKUP($BQ62,DADOS!$CO$5:$CP$7,2,FALSE))*IF($BR62="",1,VLOOKUP($BR62,DADOS!$CR$5:$CS$15,2,FALSE)),4)>0,MAX(1,FLOOR(ROUND(VLOOKUP($BP62,DADOS!$CL$5:$CM$10,2,FALSE)*IF($BQ62="",1,VLOOKUP($BQ62,DADOS!$CO$5:$CP$7,2,FALSE))*IF($BR62="",1,VLOOKUP($BR62,DADOS!$CR$5:$CS$15,2,FALSE)),4),1)),0),""))
D63: MÃO PRINCIPAL | S63: MÃO SECUNDÁRIA | AH63: VESTINDO | BA63: =IF($AX63="","",IFERROR(IF(ROUND(VLOOKUP($AX63,DADOS!$CL$5:$CM$10,2,FALSE)*IF($AY63="",1,VLOOKUP($AY63,DADOS!$CO$5:$CP$7,2,FALSE))*IF($AZ63="",1,VLOOKUP($AZ63,DADOS!$CR$5:$CS$15,2,FALSE)),4)>0,MAX(1,FLOOR(ROUND(VLOOKUP($AX63,DADOS!$CL$5:$CM$10,2,FALSE)*IF($AY63="",1,VLOOKUP($AY63,DADOS!$CO$5:$CP$7,2,FALSE))*IF($AZ63="",1,VLOOKUP($AZ63,DADOS!$CR$5:$CS$15,2,FALSE)),4),1)),0),"")) | BG63: =IF($BD63="","",IFERROR(IF(ROUND(VLOOKUP($BD63,DADOS!$CL$5:$CM$10,2,FALSE)*IF($BE63="",1,VLOOKUP($BE63,DADOS!$CO$5:$CP$7,2,FALSE))*IF($BF63="",1,VLOOKUP($BF63,DADOS!$CR$5:$CS$15,2,FALSE)),4)>0,MAX(1,FLOOR(ROUND(VLOOKUP($BD63,DADOS!$CL$5:$CM$10,2,FALSE)*IF($BE63="",1,VLOOKUP($BE63,DADOS!$CO$5:$CP$7,2,FALSE))*IF($BF63="",1,VLOOKUP($BF63,DADOS!$CR$5:$CS$15,2,FALSE)),4),1)),0),"")) | BM63: =IF($BJ63="","",IFERROR(IF(ROUND(VLOOKUP($BJ63,DADOS!$CL$5:$CM$10,2,FALSE)*IF($BK63="",1,VLOOKUP($BK63,DADOS!$CO$5:$CP$7,2,FALSE))*IF($BL63="",1,VLOOKUP($BL63,DADOS!$CR$5:$CS$15,2,FALSE)),4)>0,MAX(1,FLOOR(ROUND(VLOOKUP($BJ63,DADOS!$CL$5:$CM$10,2,FALSE)*IF($BK63="",1,VLOOKUP($BK63,DADOS!$CO$5:$CP$7,2,FALSE))*IF($BL63="",1,VLOOKUP($BL63,DADOS!$CR$5:$CS$15,2,FALSE)),4),1)),0),"")) | BS63: =IF($BP63="","",IFERROR(IF(ROUND(VLOOKUP($BP63,DADOS!$CL$5:$CM$10,2,FALSE)*IF($BQ63="",1,VLOOKUP($BQ63,DADOS!$CO$5:$CP$7,2,FALSE))*IF($BR63="",1,VLOOKUP($BR63,DADOS!$CR$5:$CS$15,2,FALSE)),4)>0,MAX(1,FLOOR(ROUND(VLOOKUP($BP63,DADOS!$CL$5:$CM$10,2,FALSE)*IF($BQ63="",1,VLOOKUP($BQ63,DADOS!$CO$5:$CP$7,2,FALSE))*IF($BR63="",1,VLOOKUP($BR63,DADOS!$CR$5:$CS$15,2,FALSE)),4),1)),0),""))
D64: Soco | S64: — | AH64: Traje 1 | BA64: =IF($AX64="","",IFERROR(IF(ROUND(VLOOKUP($AX64,DADOS!$CL$5:$CM$10,2,FALSE)*IF($AY64="",1,VLOOKUP($AY64,DADOS!$CO$5:$CP$7,2,FALSE))*IF($AZ64="",1,VLOOKUP($AZ64,DADOS!$CR$5:$CS$15,2,FALSE)),4)>0,MAX(1,FLOOR(ROUND(VLOOKUP($AX64,DADOS!$CL$5:$CM$10,2,FALSE)*IF($AY64="",1,VLOOKUP($AY64,DADOS!$CO$5:$CP$7,2,FALSE))*IF($AZ64="",1,VLOOKUP($AZ64,DADOS!$CR$5:$CS$15,2,FALSE)),4),1)),0),"")) | BG64: =IF($BD64="","",IFERROR(IF(ROUND(VLOOKUP($BD64,DADOS!$CL$5:$CM$10,2,FALSE)*IF($BE64="",1,VLOOKUP($BE64,DADOS!$CO$5:$CP$7,2,FALSE))*IF($BF64="",1,VLOOKUP($BF64,DADOS!$CR$5:$CS$15,2,FALSE)),4)>0,MAX(1,FLOOR(ROUND(VLOOKUP($BD64,DADOS!$CL$5:$CM$10,2,FALSE)*IF($BE64="",1,VLOOKUP($BE64,DADOS!$CO$5:$CP$7,2,FALSE))*IF($BF64="",1,VLOOKUP($BF64,DADOS!$CR$5:$CS$15,2,FALSE)),4),1)),0),"")) | BM64: =IF($BJ64="","",IFERROR(IF(ROUND(VLOOKUP($BJ64,DADOS!$CL$5:$CM$10,2,FALSE)*IF($BK64="",1,VLOOKUP($BK64,DADOS!$CO$5:$CP$7,2,FALSE))*IF($BL64="",1,VLOOKUP($BL64,DADOS!$CR$5:$CS$15,2,FALSE)),4)>0,MAX(1,FLOOR(ROUND(VLOOKUP($BJ64,DADOS!$CL$5:$CM$10,2,FALSE)*IF($BK64="",1,VLOOKUP($BK64,DADOS!$CO$5:$CP$7,2,FALSE))*IF($BL64="",1,VLOOKUP($BL64,DADOS!$CR$5:$CS$15,2,FALSE)),4),1)),0),"")) | BS64: =IF($BP64="","",IFERROR(IF(ROUND(VLOOKUP($BP64,DADOS!$CL$5:$CM$10,2,FALSE)*IF($BQ64="",1,VLOOKUP($BQ64,DADOS!$CO$5:$CP$7,2,FALSE))*IF($BR64="",1,VLOOKUP($BR64,DADOS!$CR$5:$CS$15,2,FALSE)),4)>0,MAX(1,FLOOR(ROUND(VLOOKUP($BP64,DADOS!$CL$5:$CM$10,2,FALSE)*IF($BQ64="",1,VLOOKUP($BQ64,DADOS!$CO$5:$CP$7,2,FALSE))*IF($BR64="",1,VLOOKUP($BR64,DADOS!$CR$5:$CS$15,2,FALSE)),4),1)),0),""))
BA65: =IF($AX65="","",IFERROR(IF(ROUND(VLOOKUP($AX65,DADOS!$CL$5:$CM$10,2,FALSE)*IF($AY65="",1,VLOOKUP($AY65,DADOS!$CO$5:$CP$7,2,FALSE))*IF($AZ65="",1,VLOOKUP($AZ65,DADOS!$CR$5:$CS$15,2,FALSE)),4)>0,MAX(1,FLOOR(ROUND(VLOOKUP($AX65,DADOS!$CL$5:$CM$10,2,FALSE)*IF($AY65="",1,VLOOKUP($AY65,DADOS!$CO$5:$CP$7,2,FALSE))*IF($AZ65="",1,VLOOKUP($AZ65,DADOS!$CR$5:$CS$15,2,FALSE)),4),1)),0),"")) | BG65: =IF($BD65="","",IFERROR(IF(ROUND(VLOOKUP($BD65,DADOS!$CL$5:$CM$10,2,FALSE)*IF($BE65="",1,VLOOKUP($BE65,DADOS!$CO$5:$CP$7,2,FALSE))*IF($BF65="",1,VLOOKUP($BF65,DADOS!$CR$5:$CS$15,2,FALSE)),4)>0,MAX(1,FLOOR(ROUND(VLOOKUP($BD65,DADOS!$CL$5:$CM$10,2,FALSE)*IF($BE65="",1,VLOOKUP($BE65,DADOS!$CO$5:$CP$7,2,FALSE))*IF($BF65="",1,VLOOKUP($BF65,DADOS!$CR$5:$CS$15,2,FALSE)),4),1)),0),"")) | BM65: =IF($BJ65="","",IFERROR(IF(ROUND(VLOOKUP($BJ65,DADOS!$CL$5:$CM$10,2,FALSE)*IF($BK65="",1,VLOOKUP($BK65,DADOS!$CO$5:$CP$7,2,FALSE))*IF($BL65="",1,VLOOKUP($BL65,DADOS!$CR$5:$CS$15,2,FALSE)),4)>0,MAX(1,FLOOR(ROUND(VLOOKUP($BJ65,DADOS!$CL$5:$CM$10,2,FALSE)*IF($BK65="",1,VLOOKUP($BK65,DADOS!$CO$5:$CP$7,2,FALSE))*IF($BL65="",1,VLOOKUP($BL65,DADOS!$CR$5:$CS$15,2,FALSE)),4),1)),0),"")) | BS65: =IF($BP65="","",IFERROR(IF(ROUND(VLOOKUP($BP65,DADOS!$CL$5:$CM$10,2,FALSE)*IF($BQ65="",1,VLOOKUP($BQ65,DADOS!$CO$5:$CP$7,2,FALSE))*IF($BR65="",1,VLOOKUP($BR65,DADOS!$CR$5:$CS$15,2,FALSE)),4)>0,MAX(1,FLOOR(ROUND(VLOOKUP($BP65,DADOS!$CL$5:$CM$10,2,FALSE)*IF($BQ65="",1,VLOOKUP($BQ65,DADOS!$CO$5:$CP$7,2,FALSE))*IF($BR65="",1,VLOOKUP($BR65,DADOS!$CR$5:$CS$15,2,FALSE)),4),1)),0),""))
D66: =IF(DADOS!$CZ$6=1,DADOS!$CZ$9&IF(DADOS!$CZ$25=0," · para outra arma, guarde ela nos Equipáveis guardados"," · sem propriedade · o dado sobe com a maestria"),IF(DADOS!$CZ$7="","Não está nos equipáveis guardados",DADOS!$CZ$13&IF(DADOS!$CZ$10<>""," · "&DADOS!$CZ$10,"")&IF(DADOS!$CZ$12=1," · nas duas mãos",IF(DADOS!$CZ$8=2," · duas mãos",""))&IF(DADOS!$CZ$14<>""," · "&DADOS!$CZ$14,"")&IF(DADOS!$CZ$15<>""," · recarga a cada "&DADOS!$CZ$15,""))) | S66: =IF(DADOS!$CZ$8=2,"Ocupada: a arma da outra mão é de duas mãos",IF($S$64="Nas duas mãos",IF(DADOS!$CZ$12=1,"A mesma arma, nas duas mãos","A arma da outra mão não é Versátil"),IF(DADOS!$CZ$17=0,IF(DADOS!$CZ$26=0,"Mão livre · arma de uma mão ou escudo guardado aparece aqui","Mão livre"),IF(DADOS!$CZ$18="","Não está nos equipáveis guardados",IF(DADOS!$CZ$19=1,"Escudo · "&DADOS!$CZ$21,DADOS!$CZ$20&IF(DADOS!$CZ$21<>""," · "&DADOS!$CZ$21,"")&IF(DADOS!$CZ$23<>""," · "&DADOS!$CZ$23,"")&IF(DADOS!$CZ$24<>""," · recarga a cada "&DADOS!$CZ$24,"")))))) | AH66: =IF(DADOS!$CZ$27=0,"Sem uniforme: vale a proteção do cobrir-se","Proteção "&DADOS!$CZ$28&" · "&IF(DADOS!$CZ$29&""="—","sem teto de Destreza","teto de Destreza "&DADOS!$CZ$29)) | BA66: =IF($AX66="","",IFERROR(IF(ROUND(VLOOKUP($AX66,DADOS!$CL$5:$CM$10,2,FALSE)*IF($AY66="",1,VLOOKUP($AY66,DADOS!$CO$5:$CP$7,2,FALSE))*IF($AZ66="",1,VLOOKUP($AZ66,DADOS!$CR$5:$CS$15,2,FALSE)),4)>0,MAX(1,FLOOR(ROUND(VLOOKUP($AX66,DADOS!$CL$5:$CM$10,2,FALSE)*IF($AY66="",1,VLOOKUP($AY66,DADOS!$CO$5:$CP$7,2,FALSE))*IF($AZ66="",1,VLOOKUP($AZ66,DADOS!$CR$5:$CS$15,2,FALSE)),4),1)),0),"")) | BG66: =IF($BD66="","",IFERROR(IF(ROUND(VLOOKUP($BD66,DADOS!$CL$5:$CM$10,2,FALSE)*IF($BE66="",1,VLOOKUP($BE66,DADOS!$CO$5:$CP$7,2,FALSE))*IF($BF66="",1,VLOOKUP($BF66,DADOS!$CR$5:$CS$15,2,FALSE)),4)>0,MAX(1,FLOOR(ROUND(VLOOKUP($BD66,DADOS!$CL$5:$CM$10,2,FALSE)*IF($BE66="",1,VLOOKUP($BE66,DADOS!$CO$5:$CP$7,2,FALSE))*IF($BF66="",1,VLOOKUP($BF66,DADOS!$CR$5:$CS$15,2,FALSE)),4),1)),0),"")) | BM66: =IF($BJ66="","",IFERROR(IF(ROUND(VLOOKUP($BJ66,DADOS!$CL$5:$CM$10,2,FALSE)*IF($BK66="",1,VLOOKUP($BK66,DADOS!$CO$5:$CP$7,2,FALSE))*IF($BL66="",1,VLOOKUP($BL66,DADOS!$CR$5:$CS$15,2,FALSE)),4)>0,MAX(1,FLOOR(ROUND(VLOOKUP($BJ66,DADOS!$CL$5:$CM$10,2,FALSE)*IF($BK66="",1,VLOOKUP($BK66,DADOS!$CO$5:$CP$7,2,FALSE))*IF($BL66="",1,VLOOKUP($BL66,DADOS!$CR$5:$CS$15,2,FALSE)),4),1)),0),"")) | BS66: =IF($BP66="","",IFERROR(IF(ROUND(VLOOKUP($BP66,DADOS!$CL$5:$CM$10,2,FALSE)*IF($BQ66="",1,VLOOKUP($BQ66,DADOS!$CO$5:$CP$7,2,FALSE))*IF($BR66="",1,VLOOKUP($BR66,DADOS!$CR$5:$CS$15,2,FALSE)),4)>0,MAX(1,FLOOR(ROUND(VLOOKUP($BP66,DADOS!$CL$5:$CM$10,2,FALSE)*IF($BQ66="",1,VLOOKUP($BQ66,DADOS!$CO$5:$CP$7,2,FALSE))*IF($BR66="",1,VLOOKUP($BR66,DADOS!$CR$5:$CS$15,2,FALSE)),4),1)),0),""))
D67: =IF(DADOS!$CZ$16=1,"Treinada","Sem treino: desvantagem") | K67: =IF(DADOS!$CZ$11=0,"Sem requisito de Força",IF(DADOS!$CZ$36=1,"Falta Força: "&DADOS!$CZ$5&" de "&DADOS!$CZ$11,"Força "&DADOS!$CZ$5&" de "&DADOS!$CZ$11)) | S67: =IF(DADOS!$CZ$17=0,"—",IF(DADOS!$CZ$22=0,"Sem requisito de Força",IF(DADOS!$CZ$37=1,"Falta Força: "&DADOS!$CZ$5&" de "&DADOS!$CZ$22,"Força "&DADOS!$CZ$5&" de "&DADOS!$CZ$22))) | Z67: =IF(DADOS!$CZ$19=1,"Trava Selo de gesto","Sem escudo") | AH67: =IF(DADOS!$CZ$27=0,"—",IF(DADOS!$CZ$35=1,"Liberado no "&$AB$11,"Pede "&DADOS!$CZ$33)) | AO67: =IF(DADOS!$CZ$27=0,"—",IF(DADOS!$CZ$30=0,"Sem requisito de Força",IF(DADOS!$CZ$38=1,"Falta Força: "&DADOS!$CZ$5&" de "&DADOS!$CZ$30,"Força "&DADOS!$CZ$5&" de "&DADOS!$CZ$30))) | BA67: =IF($AX67="","",IFERROR(IF(ROUND(VLOOKUP($AX67,DADOS!$CL$5:$CM$10,2,FALSE)*IF($AY67="",1,VLOOKUP($AY67,DADOS!$CO$5:$CP$7,2,FALSE))*IF($AZ67="",1,VLOOKUP($AZ67,DADOS!$CR$5:$CS$15,2,FALSE)),4)>0,MAX(1,FLOOR(ROUND(VLOOKUP($AX67,DADOS!$CL$5:$CM$10,2,FALSE)*IF($AY67="",1,VLOOKUP($AY67,DADOS!$CO$5:$CP$7,2,FALSE))*IF($AZ67="",1,VLOOKUP($AZ67,DADOS!$CR$5:$CS$15,2,FALSE)),4),1)),0),"")) | BG67: =IF($BD67="","",IFERROR(IF(ROUND(VLOOKUP($BD67,DADOS!$CL$5:$CM$10,2,FALSE)*IF($BE67="",1,VLOOKUP($BE67,DADOS!$CO$5:$CP$7,2,FALSE))*IF($BF67="",1,VLOOKUP($BF67,DADOS!$CR$5:$CS$15,2,FALSE)),4)>0,MAX(1,FLOOR(ROUND(VLOOKUP($BD67,DADOS!$CL$5:$CM$10,2,FALSE)*IF($BE67="",1,VLOOKUP($BE67,DADOS!$CO$5:$CP$7,2,FALSE))*IF($BF67="",1,VLOOKUP($BF67,DADOS!$CR$5:$CS$15,2,FALSE)),4),1)),0),"")) | BM67: =IF($BJ67="","",IFERROR(IF(ROUND(VLOOKUP($BJ67,DADOS!$CL$5:$CM$10,2,FALSE)*IF($BK67="",1,VLOOKUP($BK67,DADOS!$CO$5:$CP$7,2,FALSE))*IF($BL67="",1,VLOOKUP($BL67,DADOS!$CR$5:$CS$15,2,FALSE)),4)>0,MAX(1,FLOOR(ROUND(VLOOKUP($BJ67,DADOS!$CL$5:$CM$10,2,FALSE)*IF($BK67="",1,VLOOKUP($BK67,DADOS!$CO$5:$CP$7,2,FALSE))*IF($BL67="",1,VLOOKUP($BL67,DADOS!$CR$5:$CS$15,2,FALSE)),4),1)),0),"")) | BS67: =IF($BP67="","",IFERROR(IF(ROUND(VLOOKUP($BP67,DADOS!$CL$5:$CM$10,2,FALSE)*IF($BQ67="",1,VLOOKUP($BQ67,DADOS!$CO$5:$CP$7,2,FALSE))*IF($BR67="",1,VLOOKUP($BR67,DADOS!$CR$5:$CS$15,2,FALSE)),4)>0,MAX(1,FLOOR(ROUND(VLOOKUP($BP67,DADOS!$CL$5:$CM$10,2,FALSE)*IF($BQ67="",1,VLOOKUP($BQ67,DADOS!$CO$5:$CP$7,2,FALSE))*IF($BR67="",1,VLOOKUP($BR67,DADOS!$CR$5:$CS$15,2,FALSE)),4),1)),0),""))
BA68: =IF($AX68="","",IFERROR(IF(ROUND(VLOOKUP($AX68,DADOS!$CL$5:$CM$10,2,FALSE)*IF($AY68="",1,VLOOKUP($AY68,DADOS!$CO$5:$CP$7,2,FALSE))*IF($AZ68="",1,VLOOKUP($AZ68,DADOS!$CR$5:$CS$15,2,FALSE)),4)>0,MAX(1,FLOOR(ROUND(VLOOKUP($AX68,DADOS!$CL$5:$CM$10,2,FALSE)*IF($AY68="",1,VLOOKUP($AY68,DADOS!$CO$5:$CP$7,2,FALSE))*IF($AZ68="",1,VLOOKUP($AZ68,DADOS!$CR$5:$CS$15,2,FALSE)),4),1)),0),"")) | BG68: =IF($BD68="","",IFERROR(IF(ROUND(VLOOKUP($BD68,DADOS!$CL$5:$CM$10,2,FALSE)*IF($BE68="",1,VLOOKUP($BE68,DADOS!$CO$5:$CP$7,2,FALSE))*IF($BF68="",1,VLOOKUP($BF68,DADOS!$CR$5:$CS$15,2,FALSE)),4)>0,MAX(1,FLOOR(ROUND(VLOOKUP($BD68,DADOS!$CL$5:$CM$10,2,FALSE)*IF($BE68="",1,VLOOKUP($BE68,DADOS!$CO$5:$CP$7,2,FALSE))*IF($BF68="",1,VLOOKUP($BF68,DADOS!$CR$5:$CS$15,2,FALSE)),4),1)),0),"")) | BM68: =IF($BJ68="","",IFERROR(IF(ROUND(VLOOKUP($BJ68,DADOS!$CL$5:$CM$10,2,FALSE)*IF($BK68="",1,VLOOKUP($BK68,DADOS!$CO$5:$CP$7,2,FALSE))*IF($BL68="",1,VLOOKUP($BL68,DADOS!$CR$5:$CS$15,2,FALSE)),4)>0,MAX(1,FLOOR(ROUND(VLOOKUP($BJ68,DADOS!$CL$5:$CM$10,2,FALSE)*IF($BK68="",1,VLOOKUP($BK68,DADOS!$CO$5:$CP$7,2,FALSE))*IF($BL68="",1,VLOOKUP($BL68,DADOS!$CR$5:$CS$15,2,FALSE)),4),1)),0),"")) | BS68: =IF($BP68="","",IFERROR(IF(ROUND(VLOOKUP($BP68,DADOS!$CL$5:$CM$10,2,FALSE)*IF($BQ68="",1,VLOOKUP($BQ68,DADOS!$CO$5:$CP$7,2,FALSE))*IF($BR68="",1,VLOOKUP($BR68,DADOS!$CR$5:$CS$15,2,FALSE)),4)>0,MAX(1,FLOOR(ROUND(VLOOKUP($BP68,DADOS!$CL$5:$CM$10,2,FALSE)*IF($BQ68="",1,VLOOKUP($BQ68,DADOS!$CO$5:$CP$7,2,FALSE))*IF($BR68="",1,VLOOKUP($BR68,DADOS!$CR$5:$CS$15,2,FALSE)),4),1)),0),""))
D69: TREINO EM ARMAS | BA69: =IF($AX69="","",IFERROR(IF(ROUND(VLOOKUP($AX69,DADOS!$CL$5:$CM$10,2,FALSE)*IF($AY69="",1,VLOOKUP($AY69,DADOS!$CO$5:$CP$7,2,FALSE))*IF($AZ69="",1,VLOOKUP($AZ69,DADOS!$CR$5:$CS$15,2,FALSE)),4)>0,MAX(1,FLOOR(ROUND(VLOOKUP($AX69,DADOS!$CL$5:$CM$10,2,FALSE)*IF($AY69="",1,VLOOKUP($AY69,DADOS!$CO$5:$CP$7,2,FALSE))*IF($AZ69="",1,VLOOKUP($AZ69,DADOS!$CR$5:$CS$15,2,FALSE)),4),1)),0),"")) | BG69: =IF($BD69="","",IFERROR(IF(ROUND(VLOOKUP($BD69,DADOS!$CL$5:$CM$10,2,FALSE)*IF($BE69="",1,VLOOKUP($BE69,DADOS!$CO$5:$CP$7,2,FALSE))*IF($BF69="",1,VLOOKUP($BF69,DADOS!$CR$5:$CS$15,2,FALSE)),4)>0,MAX(1,FLOOR(ROUND(VLOOKUP($BD69,DADOS!$CL$5:$CM$10,2,FALSE)*IF($BE69="",1,VLOOKUP($BE69,DADOS!$CO$5:$CP$7,2,FALSE))*IF($BF69="",1,VLOOKUP($BF69,DADOS!$CR$5:$CS$15,2,FALSE)),4),1)),0),"")) | BM69: =IF($BJ69="","",IFERROR(IF(ROUND(VLOOKUP($BJ69,DADOS!$CL$5:$CM$10,2,FALSE)*IF($BK69="",1,VLOOKUP($BK69,DADOS!$CO$5:$CP$7,2,FALSE))*IF($BL69="",1,VLOOKUP($BL69,DADOS!$CR$5:$CS$15,2,FALSE)),4)>0,MAX(1,FLOOR(ROUND(VLOOKUP($BJ69,DADOS!$CL$5:$CM$10,2,FALSE)*IF($BK69="",1,VLOOKUP($BK69,DADOS!$CO$5:$CP$7,2,FALSE))*IF($BL69="",1,VLOOKUP($BL69,DADOS!$CR$5:$CS$15,2,FALSE)),4),1)),0),"")) | BS69: =IF($BP69="","",IFERROR(IF(ROUND(VLOOKUP($BP69,DADOS!$CL$5:$CM$10,2,FALSE)*IF($BQ69="",1,VLOOKUP($BQ69,DADOS!$CO$5:$CP$7,2,FALSE))*IF($BR69="",1,VLOOKUP($BR69,DADOS!$CR$5:$CS$15,2,FALSE)),4)>0,MAX(1,FLOOR(ROUND(VLOOKUP($BP69,DADOS!$CL$5:$CM$10,2,FALSE)*IF($BQ69="",1,VLOOKUP($BQ69,DADOS!$CO$5:$CP$7,2,FALSE))*IF($BR69="",1,VLOOKUP($BR69,DADOS!$CR$5:$CS$15,2,FALSE)),4),1)),0),""))
BA70: =IF($AX70="","",IFERROR(IF(ROUND(VLOOKUP($AX70,DADOS!$CL$5:$CM$10,2,FALSE)*IF($AY70="",1,VLOOKUP($AY70,DADOS!$CO$5:$CP$7,2,FALSE))*IF($AZ70="",1,VLOOKUP($AZ70,DADOS!$CR$5:$CS$15,2,FALSE)),4)>0,MAX(1,FLOOR(ROUND(VLOOKUP($AX70,DADOS!$CL$5:$CM$10,2,FALSE)*IF($AY70="",1,VLOOKUP($AY70,DADOS!$CO$5:$CP$7,2,FALSE))*IF($AZ70="",1,VLOOKUP($AZ70,DADOS!$CR$5:$CS$15,2,FALSE)),4),1)),0),"")) | BG70: =IF($BD70="","",IFERROR(IF(ROUND(VLOOKUP($BD70,DADOS!$CL$5:$CM$10,2,FALSE)*IF($BE70="",1,VLOOKUP($BE70,DADOS!$CO$5:$CP$7,2,FALSE))*IF($BF70="",1,VLOOKUP($BF70,DADOS!$CR$5:$CS$15,2,FALSE)),4)>0,MAX(1,FLOOR(ROUND(VLOOKUP($BD70,DADOS!$CL$5:$CM$10,2,FALSE)*IF($BE70="",1,VLOOKUP($BE70,DADOS!$CO$5:$CP$7,2,FALSE))*IF($BF70="",1,VLOOKUP($BF70,DADOS!$CR$5:$CS$15,2,FALSE)),4),1)),0),"")) | BM70: =IF($BJ70="","",IFERROR(IF(ROUND(VLOOKUP($BJ70,DADOS!$CL$5:$CM$10,2,FALSE)*IF($BK70="",1,VLOOKUP($BK70,DADOS!$CO$5:$CP$7,2,FALSE))*IF($BL70="",1,VLOOKUP($BL70,DADOS!$CR$5:$CS$15,2,FALSE)),4)>0,MAX(1,FLOOR(ROUND(VLOOKUP($BJ70,DADOS!$CL$5:$CM$10,2,FALSE)*IF($BK70="",1,VLOOKUP($BK70,DADOS!$CO$5:$CP$7,2,FALSE))*IF($BL70="",1,VLOOKUP($BL70,DADOS!$CR$5:$CS$15,2,FALSE)),4),1)),0),"")) | BS70: =IF($BP70="","",IFERROR(IF(ROUND(VLOOKUP($BP70,DADOS!$CL$5:$CM$10,2,FALSE)*IF($BQ70="",1,VLOOKUP($BQ70,DADOS!$CO$5:$CP$7,2,FALSE))*IF($BR70="",1,VLOOKUP($BR70,DADOS!$CR$5:$CS$15,2,FALSE)),4)>0,MAX(1,FLOOR(ROUND(VLOOKUP($BP70,DADOS!$CL$5:$CM$10,2,FALSE)*IF($BQ70="",1,VLOOKUP($BQ70,DADOS!$CO$5:$CP$7,2,FALSE))*IF($BR70="",1,VLOOKUP($BR70,DADOS!$CR$5:$CS$15,2,FALSE)),4),1)),0),""))
D71: FALSE | E71: LÂMINA LONGA | M71: FALSE | N71: ARMA DE FOGO | V71: FALSE | W71: PORRETE | AE71: FALSE | AF71: LÂMINA CURTA | AM71: FALSE | AN71: MASSA | BA71: =IF($AX71="","",IFERROR(IF(ROUND(VLOOKUP($AX71,DADOS!$CL$5:$CM$10,2,FALSE)*IF($AY71="",1,VLOOKUP($AY71,DADOS!$CO$5:$CP$7,2,FALSE))*IF($AZ71="",1,VLOOKUP($AZ71,DADOS!$CR$5:$CS$15,2,FALSE)),4)>0,MAX(1,FLOOR(ROUND(VLOOKUP($AX71,DADOS!$CL$5:$CM$10,2,FALSE)*IF($AY71="",1,VLOOKUP($AY71,DADOS!$CO$5:$CP$7,2,FALSE))*IF($AZ71="",1,VLOOKUP($AZ71,DADOS!$CR$5:$CS$15,2,FALSE)),4),1)),0),"")) | BG71: =IF($BD71="","",IFERROR(IF(ROUND(VLOOKUP($BD71,DADOS!$CL$5:$CM$10,2,FALSE)*IF($BE71="",1,VLOOKUP($BE71,DADOS!$CO$5:$CP$7,2,FALSE))*IF($BF71="",1,VLOOKUP($BF71,DADOS!$CR$5:$CS$15,2,FALSE)),4)>0,MAX(1,FLOOR(ROUND(VLOOKUP($BD71,DADOS!$CL$5:$CM$10,2,FALSE)*IF($BE71="",1,VLOOKUP($BE71,DADOS!$CO$5:$CP$7,2,FALSE))*IF($BF71="",1,VLOOKUP($BF71,DADOS!$CR$5:$CS$15,2,FALSE)),4),1)),0),"")) | BM71: =IF($BJ71="","",IFERROR(IF(ROUND(VLOOKUP($BJ71,DADOS!$CL$5:$CM$10,2,FALSE)*IF($BK71="",1,VLOOKUP($BK71,DADOS!$CO$5:$CP$7,2,FALSE))*IF($BL71="",1,VLOOKUP($BL71,DADOS!$CR$5:$CS$15,2,FALSE)),4)>0,MAX(1,FLOOR(ROUND(VLOOKUP($BJ71,DADOS!$CL$5:$CM$10,2,FALSE)*IF($BK71="",1,VLOOKUP($BK71,DADOS!$CO$5:$CP$7,2,FALSE))*IF($BL71="",1,VLOOKUP($BL71,DADOS!$CR$5:$CS$15,2,FALSE)),4),1)),0),"")) | BS71: =IF($BP71="","",IFERROR(IF(ROUND(VLOOKUP($BP71,DADOS!$CL$5:$CM$10,2,FALSE)*IF($BQ71="",1,VLOOKUP($BQ71,DADOS!$CO$5:$CP$7,2,FALSE))*IF($BR71="",1,VLOOKUP($BR71,DADOS!$CR$5:$CS$15,2,FALSE)),4)>0,MAX(1,FLOOR(ROUND(VLOOKUP($BP71,DADOS!$CL$5:$CM$10,2,FALSE)*IF($BQ71="",1,VLOOKUP($BQ71,DADOS!$CO$5:$CP$7,2,FALSE))*IF($BR71="",1,VLOOKUP($BR71,DADOS!$CR$5:$CS$15,2,FALSE)),4),1)),0),""))
D72: FALSE | E72: Espada Longa | M72: FALSE | N72: Espingarda | V72: FALSE | W72: Bastão | AE72: FALSE | AF72: Canivete | AM72: FALSE | AN72: Kanabō | BA72: =IF($AX72="","",IFERROR(IF(ROUND(VLOOKUP($AX72,DADOS!$CL$5:$CM$10,2,FALSE)*IF($AY72="",1,VLOOKUP($AY72,DADOS!$CO$5:$CP$7,2,FALSE))*IF($AZ72="",1,VLOOKUP($AZ72,DADOS!$CR$5:$CS$15,2,FALSE)),4)>0,MAX(1,FLOOR(ROUND(VLOOKUP($AX72,DADOS!$CL$5:$CM$10,2,FALSE)*IF($AY72="",1,VLOOKUP($AY72,DADOS!$CO$5:$CP$7,2,FALSE))*IF($AZ72="",1,VLOOKUP($AZ72,DADOS!$CR$5:$CS$15,2,FALSE)),4),1)),0),"")) | BG72: =IF($BD72="","",IFERROR(IF(ROUND(VLOOKUP($BD72,DADOS!$CL$5:$CM$10,2,FALSE)*IF($BE72="",1,VLOOKUP($BE72,DADOS!$CO$5:$CP$7,2,FALSE))*IF($BF72="",1,VLOOKUP($BF72,DADOS!$CR$5:$CS$15,2,FALSE)),4)>0,MAX(1,FLOOR(ROUND(VLOOKUP($BD72,DADOS!$CL$5:$CM$10,2,FALSE)*IF($BE72="",1,VLOOKUP($BE72,DADOS!$CO$5:$CP$7,2,FALSE))*IF($BF72="",1,VLOOKUP($BF72,DADOS!$CR$5:$CS$15,2,FALSE)),4),1)),0),"")) | BM72: =IF($BJ72="","",IFERROR(IF(ROUND(VLOOKUP($BJ72,DADOS!$CL$5:$CM$10,2,FALSE)*IF($BK72="",1,VLOOKUP($BK72,DADOS!$CO$5:$CP$7,2,FALSE))*IF($BL72="",1,VLOOKUP($BL72,DADOS!$CR$5:$CS$15,2,FALSE)),4)>0,MAX(1,FLOOR(ROUND(VLOOKUP($BJ72,DADOS!$CL$5:$CM$10,2,FALSE)*IF($BK72="",1,VLOOKUP($BK72,DADOS!$CO$5:$CP$7,2,FALSE))*IF($BL72="",1,VLOOKUP($BL72,DADOS!$CR$5:$CS$15,2,FALSE)),4),1)),0),"")) | BS72: =IF($BP72="","",IFERROR(IF(ROUND(VLOOKUP($BP72,DADOS!$CL$5:$CM$10,2,FALSE)*IF($BQ72="",1,VLOOKUP($BQ72,DADOS!$CO$5:$CP$7,2,FALSE))*IF($BR72="",1,VLOOKUP($BR72,DADOS!$CR$5:$CS$15,2,FALSE)),4)>0,MAX(1,FLOOR(ROUND(VLOOKUP($BP72,DADOS!$CL$5:$CM$10,2,FALSE)*IF($BQ72="",1,VLOOKUP($BQ72,DADOS!$CO$5:$CP$7,2,FALSE))*IF($BR72="",1,VLOOKUP($BR72,DADOS!$CR$5:$CS$15,2,FALSE)),4),1)),0),""))
D73: FALSE | E73: Espadão | M73: FALSE | N73: Metralhadora Pesada | V73: FALSE | W73: Bō | AE73: FALSE | AF73: Faca | AM73: FALSE | AN73: Marreta | BA73: =IF($AX73="","",IFERROR(IF(ROUND(VLOOKUP($AX73,DADOS!$CL$5:$CM$10,2,FALSE)*IF($AY73="",1,VLOOKUP($AY73,DADOS!$CO$5:$CP$7,2,FALSE))*IF($AZ73="",1,VLOOKUP($AZ73,DADOS!$CR$5:$CS$15,2,FALSE)),4)>0,MAX(1,FLOOR(ROUND(VLOOKUP($AX73,DADOS!$CL$5:$CM$10,2,FALSE)*IF($AY73="",1,VLOOKUP($AY73,DADOS!$CO$5:$CP$7,2,FALSE))*IF($AZ73="",1,VLOOKUP($AZ73,DADOS!$CR$5:$CS$15,2,FALSE)),4),1)),0),"")) | BG73: =IF($BD73="","",IFERROR(IF(ROUND(VLOOKUP($BD73,DADOS!$CL$5:$CM$10,2,FALSE)*IF($BE73="",1,VLOOKUP($BE73,DADOS!$CO$5:$CP$7,2,FALSE))*IF($BF73="",1,VLOOKUP($BF73,DADOS!$CR$5:$CS$15,2,FALSE)),4)>0,MAX(1,FLOOR(ROUND(VLOOKUP($BD73,DADOS!$CL$5:$CM$10,2,FALSE)*IF($BE73="",1,VLOOKUP($BE73,DADOS!$CO$5:$CP$7,2,FALSE))*IF($BF73="",1,VLOOKUP($BF73,DADOS!$CR$5:$CS$15,2,FALSE)),4),1)),0),"")) | BM73: =IF($BJ73="","",IFERROR(IF(ROUND(VLOOKUP($BJ73,DADOS!$CL$5:$CM$10,2,FALSE)*IF($BK73="",1,VLOOKUP($BK73,DADOS!$CO$5:$CP$7,2,FALSE))*IF($BL73="",1,VLOOKUP($BL73,DADOS!$CR$5:$CS$15,2,FALSE)),4)>0,MAX(1,FLOOR(ROUND(VLOOKUP($BJ73,DADOS!$CL$5:$CM$10,2,FALSE)*IF($BK73="",1,VLOOKUP($BK73,DADOS!$CO$5:$CP$7,2,FALSE))*IF($BL73="",1,VLOOKUP($BL73,DADOS!$CR$5:$CS$15,2,FALSE)),4),1)),0),"")) | BS73: =IF($BP73="","",IFERROR(IF(ROUND(VLOOKUP($BP73,DADOS!$CL$5:$CM$10,2,FALSE)*IF($BQ73="",1,VLOOKUP($BQ73,DADOS!$CO$5:$CP$7,2,FALSE))*IF($BR73="",1,VLOOKUP($BR73,DADOS!$CR$5:$CS$15,2,FALSE)),4)>0,MAX(1,FLOOR(ROUND(VLOOKUP($BP73,DADOS!$CL$5:$CM$10,2,FALSE)*IF($BQ73="",1,VLOOKUP($BQ73,DADOS!$CO$5:$CP$7,2,FALSE))*IF($BR73="",1,VLOOKUP($BR73,DADOS!$CR$5:$CS$15,2,FALSE)),4),1)),0),""))
D74: FALSE | E74: Katana | M74: FALSE | N74: Pistola | V74: FALSE | W74: Cassetete | AE74: FALSE | AF74: Punhal | AM74: FALSE | AN74: Maul | BA74: =IF($AX74="","",IFERROR(IF(ROUND(VLOOKUP($AX74,DADOS!$CL$5:$CM$10,2,FALSE)*IF($AY74="",1,VLOOKUP($AY74,DADOS!$CO$5:$CP$7,2,FALSE))*IF($AZ74="",1,VLOOKUP($AZ74,DADOS!$CR$5:$CS$15,2,FALSE)),4)>0,MAX(1,FLOOR(ROUND(VLOOKUP($AX74,DADOS!$CL$5:$CM$10,2,FALSE)*IF($AY74="",1,VLOOKUP($AY74,DADOS!$CO$5:$CP$7,2,FALSE))*IF($AZ74="",1,VLOOKUP($AZ74,DADOS!$CR$5:$CS$15,2,FALSE)),4),1)),0),"")) | BG74: =IF($BD74="","",IFERROR(IF(ROUND(VLOOKUP($BD74,DADOS!$CL$5:$CM$10,2,FALSE)*IF($BE74="",1,VLOOKUP($BE74,DADOS!$CO$5:$CP$7,2,FALSE))*IF($BF74="",1,VLOOKUP($BF74,DADOS!$CR$5:$CS$15,2,FALSE)),4)>0,MAX(1,FLOOR(ROUND(VLOOKUP($BD74,DADOS!$CL$5:$CM$10,2,FALSE)*IF($BE74="",1,VLOOKUP($BE74,DADOS!$CO$5:$CP$7,2,FALSE))*IF($BF74="",1,VLOOKUP($BF74,DADOS!$CR$5:$CS$15,2,FALSE)),4),1)),0),"")) | BM74: =IF($BJ74="","",IFERROR(IF(ROUND(VLOOKUP($BJ74,DADOS!$CL$5:$CM$10,2,FALSE)*IF($BK74="",1,VLOOKUP($BK74,DADOS!$CO$5:$CP$7,2,FALSE))*IF($BL74="",1,VLOOKUP($BL74,DADOS!$CR$5:$CS$15,2,FALSE)),4)>0,MAX(1,FLOOR(ROUND(VLOOKUP($BJ74,DADOS!$CL$5:$CM$10,2,FALSE)*IF($BK74="",1,VLOOKUP($BK74,DADOS!$CO$5:$CP$7,2,FALSE))*IF($BL74="",1,VLOOKUP($BL74,DADOS!$CR$5:$CS$15,2,FALSE)),4),1)),0),"")) | BS74: =IF($BP74="","",IFERROR(IF(ROUND(VLOOKUP($BP74,DADOS!$CL$5:$CM$10,2,FALSE)*IF($BQ74="",1,VLOOKUP($BQ74,DADOS!$CO$5:$CP$7,2,FALSE))*IF($BR74="",1,VLOOKUP($BR74,DADOS!$CR$5:$CS$15,2,FALSE)),4)>0,MAX(1,FLOOR(ROUND(VLOOKUP($BP74,DADOS!$CL$5:$CM$10,2,FALSE)*IF($BQ74="",1,VLOOKUP($BQ74,DADOS!$CO$5:$CP$7,2,FALSE))*IF($BR74="",1,VLOOKUP($BR74,DADOS!$CR$5:$CS$15,2,FALSE)),4),1)),0),""))
D75: FALSE | E75: Machete | M75: FALSE | N75: Revólver | V75: FALSE | W75: Nunchaku | AE75: FALSE | AF75: Sai | AM75: FALSE | AN75: Maça | BA75: =IF($AX75="","",IFERROR(IF(ROUND(VLOOKUP($AX75,DADOS!$CL$5:$CM$10,2,FALSE)*IF($AY75="",1,VLOOKUP($AY75,DADOS!$CO$5:$CP$7,2,FALSE))*IF($AZ75="",1,VLOOKUP($AZ75,DADOS!$CR$5:$CS$15,2,FALSE)),4)>0,MAX(1,FLOOR(ROUND(VLOOKUP($AX75,DADOS!$CL$5:$CM$10,2,FALSE)*IF($AY75="",1,VLOOKUP($AY75,DADOS!$CO$5:$CP$7,2,FALSE))*IF($AZ75="",1,VLOOKUP($AZ75,DADOS!$CR$5:$CS$15,2,FALSE)),4),1)),0),"")) | BG75: =IF($BD75="","",IFERROR(IF(ROUND(VLOOKUP($BD75,DADOS!$CL$5:$CM$10,2,FALSE)*IF($BE75="",1,VLOOKUP($BE75,DADOS!$CO$5:$CP$7,2,FALSE))*IF($BF75="",1,VLOOKUP($BF75,DADOS!$CR$5:$CS$15,2,FALSE)),4)>0,MAX(1,FLOOR(ROUND(VLOOKUP($BD75,DADOS!$CL$5:$CM$10,2,FALSE)*IF($BE75="",1,VLOOKUP($BE75,DADOS!$CO$5:$CP$7,2,FALSE))*IF($BF75="",1,VLOOKUP($BF75,DADOS!$CR$5:$CS$15,2,FALSE)),4),1)),0),"")) | BM75: =IF($BJ75="","",IFERROR(IF(ROUND(VLOOKUP($BJ75,DADOS!$CL$5:$CM$10,2,FALSE)*IF($BK75="",1,VLOOKUP($BK75,DADOS!$CO$5:$CP$7,2,FALSE))*IF($BL75="",1,VLOOKUP($BL75,DADOS!$CR$5:$CS$15,2,FALSE)),4)>0,MAX(1,FLOOR(ROUND(VLOOKUP($BJ75,DADOS!$CL$5:$CM$10,2,FALSE)*IF($BK75="",1,VLOOKUP($BK75,DADOS!$CO$5:$CP$7,2,FALSE))*IF($BL75="",1,VLOOKUP($BL75,DADOS!$CR$5:$CS$15,2,FALSE)),4),1)),0),"")) | BS75: =IF($BP75="","",IFERROR(IF(ROUND(VLOOKUP($BP75,DADOS!$CL$5:$CM$10,2,FALSE)*IF($BQ75="",1,VLOOKUP($BQ75,DADOS!$CO$5:$CP$7,2,FALSE))*IF($BR75="",1,VLOOKUP($BR75,DADOS!$CR$5:$CS$15,2,FALSE)),4)>0,MAX(1,FLOOR(ROUND(VLOOKUP($BP75,DADOS!$CL$5:$CM$10,2,FALSE)*IF($BQ75="",1,VLOOKUP($BQ75,DADOS!$CO$5:$CP$7,2,FALSE))*IF($BR75="",1,VLOOKUP($BR75,DADOS!$CR$5:$CS$15,2,FALSE)),4),1)),0),""))
D76: FALSE | E76: Nodachi | M76: FALSE | N76: Rifle | V76: FALSE | W76: Tonfa | AE76: FALSE | AF76: Tanto | AM76: FALSE | AN76: Taco | BA76: =IF($AX76="","",IFERROR(IF(ROUND(VLOOKUP($AX76,DADOS!$CL$5:$CM$10,2,FALSE)*IF($AY76="",1,VLOOKUP($AY76,DADOS!$CO$5:$CP$7,2,FALSE))*IF($AZ76="",1,VLOOKUP($AZ76,DADOS!$CR$5:$CS$15,2,FALSE)),4)>0,MAX(1,FLOOR(ROUND(VLOOKUP($AX76,DADOS!$CL$5:$CM$10,2,FALSE)*IF($AY76="",1,VLOOKUP($AY76,DADOS!$CO$5:$CP$7,2,FALSE))*IF($AZ76="",1,VLOOKUP($AZ76,DADOS!$CR$5:$CS$15,2,FALSE)),4),1)),0),"")) | BG76: =IF($BD76="","",IFERROR(IF(ROUND(VLOOKUP($BD76,DADOS!$CL$5:$CM$10,2,FALSE)*IF($BE76="",1,VLOOKUP($BE76,DADOS!$CO$5:$CP$7,2,FALSE))*IF($BF76="",1,VLOOKUP($BF76,DADOS!$CR$5:$CS$15,2,FALSE)),4)>0,MAX(1,FLOOR(ROUND(VLOOKUP($BD76,DADOS!$CL$5:$CM$10,2,FALSE)*IF($BE76="",1,VLOOKUP($BE76,DADOS!$CO$5:$CP$7,2,FALSE))*IF($BF76="",1,VLOOKUP($BF76,DADOS!$CR$5:$CS$15,2,FALSE)),4),1)),0),"")) | BM76: =IF($BJ76="","",IFERROR(IF(ROUND(VLOOKUP($BJ76,DADOS!$CL$5:$CM$10,2,FALSE)*IF($BK76="",1,VLOOKUP($BK76,DADOS!$CO$5:$CP$7,2,FALSE))*IF($BL76="",1,VLOOKUP($BL76,DADOS!$CR$5:$CS$15,2,FALSE)),4)>0,MAX(1,FLOOR(ROUND(VLOOKUP($BJ76,DADOS!$CL$5:$CM$10,2,FALSE)*IF($BK76="",1,VLOOKUP($BK76,DADOS!$CO$5:$CP$7,2,FALSE))*IF($BL76="",1,VLOOKUP($BL76,DADOS!$CR$5:$CS$15,2,FALSE)),4),1)),0),"")) | BS76: =IF($BP76="","",IFERROR(IF(ROUND(VLOOKUP($BP76,DADOS!$CL$5:$CM$10,2,FALSE)*IF($BQ76="",1,VLOOKUP($BQ76,DADOS!$CO$5:$CP$7,2,FALSE))*IF($BR76="",1,VLOOKUP($BR76,DADOS!$CR$5:$CS$15,2,FALSE)),4)>0,MAX(1,FLOOR(ROUND(VLOOKUP($BP76,DADOS!$CL$5:$CM$10,2,FALSE)*IF($BQ76="",1,VLOOKUP($BQ76,DADOS!$CO$5:$CP$7,2,FALSE))*IF($BR76="",1,VLOOKUP($BR76,DADOS!$CR$5:$CS$15,2,FALSE)),4),1)),0),""))
D77: FALSE | E77: Odachi | M77: FALSE | N77: Rifle de Precisão | V77: FALSE | W77: CEIFA | AE77: FALSE | AF77: FLEXÍVEL | AM77: FALSE | AN77: ARMAS LONGAS | BA77: =IF($AX77="","",IFERROR(IF(ROUND(VLOOKUP($AX77,DADOS!$CL$5:$CM$10,2,FALSE)*IF($AY77="",1,VLOOKUP($AY77,DADOS!$CO$5:$CP$7,2,FALSE))*IF($AZ77="",1,VLOOKUP($AZ77,DADOS!$CR$5:$CS$15,2,FALSE)),4)>0,MAX(1,FLOOR(ROUND(VLOOKUP($AX77,DADOS!$CL$5:$CM$10,2,FALSE)*IF($AY77="",1,VLOOKUP($AY77,DADOS!$CO$5:$CP$7,2,FALSE))*IF($AZ77="",1,VLOOKUP($AZ77,DADOS!$CR$5:$CS$15,2,FALSE)),4),1)),0),"")) | BG77: =IF($BD77="","",IFERROR(IF(ROUND(VLOOKUP($BD77,DADOS!$CL$5:$CM$10,2,FALSE)*IF($BE77="",1,VLOOKUP($BE77,DADOS!$CO$5:$CP$7,2,FALSE))*IF($BF77="",1,VLOOKUP($BF77,DADOS!$CR$5:$CS$15,2,FALSE)),4)>0,MAX(1,FLOOR(ROUND(VLOOKUP($BD77,DADOS!$CL$5:$CM$10,2,FALSE)*IF($BE77="",1,VLOOKUP($BE77,DADOS!$CO$5:$CP$7,2,FALSE))*IF($BF77="",1,VLOOKUP($BF77,DADOS!$CR$5:$CS$15,2,FALSE)),4),1)),0),"")) | BM77: =IF($BJ77="","",IFERROR(IF(ROUND(VLOOKUP($BJ77,DADOS!$CL$5:$CM$10,2,FALSE)*IF($BK77="",1,VLOOKUP($BK77,DADOS!$CO$5:$CP$7,2,FALSE))*IF($BL77="",1,VLOOKUP($BL77,DADOS!$CR$5:$CS$15,2,FALSE)),4)>0,MAX(1,FLOOR(ROUND(VLOOKUP($BJ77,DADOS!$CL$5:$CM$10,2,FALSE)*IF($BK77="",1,VLOOKUP($BK77,DADOS!$CO$5:$CP$7,2,FALSE))*IF($BL77="",1,VLOOKUP($BL77,DADOS!$CR$5:$CS$15,2,FALSE)),4),1)),0),"")) | BS77: =IF($BP77="","",IFERROR(IF(ROUND(VLOOKUP($BP77,DADOS!$CL$5:$CM$10,2,FALSE)*IF($BQ77="",1,VLOOKUP($BQ77,DADOS!$CO$5:$CP$7,2,FALSE))*IF($BR77="",1,VLOOKUP($BR77,DADOS!$CR$5:$CS$15,2,FALSE)),4)>0,MAX(1,FLOOR(ROUND(VLOOKUP($BP77,DADOS!$CL$5:$CM$10,2,FALSE)*IF($BQ77="",1,VLOOKUP($BQ77,DADOS!$CO$5:$CP$7,2,FALSE))*IF($BR77="",1,VLOOKUP($BR77,DADOS!$CR$5:$CS$15,2,FALSE)),4),1)),0),""))
D78: FALSE | E78: Rapieira | M78: FALSE | N78: Submetralhadora | V78: FALSE | W78: Foice | AE78: FALSE | AF78: Chicote | AM78: FALSE | AN78: Lança | BA78: =IF($AX78="","",IFERROR(IF(ROUND(VLOOKUP($AX78,DADOS!$CL$5:$CM$10,2,FALSE)*IF($AY78="",1,VLOOKUP($AY78,DADOS!$CO$5:$CP$7,2,FALSE))*IF($AZ78="",1,VLOOKUP($AZ78,DADOS!$CR$5:$CS$15,2,FALSE)),4)>0,MAX(1,FLOOR(ROUND(VLOOKUP($AX78,DADOS!$CL$5:$CM$10,2,FALSE)*IF($AY78="",1,VLOOKUP($AY78,DADOS!$CO$5:$CP$7,2,FALSE))*IF($AZ78="",1,VLOOKUP($AZ78,DADOS!$CR$5:$CS$15,2,FALSE)),4),1)),0),"")) | BG78: =IF($BD78="","",IFERROR(IF(ROUND(VLOOKUP($BD78,DADOS!$CL$5:$CM$10,2,FALSE)*IF($BE78="",1,VLOOKUP($BE78,DADOS!$CO$5:$CP$7,2,FALSE))*IF($BF78="",1,VLOOKUP($BF78,DADOS!$CR$5:$CS$15,2,FALSE)),4)>0,MAX(1,FLOOR(ROUND(VLOOKUP($BD78,DADOS!$CL$5:$CM$10,2,FALSE)*IF($BE78="",1,VLOOKUP($BE78,DADOS!$CO$5:$CP$7,2,FALSE))*IF($BF78="",1,VLOOKUP($BF78,DADOS!$CR$5:$CS$15,2,FALSE)),4),1)),0),"")) | BM78: =IF($BJ78="","",IFERROR(IF(ROUND(VLOOKUP($BJ78,DADOS!$CL$5:$CM$10,2,FALSE)*IF($BK78="",1,VLOOKUP($BK78,DADOS!$CO$5:$CP$7,2,FALSE))*IF($BL78="",1,VLOOKUP($BL78,DADOS!$CR$5:$CS$15,2,FALSE)),4)>0,MAX(1,FLOOR(ROUND(VLOOKUP($BJ78,DADOS!$CL$5:$CM$10,2,FALSE)*IF($BK78="",1,VLOOKUP($BK78,DADOS!$CO$5:$CP$7,2,FALSE))*IF($BL78="",1,VLOOKUP($BL78,DADOS!$CR$5:$CS$15,2,FALSE)),4),1)),0),"")) | BS78: =IF($BP78="","",IFERROR(IF(ROUND(VLOOKUP($BP78,DADOS!$CL$5:$CM$10,2,FALSE)*IF($BQ78="",1,VLOOKUP($BQ78,DADOS!$CO$5:$CP$7,2,FALSE))*IF($BR78="",1,VLOOKUP($BR78,DADOS!$CR$5:$CS$15,2,FALSE)),4)>0,MAX(1,FLOOR(ROUND(VLOOKUP($BP78,DADOS!$CL$5:$CM$10,2,FALSE)*IF($BQ78="",1,VLOOKUP($BQ78,DADOS!$CO$5:$CP$7,2,FALSE))*IF($BR78="",1,VLOOKUP($BR78,DADOS!$CR$5:$CS$15,2,FALSE)),4),1)),0),""))
D79: FALSE | E79: Wakizashi | M79: FALSE | N79: ARREMESSO | V79: FALSE | W79: Kama | AE79: FALSE | AF79: Corrente | AM79: FALSE | AN79: Naginata | BA79: =IF($AX79="","",IFERROR(IF(ROUND(VLOOKUP($AX79,DADOS!$CL$5:$CM$10,2,FALSE)*IF($AY79="",1,VLOOKUP($AY79,DADOS!$CO$5:$CP$7,2,FALSE))*IF($AZ79="",1,VLOOKUP($AZ79,DADOS!$CR$5:$CS$15,2,FALSE)),4)>0,MAX(1,FLOOR(ROUND(VLOOKUP($AX79,DADOS!$CL$5:$CM$10,2,FALSE)*IF($AY79="",1,VLOOKUP($AY79,DADOS!$CO$5:$CP$7,2,FALSE))*IF($AZ79="",1,VLOOKUP($AZ79,DADOS!$CR$5:$CS$15,2,FALSE)),4),1)),0),"")) | BG79: =IF($BD79="","",IFERROR(IF(ROUND(VLOOKUP($BD79,DADOS!$CL$5:$CM$10,2,FALSE)*IF($BE79="",1,VLOOKUP($BE79,DADOS!$CO$5:$CP$7,2,FALSE))*IF($BF79="",1,VLOOKUP($BF79,DADOS!$CR$5:$CS$15,2,FALSE)),4)>0,MAX(1,FLOOR(ROUND(VLOOKUP($BD79,DADOS!$CL$5:$CM$10,2,FALSE)*IF($BE79="",1,VLOOKUP($BE79,DADOS!$CO$5:$CP$7,2,FALSE))*IF($BF79="",1,VLOOKUP($BF79,DADOS!$CR$5:$CS$15,2,FALSE)),4),1)),0),"")) | BM79: =IF($BJ79="","",IFERROR(IF(ROUND(VLOOKUP($BJ79,DADOS!$CL$5:$CM$10,2,FALSE)*IF($BK79="",1,VLOOKUP($BK79,DADOS!$CO$5:$CP$7,2,FALSE))*IF($BL79="",1,VLOOKUP($BL79,DADOS!$CR$5:$CS$15,2,FALSE)),4)>0,MAX(1,FLOOR(ROUND(VLOOKUP($BJ79,DADOS!$CL$5:$CM$10,2,FALSE)*IF($BK79="",1,VLOOKUP($BK79,DADOS!$CO$5:$CP$7,2,FALSE))*IF($BL79="",1,VLOOKUP($BL79,DADOS!$CR$5:$CS$15,2,FALSE)),4),1)),0),"")) | BS79: =IF($BP79="","",IFERROR(IF(ROUND(VLOOKUP($BP79,DADOS!$CL$5:$CM$10,2,FALSE)*IF($BQ79="",1,VLOOKUP($BQ79,DADOS!$CO$5:$CP$7,2,FALSE))*IF($BR79="",1,VLOOKUP($BR79,DADOS!$CR$5:$CS$15,2,FALSE)),4)>0,MAX(1,FLOOR(ROUND(VLOOKUP($BP79,DADOS!$CL$5:$CM$10,2,FALSE)*IF($BQ79="",1,VLOOKUP($BQ79,DADOS!$CO$5:$CP$7,2,FALSE))*IF($BR79="",1,VLOOKUP($BR79,DADOS!$CR$5:$CS$15,2,FALSE)),4),1)),0),""))
D80: FALSE | E80: MACHADO | M80: FALSE | N80: Chakram | V80: FALSE | W80: Kusarigama | AE80: FALSE | AF80: Manriki | AM80: FALSE | AN80: Yari | BA80: =IF($AX80="","",IFERROR(IF(ROUND(VLOOKUP($AX80,DADOS!$CL$5:$CM$10,2,FALSE)*IF($AY80="",1,VLOOKUP($AY80,DADOS!$CO$5:$CP$7,2,FALSE))*IF($AZ80="",1,VLOOKUP($AZ80,DADOS!$CR$5:$CS$15,2,FALSE)),4)>0,MAX(1,FLOOR(ROUND(VLOOKUP($AX80,DADOS!$CL$5:$CM$10,2,FALSE)*IF($AY80="",1,VLOOKUP($AY80,DADOS!$CO$5:$CP$7,2,FALSE))*IF($AZ80="",1,VLOOKUP($AZ80,DADOS!$CR$5:$CS$15,2,FALSE)),4),1)),0),"")) | BG80: =IF($BD80="","",IFERROR(IF(ROUND(VLOOKUP($BD80,DADOS!$CL$5:$CM$10,2,FALSE)*IF($BE80="",1,VLOOKUP($BE80,DADOS!$CO$5:$CP$7,2,FALSE))*IF($BF80="",1,VLOOKUP($BF80,DADOS!$CR$5:$CS$15,2,FALSE)),4)>0,MAX(1,FLOOR(ROUND(VLOOKUP($BD80,DADOS!$CL$5:$CM$10,2,FALSE)*IF($BE80="",1,VLOOKUP($BE80,DADOS!$CO$5:$CP$7,2,FALSE))*IF($BF80="",1,VLOOKUP($BF80,DADOS!$CR$5:$CS$15,2,FALSE)),4),1)),0),"")) | BM80: =IF($BJ80="","",IFERROR(IF(ROUND(VLOOKUP($BJ80,DADOS!$CL$5:$CM$10,2,FALSE)*IF($BK80="",1,VLOOKUP($BK80,DADOS!$CO$5:$CP$7,2,FALSE))*IF($BL80="",1,VLOOKUP($BL80,DADOS!$CR$5:$CS$15,2,FALSE)),4)>0,MAX(1,FLOOR(ROUND(VLOOKUP($BJ80,DADOS!$CL$5:$CM$10,2,FALSE)*IF($BK80="",1,VLOOKUP($BK80,DADOS!$CO$5:$CP$7,2,FALSE))*IF($BL80="",1,VLOOKUP($BL80,DADOS!$CR$5:$CS$15,2,FALSE)),4),1)),0),"")) | BS80: =IF($BP80="","",IFERROR(IF(ROUND(VLOOKUP($BP80,DADOS!$CL$5:$CM$10,2,FALSE)*IF($BQ80="",1,VLOOKUP($BQ80,DADOS!$CO$5:$CP$7,2,FALSE))*IF($BR80="",1,VLOOKUP($BR80,DADOS!$CR$5:$CS$15,2,FALSE)),4)>0,MAX(1,FLOOR(ROUND(VLOOKUP($BP80,DADOS!$CL$5:$CM$10,2,FALSE)*IF($BQ80="",1,VLOOKUP($BQ80,DADOS!$CO$5:$CP$7,2,FALSE))*IF($BR80="",1,VLOOKUP($BR80,DADOS!$CR$5:$CS$15,2,FALSE)),4),1)),0),""))
D81: FALSE | E81: Machadinha | M81: FALSE | N81: Kunai | V81: FALSE | W81: BALESTRA | AE81: FALSE | AF81: MANOPLA | AM81: FALSE | AN81: YUMI | BA81: =IF($AX81="","",IFERROR(IF(ROUND(VLOOKUP($AX81,DADOS!$CL$5:$CM$10,2,FALSE)*IF($AY81="",1,VLOOKUP($AY81,DADOS!$CO$5:$CP$7,2,FALSE))*IF($AZ81="",1,VLOOKUP($AZ81,DADOS!$CR$5:$CS$15,2,FALSE)),4)>0,MAX(1,FLOOR(ROUND(VLOOKUP($AX81,DADOS!$CL$5:$CM$10,2,FALSE)*IF($AY81="",1,VLOOKUP($AY81,DADOS!$CO$5:$CP$7,2,FALSE))*IF($AZ81="",1,VLOOKUP($AZ81,DADOS!$CR$5:$CS$15,2,FALSE)),4),1)),0),"")) | BG81: =IF($BD81="","",IFERROR(IF(ROUND(VLOOKUP($BD81,DADOS!$CL$5:$CM$10,2,FALSE)*IF($BE81="",1,VLOOKUP($BE81,DADOS!$CO$5:$CP$7,2,FALSE))*IF($BF81="",1,VLOOKUP($BF81,DADOS!$CR$5:$CS$15,2,FALSE)),4)>0,MAX(1,FLOOR(ROUND(VLOOKUP($BD81,DADOS!$CL$5:$CM$10,2,FALSE)*IF($BE81="",1,VLOOKUP($BE81,DADOS!$CO$5:$CP$7,2,FALSE))*IF($BF81="",1,VLOOKUP($BF81,DADOS!$CR$5:$CS$15,2,FALSE)),4),1)),0),"")) | BM81: =IF($BJ81="","",IFERROR(IF(ROUND(VLOOKUP($BJ81,DADOS!$CL$5:$CM$10,2,FALSE)*IF($BK81="",1,VLOOKUP($BK81,DADOS!$CO$5:$CP$7,2,FALSE))*IF($BL81="",1,VLOOKUP($BL81,DADOS!$CR$5:$CS$15,2,FALSE)),4)>0,MAX(1,FLOOR(ROUND(VLOOKUP($BJ81,DADOS!$CL$5:$CM$10,2,FALSE)*IF($BK81="",1,VLOOKUP($BK81,DADOS!$CO$5:$CP$7,2,FALSE))*IF($BL81="",1,VLOOKUP($BL81,DADOS!$CR$5:$CS$15,2,FALSE)),4),1)),0),"")) | BS81: =IF($BP81="","",IFERROR(IF(ROUND(VLOOKUP($BP81,DADOS!$CL$5:$CM$10,2,FALSE)*IF($BQ81="",1,VLOOKUP($BQ81,DADOS!$CO$5:$CP$7,2,FALSE))*IF($BR81="",1,VLOOKUP($BR81,DADOS!$CR$5:$CS$15,2,FALSE)),4)>0,MAX(1,FLOOR(ROUND(VLOOKUP($BP81,DADOS!$CL$5:$CM$10,2,FALSE)*IF($BQ81="",1,VLOOKUP($BQ81,DADOS!$CO$5:$CP$7,2,FALSE))*IF($BR81="",1,VLOOKUP($BR81,DADOS!$CR$5:$CS$15,2,FALSE)),4),1)),0),""))
D82: FALSE | E82: Machado | M82: FALSE | N82: Shuriken | V82: FALSE | W82: Besta | AE82: FALSE | AF82: Soqueira | AM82: FALSE | AN82: Daikyū | BA82: =IF($AX82="","",IFERROR(IF(ROUND(VLOOKUP($AX82,DADOS!$CL$5:$CM$10,2,FALSE)*IF($AY82="",1,VLOOKUP($AY82,DADOS!$CO$5:$CP$7,2,FALSE))*IF($AZ82="",1,VLOOKUP($AZ82,DADOS!$CR$5:$CS$15,2,FALSE)),4)>0,MAX(1,FLOOR(ROUND(VLOOKUP($AX82,DADOS!$CL$5:$CM$10,2,FALSE)*IF($AY82="",1,VLOOKUP($AY82,DADOS!$CO$5:$CP$7,2,FALSE))*IF($AZ82="",1,VLOOKUP($AZ82,DADOS!$CR$5:$CS$15,2,FALSE)),4),1)),0),"")) | BG82: =IF($BD82="","",IFERROR(IF(ROUND(VLOOKUP($BD82,DADOS!$CL$5:$CM$10,2,FALSE)*IF($BE82="",1,VLOOKUP($BE82,DADOS!$CO$5:$CP$7,2,FALSE))*IF($BF82="",1,VLOOKUP($BF82,DADOS!$CR$5:$CS$15,2,FALSE)),4)>0,MAX(1,FLOOR(ROUND(VLOOKUP($BD82,DADOS!$CL$5:$CM$10,2,FALSE)*IF($BE82="",1,VLOOKUP($BE82,DADOS!$CO$5:$CP$7,2,FALSE))*IF($BF82="",1,VLOOKUP($BF82,DADOS!$CR$5:$CS$15,2,FALSE)),4),1)),0),"")) | BM82: =IF($BJ82="","",IFERROR(IF(ROUND(VLOOKUP($BJ82,DADOS!$CL$5:$CM$10,2,FALSE)*IF($BK82="",1,VLOOKUP($BK82,DADOS!$CO$5:$CP$7,2,FALSE))*IF($BL82="",1,VLOOKUP($BL82,DADOS!$CR$5:$CS$15,2,FALSE)),4)>0,MAX(1,FLOOR(ROUND(VLOOKUP($BJ82,DADOS!$CL$5:$CM$10,2,FALSE)*IF($BK82="",1,VLOOKUP($BK82,DADOS!$CO$5:$CP$7,2,FALSE))*IF($BL82="",1,VLOOKUP($BL82,DADOS!$CR$5:$CS$15,2,FALSE)),4),1)),0),"")) | BS82: =IF($BP82="","",IFERROR(IF(ROUND(VLOOKUP($BP82,DADOS!$CL$5:$CM$10,2,FALSE)*IF($BQ82="",1,VLOOKUP($BQ82,DADOS!$CO$5:$CP$7,2,FALSE))*IF($BR82="",1,VLOOKUP($BR82,DADOS!$CR$5:$CS$15,2,FALSE)),4)>0,MAX(1,FLOOR(ROUND(VLOOKUP($BP82,DADOS!$CL$5:$CM$10,2,FALSE)*IF($BQ82="",1,VLOOKUP($BQ82,DADOS!$CO$5:$CP$7,2,FALSE))*IF($BR82="",1,VLOOKUP($BR82,DADOS!$CR$5:$CS$15,2,FALSE)),4),1)),0),""))
D83: FALSE | E83: Machado de Guerra | M83: FALSE | N83: Tessen | V83: FALSE | W83: Besta de Uma Mão | AE83: FALSE | AF83: Tekko | AM83: FALSE | AN83: Hankyū | BA83: =IF($AX83="","",IFERROR(IF(ROUND(VLOOKUP($AX83,DADOS!$CL$5:$CM$10,2,FALSE)*IF($AY83="",1,VLOOKUP($AY83,DADOS!$CO$5:$CP$7,2,FALSE))*IF($AZ83="",1,VLOOKUP($AZ83,DADOS!$CR$5:$CS$15,2,FALSE)),4)>0,MAX(1,FLOOR(ROUND(VLOOKUP($AX83,DADOS!$CL$5:$CM$10,2,FALSE)*IF($AY83="",1,VLOOKUP($AY83,DADOS!$CO$5:$CP$7,2,FALSE))*IF($AZ83="",1,VLOOKUP($AZ83,DADOS!$CR$5:$CS$15,2,FALSE)),4),1)),0),"")) | BG83: =IF($BD83="","",IFERROR(IF(ROUND(VLOOKUP($BD83,DADOS!$CL$5:$CM$10,2,FALSE)*IF($BE83="",1,VLOOKUP($BE83,DADOS!$CO$5:$CP$7,2,FALSE))*IF($BF83="",1,VLOOKUP($BF83,DADOS!$CR$5:$CS$15,2,FALSE)),4)>0,MAX(1,FLOOR(ROUND(VLOOKUP($BD83,DADOS!$CL$5:$CM$10,2,FALSE)*IF($BE83="",1,VLOOKUP($BE83,DADOS!$CO$5:$CP$7,2,FALSE))*IF($BF83="",1,VLOOKUP($BF83,DADOS!$CR$5:$CS$15,2,FALSE)),4),1)),0),"")) | BM83: =IF($BJ83="","",IFERROR(IF(ROUND(VLOOKUP($BJ83,DADOS!$CL$5:$CM$10,2,FALSE)*IF($BK83="",1,VLOOKUP($BK83,DADOS!$CO$5:$CP$7,2,FALSE))*IF($BL83="",1,VLOOKUP($BL83,DADOS!$CR$5:$CS$15,2,FALSE)),4)>0,MAX(1,FLOOR(ROUND(VLOOKUP($BJ83,DADOS!$CL$5:$CM$10,2,FALSE)*IF($BK83="",1,VLOOKUP($BK83,DADOS!$CO$5:$CP$7,2,FALSE))*IF($BL83="",1,VLOOKUP($BL83,DADOS!$CR$5:$CS$15,2,FALSE)),4),1)),0),"")) | BS83: =IF($BP83="","",IFERROR(IF(ROUND(VLOOKUP($BP83,DADOS!$CL$5:$CM$10,2,FALSE)*IF($BQ83="",1,VLOOKUP($BQ83,DADOS!$CO$5:$CP$7,2,FALSE))*IF($BR83="",1,VLOOKUP($BR83,DADOS!$CR$5:$CS$15,2,FALSE)),4)>0,MAX(1,FLOOR(ROUND(VLOOKUP($BP83,DADOS!$CL$5:$CM$10,2,FALSE)*IF($BQ83="",1,VLOOKUP($BQ83,DADOS!$CO$5:$CP$7,2,FALSE))*IF($BR83="",1,VLOOKUP($BR83,DADOS!$CR$5:$CS$15,2,FALSE)),4),1)),0),""))
